Workbook

Sheet Critérios
A1: Base cruzada — Mosaico Card: Cinema & Séries
A2: Versão final de 13/10/2026 · recorte: a partir de 2001 · público-alvo 15–25 anos · REGRA DA BASE: fica o título que aparece em pelo menos 3 bases OU tem selo Geração Z, mais 21 títulos resgatados manualmente (marcados em Observações/Conferir). Os demais estão na aba Excluídos.
A4: PARÂMETROS (células amarelas; a planilha recalcula ao alterar)
A5: Bônus por selo (somado ao índice, por selo presente) | B5: 0.03
A6: Corte: sai quem fica abaixo deste percentil do índice (1/3 = terço inferior) | B6: 0.33333333
A7: Corte da faixa A (índice ≥) | B7: 0.7
A8: Corte da faixa B (índice ≥) | B8: 0.4
A9: Tamanho da seleção Sucessos (por formato) | B9: 50
A11: ÍNDICE DOS FILMES
A12: Métricas (pesos iguais): percentil do público no Brasil, percentil da bilheteria mundial e percentil dos votos no IMDb. O índice é a MÉDIA das métricas que o título tem (quem não tem uma métrica não é penalizado por ela).
A13: Selos (somam o bônus acima, cada um): Letterboxd (populares/mais bem avaliados do ano ou de todos os tempos), JustWatch Brasil (populares hoje), Nielsen (tops anuais de streaming de filmes), Whip Media (top 10 semanal), Geração Z (YPulse/UCLA/Morning Consult), Parrot Analytics (alta demanda no Brasil).
A14: ÍNDICE DAS SÉRIES
A15: Métricas (pesos iguais): percentil dos votos no IMDb e "audiência oficial" = a melhor pontuação entre: Netflix Top 10 histórico (1 − (posição−1)/20), ranking Nielsen (1 − (posição−1)/(2 × tamanho da lista); TV aberta 2001–2020 com lista de 40, streaming 2020–2025 com lista de 30) e média de audiência por temporada (0,5 + 0,5 × percentil). Estar num ranking oficial já vale de 0,5 a 1.
A16: Nº de bases: cada fonte em que o título aparece conta 1 (filmes: público BR, bilheteria mundial, IMDb, Letterboxd, JustWatch, Nielsen, Whip, Geração Z, Parrot; séries: IMDb, audiência oficial coletada, Nielsen, Geração Z, Parrot, Whip, JustWatch).
A17: Selos (bônus): Geração Z, Parrot Analytics (Brasil), Whip Media, JustWatch Brasil. A Nielsen entra como métrica, não como selo, para não contar duas vezes.
A19: FAIXAS
A20: Percentis, índice e faixas são recalculados só entre os títulos da base final. Faixa A ≥ corte A; B ≥ corte B; C abaixo. A coluna informativa de terço inferior não exclui nada: "Sairia — terço inferior" se o índice estiver abaixo do percentil definido acima, calculado separadamente para filmes e para séries; "Sairia — sem métrica" se o título não tiver nenhuma métrica.
A22: ORIGEM DOS TÍTULOS
A23: Bilheteria (Ancine/Wikipédia): base original de filmes. Audiência oficial (coleta) / Curadoria: base original de séries. "Adicionado por: …": título que não estava na base e entrou porque apareceu numa das novas fontes (Letterboxd, JustWatch, Nielsen, Whip, Parrot, Geração Z), sempre lançado de 2001 em diante e excluídos realities, esportes, noticiários e programas de auditório.
A25: CUIDADOS
... A37: Status (amarelo): candidato → selecionado → em escrita → aprovado, ou excluído. Filtre por "Corte (prévia)" para revisar quem sairia antes de excluir.

Sheet Resumo
A1: Resumo da base final
A3: FILMES
A4: Total | B4: =COUNTA(Filmes!A2:A354) -> 353
A5: Faixa A | B5: =COUNTIF(Filmes!Y2:Y354,"A") -> 71
A6: Faixa B | B6: =COUNTIF(Filmes!Y2:Y354,"B") -> 163
A7: Faixa C | B7: =COUNTIF(Filmes!Y2:Y354,"C") -> 119
A8: Nacionais | B8: =COUNTIF(Filmes!E2:E354,"Sim") -> 7
A9: Com 3 métricas | B9: =COUNTIF(Filmes!P2:P354,3) -> 230
A10: Com ao menos 1 selo | B10: =COUNTIF(Filmes!W2:W354,">0") -> 197
A11: Adicionados pelas novas fontes | B11: =COUNTIF(Filmes!F2:F354,"Adicionado*") -> 39
A12: SÉRIES
A13: Total | B13: =COUNTA(Séries!A2:A85) -> 84
A14: Faixa A | B14: =COUNTIF(Séries!AB2:AB85,"A") -> 39
A15: Faixa B | B15: =COUNTIF(Séries!AB2:AB85,"B") -> 32
A16: Faixa C | B16: =COUNTIF(Séries!AB2:AB85,"C") -> 13
A17: Com audiência oficial | B17: =COUNT(Séries!T2:T85) -> 55
A18: Com ao menos 1 selo | B18: =COUNTIF(Séries!Z2:Z85,">0") -> 75
A19: Adicionadas pelas novas fontes | B19: =COUNTIF(Séries!F2:F85,"Adicionado*") -> 26
A20: TOTAL NA BASE FINAL | B20: =B4+B13 -> 437
A21: Excluídos (aba Excluídos) | B21: =COUNTA(Excluídos!A2:A1428) -> 1427
A22: Mantidos só pelo selo Geração Z (filmes/séries) | B22: 0 / 7
A23: Seleção Sucessos — filmes | B23: =COUNTIF(Filmes!AJ2:AJ354,"Sim") -> 50
A24: Seleção Sucessos — séries | B24: =COUNTIF(Séries!AN2:AN85,"Sim") -> 50
A25: Resgatados manualmente (filmes/séries) | B25: 11 / 10

Sheet Filmes
A1: ID | B1: Título no Brasil | C1: Título original | D1: Ano | E1: Nacional | F1: Origem na base | G1: Público no Brasil | H1: Renda no Brasil (R$) | I1: Bilheteria mundial (US$) | J1: Posição mundial no ano | K1: Votos no IMDb | L1: Nota IMDb | M1: Percentil público BR | N1: Percentil bilheteria mundial | O1: Percentil votos IMDb | P1: Nº de métricas | Q1: Selo Letterboxd | R1: Selo JustWatch BR | S1: Selo Nielsen | T1: Selo Whip Media | U1: Selo Geração Z | V1: Selo Parrot BR | W1: Nº de selos | X1: Índice | Y1: Faixa | Z1: Posição | AA1: Terço inferior da base final (informativo) | AB1: Protagonista (preliminar) | AC1: Observações | AD1: Status | AE1: Notas editoriais | AF1: Fontes | AG1: IMDb ID | AH1: Nº de bases em que aparece | AI1: Presente em ≥3 bases | AJ1: Seleção Sucessos
A2: F0001 | B2: Vingadores: Ultimato | C2: Avengers: Endgame | D2: 2019 | E2: Não | F2: Bilheteria (Ancine/Wikipédia) | G2: 19656475 | H2: 338624955 | I2: 2799439100 | J2: 1 | K2: 1499173 | L2: 8.4 | M2: =IF(G2="","",PERCENTRANK($G$2:$G$354,G2)) -> 0.997 | N2: =IF(I2="","",PERCENTRANK($I$2:$I$354,I2)) -> 1 | O2: =IF(K2="","",PERCENTRANK($K$2:$K$354,K2)) -> 0.966 | P2: =COUNT(M2:O2) -> 3 | Q2: 2019 populares #1 | W2: =COUNTA(Q2:V2) -> 1 | X2: =IF(P2=0,"",MIN(1,AVERAGE(M2:O2)+Critérios!$B$5*W2)) -> 1 | Y2: =IF(X2="","",IF(X2>=Critérios!$B$7,"A",IF(X2>=Critérios!$B$8,"B","C"))) -> A | Z2: =IF(X2="","",RANK(X2,$X$2:$X$354)) -> 1 | AA2: =IF(X2="","Sairia — sem métrica",IF(PERCENTRANK($X$2:$X$354,X2)<Critérios!$B$6,"Sairia — terço inferior","Fica")) -> Fica | AB2: ambíguo (provável) — conferir | AD2: candidato | AF2: S052, S192, S201, S208 | AG2: tt4154796 | AH2: =COUNT(G2,I2,K2)+COUNTA(Q2:V2) -> 4 | AI2: =IF(AH2>=3,"Sim","Não") -> Sim | AJ2: =IF(AND(Z2<>"",Z2<=Critérios!$B$9),"Sim","Não") -> Sim
A3: F0002 | B3: Homem-Aranha: Sem Volta para Casa | C3: Spider-Man: No Way Home | D3: 2021 | E3: Não | F3: Bilheteria (Ancine/Wikipédia) | G3: 16614010 | H3: 307392631 | I3: 1921426073 | J3: 1 | K3: 1081111 | L3: 8.1 | M3: =IF(G3="","",PERCENTRANK($G$2:$G$354,G3)) -> 0.99 | N3: =IF(I3="","",PERCENTRANK($I$2:$I$354,I3)) -> 0.97 | O3: =IF(K3="","",PERCENTRANK($K$2:$K$354,K3)) -> 0.912 | P3: =COUNT(M3:O3) -> 3 | Q3: 2021 populares #2; 2021 mais bem avaliados #1 | R3: #43 hoje | T3: 15–17 jul 2022 #9 (United States); 22–24 jul 2022 #8 (United States) | W3: =COUNTA(Q3:V3) -> 3 | X3: =IF(P3=0,"",MIN(1,AVERAGE(M3:O3)+Critérios!$B$5*W3)) -> 1 | Y3: =IF(X3="","",IF(X3>=Critérios!$B$7,"A",IF(X3>=Critérios!$B$8,"B","C"))) -> A | Z3: =IF(X3="","",RANK(X3,$X$2:$X$354)) -> 1 | AA3: =IF(X3="","Sairia — sem métrica",IF(PERCENTRANK($X$2:$X$354,X3)<Critérios!$B$6,"Sairia — terço inferior","Fica")) -> Fica | AB3: a avaliar | AD3: candidato | AF3: S054, S192, S199, S200, S201 | AG3: tt10872600 | AH3: =COUNT(G3,I3,K3)+COUNTA(Q3:V3) -> 6 | AI3: =IF(AH3>=3,"Sim","Não") -> Sim | AJ3: =IF(AND(Z3<>"",Z3<=Critérios!$B$9),"Sim","Não") -> Sim
A4: F0003 | B4: Vingadores: Guerra Infinita | C4: Avengers: Infinity War | D4: 2018 | E4: Não | F4: Bilheteria (Ancine/Wikipédia) | G4: 14502151 | H4: 238029913 | I4: 2048359754 | J4: 1 | K4: 1417008 | L4: 8.4 | M4: =IF(G4="","",PERCENTRANK($G$2:$G$354,G4)) -> 0.984 | N4: =IF(I4="","",PERCENTRANK($I$2:$I$354,I4)) -> 0.975 | O4: =IF(K4="","",PERCENTRANK($K$2:$K$354,K4)) -> 0.963 | P4: =COUNT(M4:O4) -> 3 | Q4: 2018 populares #2; 2018 mais bem avaliados #13 | W4: =COUNTA(Q4:V4) -> 1 | X4: =IF(P4=0,"",MIN(1,AVERAGE(M4:O4)+Critérios!$B$5*W4)) -> 1 | Y4: =IF(X4="","",IF(X4>=Critérios!$B$7,"A",IF(X4>=Critérios!$B$8,"B","C"))) -> A | Z4: =IF(X4="","",RANK(X4,$X$2:$X$354)) -> 1 | AA4: =IF(X4="","Sairia — sem métrica",IF(PERCENTRANK($X$2:$X$354,X4)<Critérios!$B$6,"Sairia — terço inferior","Fica")) -> Fica | AB4: ambíguo (provável) — conferir | AD4: candidato | AF4: S051, S191, S192, S201 | AG4: tt4154756 | AH4: =COUNT(G4,I4,K4)+COUNTA(Q4:V4) -> 4 | AI4: =IF(AH4>=3,"Sim","Não") -> Sim | AJ4: =IF(AND(Z4<>"",Z4<=Critérios!$B$9),"Sim","Não") -> Sim
A5: F0004 | B5: Avatar: O Caminho da Água | C5: Avatar: The Way of Water | D5: 2022 | E5: Não | F5: Bilheteria (Ancine/Wikipédia) | G5: 11551730 | H5: 240271275 | I5: 2320250281 | J5: 1 | K5: 649893 | L5: 7.5 | M5: =IF(G5="","",PERCENTRANK($G$2:$G$354,G5)) -> 0.98 | N5: =IF(I5="","",PERCENTRANK($I$2:$I$354,I5)) -> 0.987 | O5: =IF(K5="","",PERCENTRANK($K$2:$K$354,K5)) -> 0.696 | P5: =COUNT(M5:O5) -> 3 | Q5: 2022 populares #16 | S5: 2023 #9 | T5: 16–18 jun 2023 #3 (United States) | W5: =COUNTA(Q5:V5) -> 3 | X5: =IF(P5=0,"",MIN(1,AVERAGE(M5:O5)+Critérios!$B$5*W5)) -> 0.97766667 | Y5: =IF(X5="","",IF(X5>=Critérios!$B$7,"A",IF(X5>=Critérios!$B$8,"B","C"))) -> A | Z5: =IF(X5="","",RANK(X5,$X$2:$X$354)) -> 4 | AA5: =IF(X5="","Sairia — sem métrica",IF(PERCENTRANK($X$2:$X$354,X5)<Critérios!$B$6,"Sairia — terço inferior","Fica")) -> Fica | AB5: a avaliar | AD5: candidato | AF5: S055, S192, S200, S201 | AG5: tt1630029 | AH5: =COUNT(G5,I5,K5)+COUNTA(Q5:V5) -> 6 | AI5: =IF(AH5>=3,"Sim","Não") -> Sim | AJ5: =IF(AND(Z5<>"",Z5<=Critérios!$B$9),"Sim","Não") -> Sim
A6: F0005 | B6: V de Vingança | C6: V for Vendetta | D6: 2005 | E6: Não | F6: Adicionado por: JustWatch Brasil | K6: 1258464 | L6: 8.1 | M6: =IF(G6="","",PERCENTRANK($G$2:$G$354,G6)) | N6: =IF(I6="","",PERCENTRANK($I$2:$I$354,I6)) | O6: =IF(K6="","",PERCENTRANK($K$2:$K$354,K6)) -> 0.943 | P6: =COUNT(M6:O6) -> 1 | R6: #71 hoje | W6: =COUNTA(Q6:V6) -> 1 | X6: =IF(P6=0,"",MIN(1,AVERAGE(M6:O6)+Critérios!$B$5*W6)) -> 0.973 | Y6: =IF(X6="","",IF(X6>=Critérios!$B$7,"A",IF(X6>=Critérios!$B$8,"B","C"))) -> A | Z6: =IF(X6="","",RANK(X6,$X$2:$X$354)) -> 5 | AA6: =IF(X6="","Sairia — sem métrica",IF(PERCENTRANK($X$2:$X$354,X6)<Critérios!$B$6,"Sairia — terço inferior","Fica")) -> Fica | AB6: a avaliar | AC6: Resgatado manualmente (lista aprovada em 13/10/2026) | AD6: candidato | AG6: tt0434409 | AH6: =COUNT(G6,I6,K6)+COUNTA(Q6:V6) -> 2 | AI6: =IF(AH6>=3,"Sim","Não") -> Não | AJ6: =IF(AND(Z6<>"",Z6<=Critérios!$B$9),"Sim","Não") -> Sim
A7: F0006 | B7: Avatar | C7: Avatar | D7: 2009 | E7: Não | F7: Bilheteria (Ancine/Wikipédia) | G7: 9111628 | H7: 102346712 | I7: 2743577587 | J7: 1 | K7: 1518568 | L7: 7.9 | M7: =IF(G7="","",PERCENTRANK($G$2:$G$354,G7)) -> 0.944 | N7: =IF(I7="","",PERCENTRANK($I$2:$I$354,I7)) -> 0.996 | O7: =IF(K7="","",PERCENTRANK($K$2:$K$354,K7)) -> 0.969 | P7: =COUNT(M7:O7) -> 3 | W7: =COUNTA(Q7:V7) -> 0 | X7: =IF(P7=0,"",MIN(1,AVERAGE(M7:O7)+Critérios!$B$5*W7)) -> 0.96966667 | Y7: =IF(X7="","",IF(X7>=Critérios!$B$7,"A",IF(X7>=Critérios!$B$8,"B","C"))) -> A | Z7: =IF(X7="","",RANK(X7,$X$2:$X$354)) -> 6 | AA7: =IF(X7="","Sairia — sem métrica",IF(PERCENTRANK($X$2:$X$354,X7)<Critérios!$B$6,"Sairia — terço inferior","Fica")) -> Fica | AB7: a avaliar | AD7: candidato | AF7: S042, S191, S197 | AG7: tt0499549 | AH7: =COUNT(G7,I7,K7)+COUNTA(Q7:V7) -> 3 | AI7: =IF(AH7>=3,"Sim","Não") -> Sim | AJ7: =IF(AND(Z7<>"",Z7<=Critérios!$B$9),"Sim","Não") -> Sim
A8: F0007 | B8: Os Vingadores | C8: The Avengers | D8: 2012 | E8: Não | F8: Bilheteria (Ancine/Wikipédia) | G8: 10911371 | H8: 129595590 | I8: 1518812988 | J8: 1 | K8: 1587532 | L8: 8 | M8: =IF(G8="","",PERCENTRANK($G$2:$G$354,G8)) -> 0.977 | N8: =IF(I8="","",PERCENTRANK($I$2:$I$354,I8)) -> 0.945 | O8: =IF(K8="","",PERCENTRANK($K$2:$K$354,K8)) -> 0.974 | P8: =COUNT(M8:O8) -> 3 | W8: =COUNTA(Q8:V8) -> 0 | X8: =IF(P8=0,"",MIN(1,AVERAGE(M8:O8)+Critérios!$B$5*W8)) -> 0.96533333 | Y8: =IF(X8="","",IF(X8>=Critérios!$B$7,"A",IF(X8>=Critérios!$B$8,"B","C"))) -> A | Z8: =IF(X8="","",RANK(X8,$X$2:$X$354)) -> 7 | AA8: =IF(X8="","Sairia — sem métrica",IF(PERCENTRANK($X$2:$X$354,X8)<Critérios!$B$6,"Sairia — terço inferior","Fica")) -> Fica | AB8: ambíguo (provável) — conferir | AD8: candidato | AF8: S045, S191, S205 | AG8: tt0848228 | AH8: =COUNT(G8,I8,K8)+COUNTA(Q8:V8) -> 3 | AI8: =IF(AH8>=3,"Sim","Não") -> Sim | AJ8: =IF(AND(Z8<>"",Z8<=Critérios!$B$9),"Sim","Não") -> Sim
A9: F0008 | B9: Onde os Fracos Não Têm Vez | C9: No Country for Old Men | D9: 2007 | E9: Não | F9: Adicionado por: JustWatch Brasil | K9: 1217854 | L9: 8.2 | M9: =IF(G9="","",PERCENTRANK($G$2:$G$354,G9)) | N9: =IF(I9="","",PERCENTRANK($I$2:$I$354,I9)) | O9: =IF(K9="","",PERCENTRANK($K$2:$K$354,K9)) -> 0.935 | P9: =COUNT(M9:O9) -> 1 | R9: #98 hoje | W9: =COUNTA(Q9:V9) -> 1 | X9: =IF(P9=0,"",MIN(1,AVERAGE(M9:O9)+Critérios!$B$5*W9)) -> 0.965 | Y9: =IF(X9="","",IF(X9>=Critérios!$B$7,"A",IF(X9>=Critérios!$B$8,"B","C"))) -> A | Z9: =IF(X9="","",RANK(X9,$X$2:$X$354)) -> 8 | AA9: =IF(X9="","Sairia — sem métrica",IF(PERCENTRANK($X$2:$X$354,X9)<Critérios!$B$6,"Sairia — terço inferior","Fica")) -> Fica | AB9: a avaliar | AC9: Resgatado manualmente (lista aprovada em 13/10/2026) | AD9: candidato | AG9: tt0477348 | AH9: =COUNT(G9,I9,K9)+COUNTA(Q9:V9) -> 2 | AI9: =IF(AH9>=3,"Sim","Não") -> Não | AJ9: =IF(AND(Z9<>"",Z9<=Critérios!$B$9),"Sim","Não") -> Sim
A10: F0009 | B10: Brilho Eterno de uma Mente sem Lembranças | C10: Eternal Sunshine of the Spotless Mind | D10: 2004 | E10: Não | F10: Adicionado por: JustWatch Brasil | K10: 1199281 | L10: 8.3 | M10: =IF(G10="","",PERCENTRANK($G$2:$G$354,G10)) | N10: =IF(I10="","",PERCENTRANK($I$2:$I$354,I10)) | O10: =IF(K10="","",PERCENTRANK($K$2:$K$354,K10)) -> 0.929 | P10: =COUNT(M10:O10) -> 1 | R10: #129 hoje | W10: =COUNTA(Q10:V10) -> 1 | X10: =IF(P10=0,"",MIN(1,AVERAGE(M10:O10)+Critérios!$B$5*W10)) -> 0.959 | Y10: =IF(X10="","",IF(X10>=Critérios!$B$7,"A",IF(X10>=Critérios!$B$8,"B","C"))) -> A | Z10: =IF(X10="","",RANK(X10,$X$2:$X$354)) -> 9 | AA10: =IF(X10="","Sairia — sem métrica",IF(PERCENTRANK($X$2:$X$354,X10)<Critérios!$B$6,"Sairia — terço inferior","Fica")) -> Fica | AB10: a avaliar | AC10: Resgatado manualmente (lista aprovada em 13/10/2026) | AD10: candidato | AG10: tt0338013 | AH10: =COUNT(G10,I10,K10)+COUNTA(Q10:V10) -> 2 | AI10: =IF(AH10>=3,"Sim","Não") -> Não | AJ10: =IF(AND(Z10<>"",Z10<=Critérios!$B$9),"Sim","Não") -> Sim
A11: F0010 | B11: Garota Exemplar | C11: Gone Girl | D11: 2014 | E11: Não | F11: Adicionado por: JustWatch Brasil | K11: 1191566 | L11: 8.1 | M11: =IF(G11="","",PERCENTRANK($G$2:$G$354,G11)) | N11: =IF(I11="","",PERCENTRANK($I$2:$I$354,I11)) | O11: =IF(K11="","",PERCENTRANK($K$2:$K$354,K11)) -> 0.926 | P11: =COUNT(M11:O11) -> 1 | R11: #106 hoje | W11: =COUNTA(Q11:V11) -> 1 | X11: =IF(P11=0,"",MIN(1,AVERAGE(M11:O11)+Critérios!$B$5*W11)) -> 0.956 | Y11: =IF(X11="","",IF(X11>=Critérios!$B$7,"A",IF(X11>=Critérios!$B$8,"B","C"))) -> A | Z11: =IF(X11="","",RANK(X11,$X$2:$X$354)) -> 10 | AA11: =IF(X11="","Sairia — sem métrica",IF(PERCENTRANK($X$2:$X$354,X11)<Critérios!$B$6,"Sairia — terço inferior","Fica")) -> Fica | AB11: a avaliar | AC11: Resgatado manualmente (lista aprovada em 13/10/2026) | AD11: candidato | AG11: tt2267998 | AH11: =COUNT(G11,I11,K11)+COUNTA(Q11:V11) -> 2 | AI11: =IF(AH11>=3,"Sim","Não") -> Não | AJ11: =IF(AND(Z11<>"",Z11<=Critérios!$B$9),"Sim","Não") -> Sim
A12: F0011 | B12: Coringa | C12: Joker | D12: 2019 | E12: Não | F12: Bilheteria (Ancine/Wikipédia) | G12: 9766507 | H12: 157153605 | I12: 1079751311 | J12: 6 | K12: 1730798 | L12: 8.3 | M12: =IF(G12="","",PERCENTRANK($G$2:$G$354,G12)) -> 0.958 | N12: =IF(I12="","",PERCENTRANK($I$2:$I$354,I12)) -> 0.822 | O12: =IF(K12="","",PERCENTRANK($K$2:$K$354,K12)) -> 0.977 | P12: =COUNT(M12:O12) -> 3 | Q12: 2019 populares #2; populares de todos os tempos #5; populares de todos os tempos #2; populares de todos os tempos #6 | W12: =COUNTA(Q12:V12) -> 1 | X12: =IF(P12=0,"",MIN(1,AVERAGE(M12:O12)+Critérios!$B$5*W12)) -> 0.949 | Y12: =IF(X12="","",IF(X12>=Critérios!$B$7,"A",IF(X12>=Critérios!$B$8,"B","C"))) -> A | Z12: =IF(X12="","",RANK(X12,$X$2:$X$354)) -> 11 | AA12: =IF(X12="","Sairia — sem métrica",IF(PERCENTRANK($X$2:$X$354,X12)<Critérios!$B$6,"Sairia — terço inferior","Fica")) -> Fica | AB12: a avaliar | AD12: candidato | AF12: S052, S192, S201, S208 | AG12: tt7286456 | AH12: =COUNT(G12,I12,K12)+COUNTA(Q12:V12) -> 4 | AI12: =IF(AH12>=3,"Sim","Não") -> Sim | AJ12: =IF(AND(Z12<>"",Z12<=Critérios!$B$9),"Sim","Não") -> Sim
A13: F0012 | B13: Era Uma Vez em... Hollywood | C13: Once Upon a Time in... Hollywood | D13: 2019 | E13: Não | F13: Adicionado por: Letterboxd | K13: 982180 | L13: 7.6 | M13: =IF(G13="","",PERCENTRANK($G$2:$G$354,G13)) | N13: =IF(I13="","",PERCENTRANK($I$2:$I$354,I13)) | O13: =IF(K13="","",PERCENTRANK($K$2:$K$354,K13)) -> 0.881 | P13: =COUNT(M13:O13) -> 1 | Q13: 2019 populares #3 | R13: #103 hoje | W13: =COUNTA(Q13:V13) -> 2 | X13: =IF(P13=0,"",MIN(1,AVERAGE(M13:O13)+Critérios!$B$5*W13)) -> 0.941 | Y13: =IF(X13="","",IF(X13>=Critérios!$B$7,"A",IF(X13>=Critérios!$B$8,"B","C"))) -> A | Z13: =IF(X13="","",RANK(X13,$X$2:$X$354)) -> 12 | AA13: =IF(X13="","Sairia — sem métrica",IF(PERCENTRANK($X$2:$X$354,X13)<Critérios!$B$6,"Sairia — terço inferior","Fica")) -> Fica | AB13: a avaliar | AD13: candidato | AG13: tt7131622 | AH13: =COUNT(G13,I13,K13)+COUNTA(Q13:V13) -> 3 | AI13: =IF(AH13>=3,"Sim","Não") -> Sim | AJ13: =IF(AND(Z13<>"",Z13<=Critérios!$B$9),"Sim","Não") -> Sim
A14: F0013 | B14: Barbie | C14: Barbie | D14: 2023 | E14: Não | F14: Bilheteria (Ancine/Wikipédia) | G14: 10679592 | H14: 207205705 | I14: 1448232531 | J14: 1 | K14: 708172 | L14: 6.8 | M14: =IF(G14="","",PERCENTRANK($G$2:$G$354,G14)) -> 0.974 | N14: =IF(I14="","",PERCENTRANK($I$2:$I$354,I14)) -> 0.924 | O14: =IF(K14="","",PERCENTRANK($K$2:$K$354,K14)) -> 0.727 | P14: =COUNT(M14:O14) -> 3 | Q14: 2023 populares #1; populares de todos os tempos #1; populares de todos os tempos #4 | U14: UCLA Teens & Screens 2023 2023-10 (10-24) | W14: =COUNTA(Q14:V14) -> 2 | X14: =IF(P14=0,"",MIN(1,AVERAGE(M14:O14)+Critérios!$B$5*W14)) -> 0.935 | Y14: =IF(X14="","",IF(X14>=Critérios!$B$7,"A",IF(X14>=Critérios!$B$8,"B","C"))) -> A | Z14: =IF(X14="","",RANK(X14,$X$2:$X$354)) -> 13 | AA14: =IF(X14="","Sairia — sem métrica",IF(PERCENTRANK($X$2:$X$354,X14)<Critérios!$B$6,"Sairia — terço inferior","Fica")) -> Fica | AB14: a avaliar | AD14: candidato | AF14: S056, S192, S201 | AG14: tt1517268 | AH14: =COUNT(G14,I14,K14)+COUNTA(Q14:V14) -> 5 | AI14: =IF(AH14>=3,"Sim","Não") -> Sim | AJ14: =IF(AND(Z14<>"",Z14<=Critérios!$B$9),"Sim","Não") -> Sim
A15: F0014 | B15: Vingadores: A Era de Ultron | C15: Avengers: Age of Ultron | D15: 2015 | E15: Não | F15: Bilheteria (Ancine/Wikipédia) | G15: 10130740 | H15: 146203313 | I15: 1402809540 | J15: 4 | K15: 1026043 | L15: 7.3 | M15: =IF(G15="","",PERCENTRANK($G$2:$G$354,G15)) -> 0.967 | N15: =IF(I15="","",PERCENTRANK($I$2:$I$354,I15)) -> 0.919 | O15: =IF(K15="","",PERCENTRANK($K$2:$K$354,K15)) -> 0.901 | P15: =COUNT(M15:O15) -> 3 | W15: =COUNTA(Q15:V15) -> 0 | X15: =IF(P15=0,"",MIN(1,AVERAGE(M15:O15)+Critérios!$B$5*W15)) -> 0.929 | Y15: =IF(X15="","",IF(X15>=Critérios!$B$7,"A",IF(X15>=Critérios!$B$8,"B","C"))) -> A | Z15: =IF(X15="","",RANK(X15,$X$2:$X$354)) -> 14 | AA15: =IF(X15="","Sairia — sem métrica",IF(PERCENTRANK($X$2:$X$354,X15)<Critérios!$B$6,"Sairia — terço inferior","Fica")) -> Fica | AB15: ambíguo (provável) — conferir | AD15: candidato | AF15: S048, S191, S192, S201, S202 | AG15: tt2395427 | AH15: =COUNT(G15,I15,K15)+COUNTA(Q15:V15) -> 3 | AI15: =IF(AH15>=3,"Sim","Não") -> Sim | AJ15: =IF(AND(Z15<>"",Z15<=Critérios!$B$9),"Sim","Não") -> Sim
A16: F0015 | B16: Capitão América: Guerra civil | C16: Captain America: Civil War | D16: 2016 | E16: Não | F16: Bilheteria (Ancine/Wikipédia) | G16: 9617668 | H16: 143337776 | I16: 1153296293 | J16: 1 | K16: 953097 | L16: 7.8 | M16: =IF(G16="","",PERCENTRANK($G$2:$G$354,G16)) -> 0.954 | N16: =IF(I16="","",PERCENTRANK($I$2:$I$354,I16)) -> 0.864 | O16: =IF(K16="","",PERCENTRANK($K$2:$K$354,K16)) -> 0.866 | P16: =COUNT(M16:O16) -> 3 | Q16: 2016 populares #2 | W16: =COUNTA(Q16:V16) -> 1 | X16: =IF(P16=0,"",MIN(1,AVERAGE(M16:O16)+Critérios!$B$5*W16)) -> 0.92466667 | Y16: =IF(X16="","",IF(X16>=Critérios!$B$7,"A",IF(X16>=Critérios!$B$8,"B","C"))) -> A | Z16: =IF(X16="","",RANK(X16,$X$2:$X$354)) -> 15 | AA16: =IF(X16="","Sairia — sem métrica",IF(PERCENTRANK($X$2:$X$354,X16)<Critérios!$B$6,"Sairia — terço inferior","Fica")) -> Fica | AB16: a avaliar | AD16: candidato | AF16: S049, S191, S192, S201, S207 | AG16: tt3498820 | AH16: =COUNT(G16,I16,K16)+COUNTA(Q16:V16) -> 4 | AI16: =IF(AH16>=3,"Sim","Não") -> Sim | AJ16: =IF(AND(Z16<>"",Z16<=Critérios!$B$9),"Sim","Não") -> Sim
A17: F0016 | B17: Pantera Negra | C17: Black Panther | D17: 2018 | E17: Não | F17: Bilheteria (Ancine/Wikipédia) | G17: 7438252 | H17: 120998283 | I17: 1347597973 | J17: 2 | K17: 929481 | L17: 7.3 | M17: =IF(G17="","",PERCENTRANK($G$2:$G$354,G17)) -> 0.873 | N17: =IF(I17="","",PERCENTRANK($I$2:$I$354,I17)) -> 0.911 | O17: =IF(K17="","",PERCENTRANK($K$2:$K$354,K17)) -> 0.849 | P17: =COUNT(M17:O17) -> 3 | Q17: 2018 populares #1 | W17: =COUNTA(Q17:V17) -> 1 | X17: =IF(P17=0,"",MIN(1,AVERAGE(M17:O17)+Critérios!$B$5*W17)) -> 0.90766667 | Y17: =IF(X17="","",IF(X17>=Critérios!$B$7,"A",IF(X17>=Critérios!$B$8,"B","C"))) -> A | Z17: =IF(X17="","",RANK(X17,$X$2:$X$354)) -> 16 | AA17: =IF(X17="","Sairia — sem métrica",IF(PERCENTRANK($X$2:$X$354,X17)<Critérios!$B$6,"Sairia — terço inferior","Fica")) -> Fica | AB17: a avaliar | AD17: candidato | AF17: S051, S191 | AG17: tt1825683 | AH17: =COUNT(G17,I17,K17)+COUNTA(Q17:V17) -> 4 | AI17: =IF(AH17>=3,"Sim","Não") -> Sim | AJ17: =IF(AND(Z17<>"",Z17<=Critérios!$B$9),"Sim","Não") -> Sim
A18: F0017 | B18: Homem de ferro 3 | C18: Iron Man 3 | D18: 2013 | E18: Não | F18: Bilheteria (Ancine/Wikipédia) | G18: 7633472 | H18: 96488326 | I18: 1214811252 | J18: 2 | K18: 987286 | L18: 7.1 | M18: =IF(G18="","",PERCENTRANK($G$2:$G$354,G18)) -> 0.879 | N18: =IF(I18="","",PERCENTRANK($I$2:$I$354,I18)) -> 0.873 | O18: =IF(K18="","",PERCENTRANK($K$2:$K$354,K18)) -> 0.886 | P18: =COUNT(M18:O18) -> 3 | W18: =COUNTA(Q18:V18) -> 0 | X18: =IF(P18=0,"",MIN(1,AVERAGE(M18:O18)+Critérios!$B$5*W18)) -> 0.87933333 | Y18: =IF(X18="","",IF(X18>=Critérios!$B$7,"A",IF(X18>=Critérios!$B$8,"B","C"))) -> A | Z18: =IF(X18="","",RANK(X18,$X$2:$X$354)) -> 17 | AA18: =IF(X18="","Sairia — sem métrica",IF(PERCENTRANK($X$2:$X$354,X18)<Critérios!$B$6,"Sairia — terço inferior","Fica")) -> Fica | AB18: a avaliar | AD18: candidato | AF18: S046, S193 | AG18: tt1300854 | AH18: =COUNT(G18,I18,K18)+COUNTA(Q18:V18) -> 3 | AI18: =IF(AH18>=3,"Sim","Não") -> Sim | AJ18: =IF(AND(Z18<>"",Z18<=Critérios!$B$9),"Sim","Não") -> Sim
A19: F0018 | B19: Logan | D19: 2017 | E19: Não | F19: Bilheteria (Ancine/Wikipédia) | G19: 6400985 | H19: 91260487 | K19: 943654 | L19: 8.1 | M19: =IF(G19="","",PERCENTRANK($G$2:$G$354,G19)) -> 0.83 | N19: =IF(I19="","",PERCENTRANK($I$2:$I$354,I19)) | O19: =IF(K19="","",PERCENTRANK($K$2:$K$354,K19)) -> 0.861 | P19: =COUNT(M19:O19) -> 2 | Q19: 2017 populares #3; 2017 mais bem avaliados #10 | W19: =COUNTA(Q19:V19) -> 1 | X19: =IF(P19=0,"",MIN(1,AVERAGE(M19:O19)+Critérios!$B$5*W19)) -> 0.8755 | Y19: =IF(X19="","",IF(X19>=Critérios!$B$7,"A",IF(X19>=Critérios!$B$8,"B","C"))) -> A | Z19: =IF(X19="","",RANK(X19,$X$2:$X$354)) -> 18 | AA19: =IF(X19="","Sairia — sem métrica",IF(PERCENTRANK($X$2:$X$354,X19)<Critérios!$B$6,"Sairia — terço inferior","Fica")) -> Fica | AB19: a avaliar | AD19: candidato | AF19: S203 | AG19: tt3315342 | AH19: =COUNT(G19,I19,K19)+COUNTA(Q19:V19) -> 3 | AI19: =IF(AH19>=3,"Sim","Não") -> Sim | AJ19: =IF(AND(Z19<>"",Z19<=Critérios!$B$9),"Sim","Não") -> Sim
A20: F0019 | B20: Harry Potter e as Reliquias da Morte: Parte 2 | C20: Harry Potter and the Deathly Hallows – Part 2 | D20: 2011 | E20: Não | F20: Bilheteria (Ancine/Wikipédia) | G20: 5577582 | H20: 57145553 | I20: 1341511219 | J20: 1 | K20: 1065924 | L20: 8.1 | M20: =IF(G20="","",PERCENTRANK($G$2:$G$354,G20)) -> 0.778 | N20: =IF(I20="","",PERCENTRANK($I$2:$I$354,I20)) -> 0.907 | O20: =IF(K20="","",PERCENTRANK($K$2:$K$354,K20)) -> 0.906 | P20: =COUNT(M20:O20) -> 3 | W20: =COUNTA(Q20:V20) -> 0 | X20: =IF(P20=0,"",MIN(1,AVERAGE(M20:O20)+Critérios!$B$5*W20)) -> 0.86366667 | Y20: =IF(X20="","",IF(X20>=Critérios!$B$7,"A",IF(X20>=Critérios!$B$8,"B","C"))) -> A | Z20: =IF(X20="","",RANK(X20,$X$2:$X$354)) -> 19 | AA20: =IF(X20="","Sairia — sem métrica",IF(PERCENTRANK($X$2:$X$354,X20)<Critérios!$B$6,"Sairia — terço inferior","Fica")) -> Fica | AB20: a avaliar | AD20: candidato | AF20: S044, S187 | AG20: tt1201607 | AH20: =COUNT(G20,I20,K20)+COUNTA(Q20:V20) -> 3 | AI20: =IF(AH20>=3,"Sim","Não") -> Sim | AJ20: =IF(AND(Z20<>"",Z20<=Critérios!$B$9),"Sim","Não") -> Sim
A21: F0020 | B21: Top Gun: Maverick | C21: Top Gun: Maverick | D21: 2022 | E21: Não | F21: Bilheteria (Ancine/Wikipédia) | G21: 5006094 | H21: 110317368 | I21: 1495696292 | J21: 2 | K21: 909213 | L21: 8.2 | M21: =IF(G21="","",PERCENTRANK($G$2:$G$354,G21)) -> 0.725 | N21: =IF(I21="","",PERCENTRANK($I$2:$I$354,I21)) -> 0.936 | O21: =IF(K21="","",PERCENTRANK($K$2:$K$354,K21)) -> 0.835 | P21: =COUNT(M21:O21) -> 3 | Q21: 2022 populares #5 | W21: =COUNTA(Q21:V21) -> 1 | X21: =IF(P21=0,"",MIN(1,AVERAGE(M21:O21)+Critérios!$B$5*W21)) -> 0.862 | Y21: =IF(X21="","",IF(X21>=Critérios!$B$7,"A",IF(X21>=Critérios!$B$8,"B","C"))) -> A | Z21: =IF(X21="","",RANK(X21,$X$2:$X$354)) -> 21 | AA21: =IF(X21="","Sairia — sem métrica",IF(PERCENTRANK($X$2:$X$354,X21)<Critérios!$B$6,"Sairia — terço inferior","Fica")) -> Fica | AB21: a avaliar | AD21: candidato | AF21: S055, S200 | AG21: tt1745960 | AH21: =COUNT(G21,I21,K21)+COUNTA(Q21:V21) -> 4 | AI21: =IF(AH21>=3,"Sim","Não") -> Sim | AJ21: =IF(AND(Z21<>"",Z21<=Critérios!$B$9),"Sim","Não") -> Sim
A22: F0021 | B22: Homem-Aranha Longe de Casa | C22: Spider-Man: Far From Home | D22: 2019 | E22: Não | F22: Bilheteria (Ancine/Wikipédia) | G22: 6555353 | H22: 106552456 | I22: 1133927996 | J22: 4 | K22: 679969 | L22: 7.3 | M22: =IF(G22="","",PERCENTRANK($G$2:$G$354,G22)) -> 0.837 | N22: =IF(I22="","",PERCENTRANK($I$2:$I$354,I22)) -> 0.852 | O22: =IF(K22="","",PERCENTRANK($K$2:$K$354,K22)) -> 0.719 | P22: =COUNT(M22:O22) -> 3 | Q22: 2019 populares #8 | R22: #114 hoje | W22: =COUNTA(Q22:V22) -> 2 | X22: =IF(P22=0,"",MIN(1,AVERAGE(M22:O22)+Critérios!$B$5*W22)) -> 0.86266667 | Y22: =IF(X22="","",IF(X22>=Critérios!$B$7,"A",IF(X22>=Critérios!$B$8,"B","C"))) -> A | Z22: =IF(X22="","",RANK(X22,$X$2:$X$354)) -> 20 | AA22: =IF(X22="","Sairia — sem métrica",IF(PERCENTRANK($X$2:$X$354,X22)<Critérios!$B$6,"Sairia — terço inferior","Fica")) -> Fica | AB22: a avaliar | AD22: candidato | AF22: S052, S208 | AG22: tt6320628 | AH22: =COUNT(G22,I22,K22)+COUNTA(Q22:V22) -> 5 | AI22: =IF(AH22>=3,"Sim","Não") -> Sim | AJ22: =IF(AND(Z22<>"",Z22<=Critérios!$B$9),"Sim","Não") -> Sim
A23: F0022 | B23: Capitã Marvel | C23: Captain Marvel | D23: 2019 | E23: Não | F23: Bilheteria (Ancine/Wikipédia) | G23: 8993389 | H23: 146783970 | I23: 1131274794 | J23: 5 | K23: 675498 | L23: 6.7 | M23: =IF(G23="","",PERCENTRANK($G$2:$G$354,G23)) -> 0.938 | N23: =IF(I23="","",PERCENTRANK($I$2:$I$354,I23)) -> 0.847 | O23: =IF(K23="","",PERCENTRANK($K$2:$K$354,K23)) -> 0.71 | P23: =COUNT(M23:O23) -> 3 | Q23: 2019 populares #6 | W23: =COUNTA(Q23:V23) -> 1 | X23: =IF(P23=0,"",MIN(1,AVERAGE(M23:O23)+Critérios!$B$5*W23)) -> 0.86166667 | Y23: =IF(X23="","",IF(X23>=Critérios!$B$7,"A",IF(X23>=Critérios!$B$8,"B","C"))) -> A | Z23: =IF(X23="","",RANK(X23,$X$2:$X$354)) -> 22 | AA23: =IF(X23="","Sairia — sem métrica",IF(PERCENTRANK($X$2:$X$354,X23)<Critérios!$B$6,"Sairia — terço inferior","Fica")) -> Fica | AB23: a avaliar | AD23: candidato | AF23: S052, S192, S201, S208 | AG23: tt4154664 | AH23: =COUNT(G23,I23,K23)+COUNTA(Q23:V23) -> 4 | AI23: =IF(AH23>=3,"Sim","Não") -> Sim | AJ23: =IF(AND(Z23<>"",Z23<=Critérios!$B$9),"Sim","Não") -> Sim
A24: F0023 | B24: O Jogo da Imitação | C24: The Imitation Game | D24: 2014 | E24: Não | F24: Adicionado por: JustWatch Brasil | K24: 887022 | L24: 8 | M24: =IF(G24="","",PERCENTRANK($G$2:$G$354,G24)) | N24: =IF(I24="","",PERCENTRANK($I$2:$I$354,I24)) | O24: =IF(K24="","",PERCENTRANK($K$2:$K$354,K24)) -> 0.827 | P24: =COUNT(M24:O24) -> 1 | R24: #89 hoje | W24: =COUNTA(Q24:V24) -> 1 | X24: =IF(P24=0,"",MIN(1,AVERAGE(M24:O24)+Critérios!$B$5*W24)) -> 0.857 | Y24: =IF(X24="","",IF(X24>=Critérios!$B$7,"A",IF(X24>=Critérios!$B$8,"B","C"))) -> A | Z24: =IF(X24="","",RANK(X24,$X$2:$X$354)) -> 23 | AA24: =IF(X24="","Sairia — sem métrica",IF(PERCENTRANK($X$2:$X$354,X24)<Critérios!$B$6,"Sairia — terço inferior","Fica")) -> Fica | AB24: a avaliar | AC24: Resgatado manualmente (lista aprovada em 13/10/2026) | AD24: candidato | AG24: tt2084970 | AH24: =COUNT(G24,I24,K24)+COUNTA(Q24:V24) -> 2 | AI24: =IF(AH24>=3,"Sim","Não") -> Não | AJ24: =IF(AND(Z24<>"",Z24<=Critérios!$B$9),"Sim","Não") -> Sim
A25: F0024 | B25: Batman: O Cavaleiro das Trevas Ressurge | C25: The Dark Knight Rises | D25: 2012 | E25: Não | F25: Bilheteria (Ancine/Wikipédia) | G25: 5146519 | H25: 55062755 | I25: 1081041287 | J25: 3 | K25: 2032805 | L25: 8.4 | M25: =IF(G25="","",PERCENTRANK($G$2:$G$354,G25)) -> 0.742 | N25: =IF(I25="","",PERCENTRANK($I$2:$I$354,I25)) -> 0.826 | O25: =IF(K25="","",PERCENTRANK($K$2:$K$354,K25)) -> 0.986 | P25: =COUNT(M25:O25) -> 3 | W25: =COUNTA(Q25:V25) -> 0 | X25: =IF(P25=0,"",MIN(1,AVERAGE(M25:O25)+Critérios!$B$5*W25)) -> 0.85133333 | Y25: =IF(X25="","",IF(X25>=Critérios!$B$7,"A",IF(X25>=Critérios!$B$8,"B","C"))) -> A | Z25: =IF(X25="","",RANK(X25,$X$2:$X$354)) -> 24 | AA25: =IF(X25="","Sairia — sem métrica",IF(PERCENTRANK($X$2:$X$354,X25)<Critérios!$B$6,"Sairia — terço inferior","Fica")) -> Fica | AB25: a avaliar | AD25: candidato | AF25: S045, S205 | AG25: tt1345836 | AH25: =COUNT(G25,I25,K25)+COUNTA(Q25:V25) -> 3 | AI25: =IF(AH25>=3,"Sim","Não") -> Sim | AJ25: =IF(AND(Z25<>"",Z25<=Critérios!$B$9),"Sim","Não") -> Sim
A26: F0025 | B26: Jurassic World: O mundo dos dinossauros | C26: Jurassic World | D26: 2015 | E26: Não | F26: Bilheteria (Ancine/Wikipédia) | G26: 6356559 | H26: 90707161 | I26: 1671537444 | J26: 2 | K26: 739583 | L26: 6.9 | M26: =IF(G26="","",PERCENTRANK($G$2:$G$354,G26)) -> 0.824 | N26: =IF(I26="","",PERCENTRANK($I$2:$I$354,I26)) -> 0.958 | O26: =IF(K26="","",PERCENTRANK($K$2:$K$354,K26)) -> 0.75 | P26: =COUNT(M26:O26) -> 3 | W26: =COUNTA(Q26:V26) -> 0 | X26: =IF(P26=0,"",MIN(1,AVERAGE(M26:O26)+Critérios!$B$5*W26)) -> 0.844 | Y26: =IF(X26="","",IF(X26>=Critérios!$B$7,"A",IF(X26>=Critérios!$B$8,"B","C"))) -> A | Z26: =IF(X26="","",RANK(X26,$X$2:$X$354)) -> 25 | AA26: =IF(X26="","Sairia — sem métrica",IF(PERCENTRANK($X$2:$X$354,X26)<Critérios!$B$6,"Sairia — terço inferior","Fica")) -> Fica | AB26: ambíguo (provável) — conferir | AD26: candidato | AF26: S048, S202 | AG26: tt0369610 | AH26: =COUNT(G26,I26,K26)+COUNTA(Q26:V26) -> 3 | AI26: =IF(AH26>=3,"Sim","Não") -> Sim | AJ26: =IF(AND(Z26<>"",Z26<=Critérios!$B$9),"Sim","Não") -> Sim
A27: F0026 | B27: Deadpool & Wolverine | C27: Deadpool & Wolverine | D27: 2024 | E27: Não | F27: Bilheteria (Ancine/Wikipédia) | G27: 7365659 | H27: 155895852 | I27: 1338073645 | J27: 2 | K27: 597766 | L27: 7.5 | M27: =IF(G27="","",PERCENTRANK($G$2:$G$354,G27)) -> 0.866 | N27: =IF(I27="","",PERCENTRANK($I$2:$I$354,I27)) -> 0.903 | O27: =IF(K27="","",PERCENTRANK($K$2:$K$354,K27)) -> 0.67 | P27: =COUNT(M27:O27) -> 3 | Q27: 2024 populares #4 | W27: =COUNTA(Q27:V27) -> 1 | X27: =IF(P27=0,"",MIN(1,AVERAGE(M27:O27)+Critérios!$B$5*W27)) -> 0.843 | Y27: =IF(X27="","",IF(X27>=Critérios!$B$7,"A",IF(X27>=Critérios!$B$8,"B","C"))) -> A | Z27: =IF(X27="","",RANK(X27,$X$2:$X$354)) -> 26 | AA27: =IF(X27="","Sairia — sem métrica",IF(PERCENTRANK($X$2:$X$354,X27)<Critérios!$B$6,"Sairia — terço inferior","Fica")) -> Fica | AB27: a avaliar | AD27: candidato | AF27: S057, S209 | AG27: tt6263850 | AH27: =COUNT(G27,I27,K27)+COUNTA(Q27:V27) -> 4 | AI27: =IF(AH27>=3,"Sim","Não") -> Sim | AJ27: =IF(AND(Z27<>"",Z27<=Critérios!$B$9),"Sim","Não") -> Sim
A28: F0027 | B28: Homem-Aranha: De Volta ao Lar | C28: Spider-Man: Homecoming | D28: 2017 | E28: Não | F28: Bilheteria (Ancine/Wikipédia) | G28: 6686736 | H28: 102726271 | I28: 880166924 | J28: 6 | K28: 842372 | L28: 7.4 | M28: =IF(G28="","",PERCENTRANK($G$2:$G$354,G28)) -> 0.843 | N28: =IF(I28="","",PERCENTRANK($I$2:$I$354,I28)) -> 0.648 | O28: =IF(K28="","",PERCENTRANK($K$2:$K$354,K28)) -> 0.815 | P28: =COUNT(M28:O28) -> 3 | Q28: 2017 populares #9 | R28: #107 hoje | W28: =COUNTA(Q28:V28) -> 2 | X28: =IF(P28=0,"",MIN(1,AVERAGE(M28:O28)+Critérios!$B$5*W28)) -> 0.82866667 | Y28: =IF(X28="","",IF(X28>=Critérios!$B$7,"A",IF(X28>=Critérios!$B$8,"B","C"))) -> A | Z28: =IF(X28="","",RANK(X28,$X$2:$X$354)) -> 27 | AA28: =IF(X28="","Sairia — sem métrica",IF(PERCENTRANK($X$2:$X$354,X28)<Critérios!$B$6,"Sairia — terço inferior","Fica")) -> Fica | AB28: a avaliar | AD28: candidato | AF28: S050, S203 | AG28: tt2250912 | AH28: =COUNT(G28,I28,K28)+COUNTA(Q28:V28) -> 5 | AI28: =IF(AH28>=3,"Sim","Não") -> Sim | AJ28: =IF(AND(Z28<>"",Z28<=Critérios!$B$9),"Sim","Não") -> Sim
A29: F0028 | B29: Homem-Aranha: Um Novo Dia | C29: Spider-Man: Brand New Day | D29: 2026 | E29: Não | F29: Bilheteria (Ancine/Wikipédia) | G29: 18780000 | H29: 412100000 | I29: 2421842642 | J29: 1 | K29: 344361 | L29: 7.9 | M29: =IF(G29="","",PERCENTRANK($G$2:$G$354,G29)) -> 0.993 | N29: =IF(I29="","",PERCENTRANK($I$2:$I$354,I29)) -> 0.992 | O29: =IF(K29="","",PERCENTRANK($K$2:$K$354,K29)) -> 0.406 | P29: =COUNT(M29:O29) -> 3 | R29: #5 hoje | W29: =COUNTA(Q29:V29) -> 1 | X29: =IF(P29=0,"",MIN(1,AVERAGE(M29:O29)+Critérios!$B$5*W29)) -> 0.827 | Y29: =IF(X29="","",IF(X29>=Critérios!$B$7,"A",IF(X29>=Critérios!$B$8,"B","C"))) -> A | Z29: =IF(X29="","",RANK(X29,$X$2:$X$354)) -> 28 | AA29: =IF(X29="","Sairia — sem métrica",IF(PERCENTRANK($X$2:$X$354,X29)<Critérios!$B$6,"Sairia — terço inferior","Fica")) -> Fica | AB29: a avaliar | AC29: 2026: dados parciais | AD29: candidato | AF29: S059, S189 | AG29: tt22084616 | AH29: =COUNT(G29,I29,K29)+COUNTA(Q29:V29) -> 4 | AI29: =IF(AH29>=3,"Sim","Não") -> Sim | AJ29: =IF(AND(Z29<>"",Z29<=Critérios!$B$9),"Sim","Não") -> Sim
A30: F0029 | B30: Homem-Aranha | C30: Spider-Man | D30: 2002 | E30: Não | F30: Bilheteria (Ancine/Wikipédia) | G30: 8488182 | H30: 46026289 | I30: 821708551 | J30: 3 | K30: 1000733 | L30: 7.4 | M30: =IF(G30="","",PERCENTRANK($G$2:$G$354,G30)) -> 0.918 | N30: =IF(I30="","",PERCENTRANK($I$2:$I$354,I30)) -> 0.568 | O30: =IF(K30="","",PERCENTRANK($K$2:$K$354,K30)) -> 0.898 | P30: =COUNT(M30:O30) -> 3 | U30: UCLA Center for Scholars & Storytellers 2025-10 (10-24) #4 | W30: =COUNTA(Q30:V30) -> 1 | X30: =IF(P30=0,"",MIN(1,AVERAGE(M30:O30)+Critérios!$B$5*W30)) -> 0.82466667 | Y30: =IF(X30="","",IF(X30>=Critérios!$B$7,"A",IF(X30>=Critérios!$B$8,"B","C"))) -> A | Z30: =IF(X30="","",RANK(X30,$X$2:$X$354)) -> 29 | AA30: =IF(X30="","Sairia — sem métrica",IF(PERCENTRANK($X$2:$X$354,X30)<Critérios!$B$6,"Sairia — terço inferior","Fica")) -> Fica | AB30: a avaliar | AD30: candidato | AF30: S035, S180 | AG30: tt0145487 | AH30: =COUNT(G30,I30,K30)+COUNTA(Q30:V30) -> 4 | AI30: =IF(AH30>=3,"Sim","Não") -> Sim | AJ30: =IF(AND(Z30<>"",Z30<=Critérios!$B$9),"Sim","Não") -> Sim
A31: F0030 | B31: Batman vs Superman: a Origem da Justiça | C31: Batman v Superman: Dawn of Justice | D31: 2016 | E31: Não | F31: Bilheteria (Ancine/Wikipédia) | G31: 8565462 | H31: 132443918 | I31: 874360194 | J31: 7 | K31: 800609 | L31: 6.4 | M31: =IF(G31="","",PERCENTRANK($G$2:$G$354,G31)) -> 0.925 | N31: =IF(I31="","",PERCENTRANK($I$2:$I$354,I31)) -> 0.631 | O31: =IF(K31="","",PERCENTRANK($K$2:$K$354,K31)) -> 0.801 | P31: =COUNT(M31:O31) -> 3 | Q31: 2016 populares #4 | W31: =COUNTA(Q31:V31) -> 1 | X31: =IF(P31=0,"",MIN(1,AVERAGE(M31:O31)+Critérios!$B$5*W31)) -> 0.81566667 | Y31: =IF(X31="","",IF(X31>=Critérios!$B$7,"A",IF(X31>=Critérios!$B$8,"B","C"))) -> A | Z31: =IF(X31="","",RANK(X31,$X$2:$X$354)) -> 30 | AA31: =IF(X31="","Sairia — sem métrica",IF(PERCENTRANK($X$2:$X$354,X31)<Critérios!$B$6,"Sairia — terço inferior","Fica")) -> Fica | AB31: a avaliar | AD31: candidato | AF31: S049, S191, S201, S207 | AG31: tt2975590 | AH31: =COUNT(G31,I31,K31)+COUNTA(Q31:V31) -> 4 | AI31: =IF(AH31>=3,"Sim","Não") -> Sim | AJ31: =IF(AND(Z31<>"",Z31<=Critérios!$B$9),"Sim","Não") -> Sim
A32: F0031 | B32: O Senhor dos Anéis: O Retorno do Rei | C32: The Lord of the Rings: The Return of the King | D32: 2003 | E32: Não | F32: Bilheteria (Ancine/Wikipédia) | G32: 4268649 | H32: 28906614 | I32: 1118887224 | J32: 1 | K32: 2200389 | L32: 9 | M32: =IF(G32="","",PERCENTRANK($G$2:$G$354,G32)) -> 0.608 | N32: =IF(I32="","",PERCENTRANK($I$2:$I$354,I32)) -> 0.839 | O32: =IF(K32="","",PERCENTRANK($K$2:$K$354,K32)) -> 0.989 | P32: =COUNT(M32:O32) -> 3 | W32: =COUNTA(Q32:V32) -> 0 | X32: =IF(P32=0,"",MIN(1,AVERAGE(M32:O32)+Critérios!$B$5*W32)) -> 0.812 | Y32: =IF(X32="","",IF(X32>=Critérios!$B$7,"A",IF(X32>=Critérios!$B$8,"B","C"))) -> A | Z32: =IF(X32="","",RANK(X32,$X$2:$X$354)) -> 31 | AA32: =IF(X32="","Sairia — sem métrica",IF(PERCENTRANK($X$2:$X$354,X32)<Critérios!$B$6,"Sairia — terço inferior","Fica")) -> Fica | AB32: ambíguo (provável) — conferir | AD32: candidato | AF32: S036, S181 | AG32: tt0167260 | AH32: =COUNT(G32,I32,K32)+COUNTA(Q32:V32) -> 3 | AI32: =IF(AH32>=3,"Sim","Não") -> Sim | AJ32: =IF(AND(Z32<>"",Z32<=Critérios!$B$9),"Sim","Não") -> Sim
A33: F0032 | B33: Não Olhe para Cima | C33: Don't Look Up | D33: 2021 | E33: Não | F33: Adicionado por: Nielsen | K33: 683308 | L33: 7.1 | M33: =IF(G33="","",PERCENTRANK($G$2:$G$354,G33)) | N33: =IF(I33="","",PERCENTRANK($I$2:$I$354,I33)) | O33: =IF(K33="","",PERCENTRANK($K$2:$K$354,K33)) -> 0.722 | P33: =COUNT(M33:O33) -> 1 | Q33: 2021 populares #8 | S33: 2022 #7 | T33: fim de semana 7–9 jan 2022 #2 (United States); 18–20 fev 2022 #10 (United States) | W33: =COUNTA(Q33:V33) -> 3 | X33: =IF(P33=0,"",MIN(1,AVERAGE(M33:O33)+Critérios!$B$5*W33)) -> 0.812 | Y33: =IF(X33="","",IF(X33>=Critérios!$B$7,"A",IF(X33>=Critérios!$B$8,"B","C"))) -> A | Z33: =IF(X33="","",RANK(X33,$X$2:$X$354)) -> 31 | AA33: =IF(X33="","Sairia — sem métrica",IF(PERCENTRANK($X$2:$X$354,X33)<Critérios!$B$6,"Sairia — terço inferior","Fica")) -> Fica | AB33: a avaliar | AD33: candidato | AG33: tt11286314 | AH33: =COUNT(G33,I33,K33)+COUNTA(Q33:V33) -> 4 | AI33: =IF(AH33>=3,"Sim","Não") -> Sim | AJ33: =IF(AND(Z33<>"",Z33<=Critérios!$B$9),"Sim","Não") -> Sim
A34: F0033 | B34: Doutor Estranho no Multiverso da Loucura | C34: Doctor Strange in the Multiverse of Madness | D34: 2022 | E34: Não | F34: Bilheteria (Ancine/Wikipédia) | G34: 8293496 | H34: 167507986 | I34: 960775804 | J34: 4 | K34: 563046 | L34: 6.8 | M34: =IF(G34="","",PERCENTRANK($G$2:$G$354,G34)) -> 0.908 | N34: =IF(I34="","",PERCENTRANK($I$2:$I$354,I34)) -> 0.699 | O34: =IF(K34="","",PERCENTRANK($K$2:$K$354,K34)) -> 0.642 | P34: =COUNT(M34:O34) -> 3 | Q34: 2022 populares #4 | T34: 15–17 jul 2022 #3 (United States); 22–24 jul 2022 #2 (United States) | W34: =COUNTA(Q34:V34) -> 2 | X34: =IF(P34=0,"",MIN(1,AVERAGE(M34:O34)+Critérios!$B$5*W34)) -> 0.80966667 | Y34: =IF(X34="","",IF(X34>=Critérios!$B$7,"A",IF(X34>=Critérios!$B$8,"B","C"))) -> A | Z34: =IF(X34="","",RANK(X34,$X$2:$X$354)) -> 33 | AA34: =IF(X34="","Sairia — sem métrica",IF(PERCENTRANK($X$2:$X$354,X34)<Critérios!$B$6,"Sairia — terço inferior","Fica")) -> Fica | AB34: a avaliar | AD34: candidato | AF34: S055, S200 | AG34: tt9419884 | AH34: =COUNT(G34,I34,K34)+COUNTA(Q34:V34) -> 5 | AI34: =IF(AH34>=3,"Sim","Não") -> Sim | AJ34: =IF(AND(Z34<>"",Z34<=Critérios!$B$9),"Sim","Não") -> Sim
A35: F0034 | B35: Velozes e Furiosos 7 | C35: Furious 7 | D35: 2015 | E35: Não | F35: Bilheteria (Ancine/Wikipédia) | G35: 9857968 | H35: 142466037 | I35: 1515341399 | J35: 3 | K35: 445858 | L35: 7.1 | M35: =IF(G35="","",PERCENTRANK($G$2:$G$354,G35)) -> 0.964 | N35: =IF(I35="","",PERCENTRANK($I$2:$I$354,I35)) -> 0.941 | O35: =IF(K35="","",PERCENTRANK($K$2:$K$354,K35)) -> 0.514 | P35: =COUNT(M35:O35) -> 3 | W35: =COUNTA(Q35:V35) -> 0 | X35: =IF(P35=0,"",MIN(1,AVERAGE(M35:O35)+Critérios!$B$5*W35)) -> 0.80633333 | Y35: =IF(X35="","",IF(X35>=Critérios!$B$7,"A",IF(X35>=Critérios!$B$8,"B","C"))) -> A | Z35: =IF(X35="","",RANK(X35,$X$2:$X$354)) -> 34 | AA35: =IF(X35="","Sairia — sem métrica",IF(PERCENTRANK($X$2:$X$354,X35)<Critérios!$B$6,"Sairia — terço inferior","Fica")) -> Fica | AB35: ambíguo (provável) — conferir | AD35: candidato | AF35: S048, S191, S192, S201, S202 | AG35: tt2820852 | AH35: =COUNT(G35,I35,K35)+COUNTA(Q35:V35) -> 3 | AI35: =IF(AH35>=3,"Sim","Não") -> Sim | AJ35: =IF(AND(Z35<>"",Z35<=Critérios!$B$9),"Sim","Não") -> Sim
A36: F0035 | B36: A Odisseia | C36: The Odyssey | D36: 2026 | E36: Não | F36: Bilheteria (Ancine/Wikipédia) | G36: 5330290 | H36: 131030000 | I36: 1657467504 | J36: 2 | K36: 526880 | L36: 8.4 | M36: =IF(G36="","",PERCENTRANK($G$2:$G$354,G36)) -> 0.761 | N36: =IF(I36="","",PERCENTRANK($I$2:$I$354,I36)) -> 0.949 | O36: =IF(K36="","",PERCENTRANK($K$2:$K$354,K36)) -> 0.614 | P36: =COUNT(M36:O36) -> 3 | R36: #16 hoje | W36: =COUNTA(Q36:V36) -> 1 | X36: =IF(P36=0,"",MIN(1,AVERAGE(M36:O36)+Critérios!$B$5*W36)) -> 0.80466667 | Y36: =IF(X36="","",IF(X36>=Critérios!$B$7,"A",IF(X36>=Critérios!$B$8,"B","C"))) -> A | Z36: =IF(X36="","",RANK(X36,$X$2:$X$354)) -> 35 | AA36: =IF(X36="","Sairia — sem métrica",IF(PERCENTRANK($X$2:$X$354,X36)<Critérios!$B$6,"Sairia — terço inferior","Fica")) -> Fica | AB36: a avaliar | AC36: 2026: dados parciais | AD36: candidato | AF36: S059, S189 | AG36: tt33764258 | AH36: =COUNT(G36,I36,K36)+COUNTA(Q36:V36) -> 4 | AI36: =IF(AH36>=3,"Sim","Não") -> Sim | AJ36: =IF(AND(Z36<>"",Z36<=Critérios!$B$9),"Sim","Não") -> Sim
A37: F0036 | B37: Doutor Estranho | C37: Doctor Strange | D37: 2016 | E37: Não | F37: Bilheteria (Ancine/Wikipédia) | G37: 4797512 | H37: 74731453 | K37: 900827 | L37: 7.5 | M37: =IF(G37="","",PERCENTRANK($G$2:$G$354,G37)) -> 0.716 | N37: =IF(I37="","",PERCENTRANK($I$2:$I$354,I37)) | O37: =IF(K37="","",PERCENTRANK($K$2:$K$354,K37)) -> 0.832 | P37: =COUNT(M37:O37) -> 2 | Q37: 2016 populares #15 | W37: =COUNTA(Q37:V37) -> 1 | X37: =IF(P37=0,"",MIN(1,AVERAGE(M37:O37)+Critérios!$B$5*W37)) -> 0.804 | Y37: =IF(X37="","",IF(X37>=Critérios!$B$7,"A",IF(X37>=Critérios!$B$8,"B","C"))) -> A | Z37: =IF(X37="","",RANK(X37,$X$2:$X$354)) -> 36 | AA37: =IF(X37="","Sairia — sem métrica",IF(PERCENTRANK($X$2:$X$354,X37)<Critérios!$B$6,"Sairia — terço inferior","Fica")) -> Fica | AB37: a avaliar | AD37: candidato | AF37: S207 | AG37: tt1211837 | AH37: =COUNT(G37,I37,K37)+COUNTA(Q37:V37) -> 3 | AI37: =IF(AH37>=3,"Sim","Não") -> Sim | AJ37: =IF(AND(Z37<>"",Z37<=Critérios!$B$9),"Sim","Não") -> Sim
A38: F0037 | B38: Batman – O Cavaleiro das Trevas | C38: The Dark Knight | D38: 2008 | E38: Não | F38: Bilheteria (Ancine/Wikipédia) | G38: 4026563 | H38: 32773928 | I38: 997000000 | J38: 1 | K38: 3238631 | L38: 9.1 | M38: =IF(G38="","",PERCENTRANK($G$2:$G$354,G38)) -> 0.575 | N38: =IF(I38="","",PERCENTRANK($I$2:$I$354,I38)) -> 0.746 | O38: =IF(K38="","",PERCENTRANK($K$2:$K$354,K38)) -> 1 | P38: =COUNT(M38:O38) -> 3 | Q38: populares de todos os tempos #7; populares de todos os tempos #6 | W38: =COUNTA(Q38:V38) -> 1 | X38: =IF(P38=0,"",MIN(1,AVERAGE(M38:O38)+Critérios!$B$5*W38)) -> 0.80366667 | Y38: =IF(X38="","",IF(X38>=Critérios!$B$7,"A",IF(X38>=Critérios!$B$8,"B","C"))) -> A | Z38: =IF(X38="","",RANK(X38,$X$2:$X$354)) -> 37 | AA38: =IF(X38="","Sairia — sem métrica",IF(PERCENTRANK($X$2:$X$354,X38)<Critérios!$B$6,"Sairia — terço inferior","Fica")) -> Fica | AB38: a avaliar | AD38: candidato | AF38: S041, S186 | AG38: tt0468569 | AH38: =COUNT(G38,I38,K38)+COUNTA(Q38:V38) -> 4 | AI38: =IF(AH38>=3,"Sim","Não") -> Sim | AJ38: =IF(AND(Z38<>"",Z38<=Critérios!$B$9),"Sim","Não") -> Sim
A39: F0038 | B39: Os Incríveis 2 | C39: Incredibles 2 | D39: 2018 | E39: Não | F39: Bilheteria (Ancine/Wikipédia) | G39: 9809521 | H39: 145012895 | I39: 1242805359 | J39: 4 | K39: 378977 | L39: 7.5 | M39: =IF(G39="","",PERCENTRANK($G$2:$G$354,G39)) -> 0.961 | N39: =IF(I39="","",PERCENTRANK($I$2:$I$354,I39)) -> 0.881 | O39: =IF(K39="","",PERCENTRANK($K$2:$K$354,K39)) -> 0.446 | P39: =COUNT(M39:O39) -> 3 | Q39: 2018 populares #6 | W39: =COUNTA(Q39:V39) -> 1 | X39: =IF(P39=0,"",MIN(1,AVERAGE(M39:O39)+Critérios!$B$5*W39)) -> 0.79266667 | Y39: =IF(X39="","",IF(X39>=Critérios!$B$7,"A",IF(X39>=Critérios!$B$8,"B","C"))) -> A | Z39: =IF(X39="","",RANK(X39,$X$2:$X$354)) -> 38 | AA39: =IF(X39="","Sairia — sem métrica",IF(PERCENTRANK($X$2:$X$354,X39)<Critérios!$B$6,"Sairia — terço inferior","Fica")) -> Fica | AB39: ambíguo (provável) — conferir | AD39: candidato | AF39: S051, S191, S192, S201 | AG39: tt3606756 | AH39: =COUNT(G39,I39,K39)+COUNTA(Q39:V39) -> 4 | AI39: =IF(AH39>=3,"Sim","Não") -> Sim | AJ39: =IF(AND(Z39<>"",Z39<=Critérios!$B$9),"Sim","Não") -> Sim
A40: F0039 | B40: Deadpool | C40: Deadpool | D40: 2016 | E40: Não | F40: Bilheteria (Ancine/Wikipédia) | G40: 6044324 | H40: 81932430 | I40: 782612155 | J40: 9 | K40: 1275146 | L40: 8 | M40: =IF(G40="","",PERCENTRANK($G$2:$G$354,G40)) -> 0.807 | N40: =IF(I40="","",PERCENTRANK($I$2:$I$354,I40)) -> 0.525 | O40: =IF(K40="","",PERCENTRANK($K$2:$K$354,K40)) -> 0.952 | P40: =COUNT(M40:O40) -> 3 | Q40: 2016 populares #1 | W40: =COUNTA(Q40:V40) -> 1 | X40: =IF(P40=0,"",MIN(1,AVERAGE(M40:O40)+Critérios!$B$5*W40)) -> 0.79133333 | Y40: =IF(X40="","",IF(X40>=Critérios!$B$7,"A",IF(X40>=Critérios!$B$8,"B","C"))) -> A | Z40: =IF(X40="","",RANK(X40,$X$2:$X$354)) -> 39 | AA40: =IF(X40="","Sairia — sem métrica",IF(PERCENTRANK($X$2:$X$354,X40)<Critérios!$B$6,"Sairia — terço inferior","Fica")) -> Fica | AB40: a avaliar | AD40: candidato | AF40: S049, S207 | AG40: tt1431045 | AH40: =COUNT(G40,I40,K40)+COUNTA(Q40:V40) -> 4 | AI40: =IF(AH40>=3,"Sim","Não") -> Sim | AJ40: =IF(AND(Z40<>"",Z40<=Critérios!$B$9),"Sim","Não") -> Sim
A41: F0040 | B41: Liga da Justiça | C41: Justice League | D41: 2017 | E41: Não | F41: Bilheteria (Ancine/Wikipédia) | G41: 8671203 | H41: 136039247 | K41: 510990 | L41: 6 | M41: =IF(G41="","",PERCENTRANK($G$2:$G$354,G41)) -> 0.928 | N41: =IF(I41="","",PERCENTRANK($I$2:$I$354,I41)) | O41: =IF(K41="","",PERCENTRANK($K$2:$K$354,K41)) -> 0.591 | P41: =COUNT(M41:O41) -> 2 | Q41: 2017 populares #24 | W41: =COUNTA(Q41:V41) -> 1 | X41: =IF(P41=0,"",MIN(1,AVERAGE(M41:O41)+Critérios!$B$5*W41)) -> 0.7895 | Y41: =IF(X41="","",IF(X41>=Critérios!$B$7,"A",IF(X41>=Critérios!$B$8,"B","C"))) -> A | Z41: =IF(X41="","",RANK(X41,$X$2:$X$354)) -> 40 | AA41: =IF(X41="","Sairia — sem métrica",IF(PERCENTRANK($X$2:$X$354,X41)<Critérios!$B$6,"Sairia — terço inferior","Fica")) -> Fica | AB41: ambíguo (provável) — conferir | AD41: candidato | AF41: S191, S192, S201, S203 | AG41: tt0974015 | AH41: =COUNT(G41,I41,K41)+COUNTA(Q41:V41) -> 3 | AI41: =IF(AH41>=3,"Sim","Não") -> Sim | AJ41: =IF(AND(Z41<>"",Z41<=Critérios!$B$9),"Sim","Não") -> Sim
A42: F0041 | B42: O Rei Leão | C42: The Lion King | D42: 2019 | E42: Não | F42: Bilheteria (Ancine/Wikipédia) | G42: 16249234 | H42: 265902594 | I42: 1662943394 | J42: 2 | K42: 296360 | L42: 6.8 | M42: =IF(G42="","",PERCENTRANK($G$2:$G$354,G42)) -> 0.987 | N42: =IF(I42="","",PERCENTRANK($I$2:$I$354,I42)) -> 0.953 | O42: =IF(K42="","",PERCENTRANK($K$2:$K$354,K42)) -> 0.335 | P42: =COUNT(M42:O42) -> 3 | Q42: 2019 populares #24 | W42: =COUNTA(Q42:V42) -> 1 | X42: =IF(P42=0,"",MIN(1,AVERAGE(M42:O42)+Critérios!$B$5*W42)) -> 0.78833333 | Y42: =IF(X42="","",IF(X42>=Critérios!$B$7,"A",IF(X42>=Critérios!$B$8,"B","C"))) -> A | Z42: =IF(X42="","",RANK(X42,$X$2:$X$354)) -> 41 | AA42: =IF(X42="","Sairia — sem métrica",IF(PERCENTRANK($X$2:$X$354,X42)<Critérios!$B$6,"Sairia — terço inferior","Fica")) -> Fica | AB42: a avaliar | AD42: candidato | AF42: S052, S192, S201, S208 | AG42: tt6105098 | AH42: =COUNT(G42,I42,K42)+COUNTA(Q42:V42) -> 4 | AI42: =IF(AH42>=3,"Sim","Não") -> Sim | AJ42: =IF(AND(Z42<>"",Z42<=Critérios!$B$9),"Sim","Não") -> Sim
A43: F0042 | B43: Batman | C43: The Batman | D43: 2022 | E43: Não | F43: Bilheteria (Ancine/Wikipédia) | G43: 5809613 | H43: 114068386 | I43: 772245583 | J43: 7 | K43: 953108 | L43: 7.8 | M43: =IF(G43="","",PERCENTRANK($G$2:$G$354,G43)) -> 0.797 | N43: =IF(I43="","",PERCENTRANK($I$2:$I$354,I43)) -> 0.513 | O43: =IF(K43="","",PERCENTRANK($K$2:$K$354,K43)) -> 0.869 | P43: =COUNT(M43:O43) -> 3 | Q43: 2022 populares #1; populares de todos os tempos #9 | T43: 17–19 jun 2022 #7 (United States); 15–17 jul 2022 #8 (United States); 22–24 jul 2022 #9 (United States) | W43: =COUNTA(Q43:V43) -> 2 | X43: =IF(P43=0,"",MIN(1,AVERAGE(M43:O43)+Critérios!$B$5*W43)) -> 0.78633333 | Y43: =IF(X43="","",IF(X43>=Critérios!$B$7,"A",IF(X43>=Critérios!$B$8,"B","C"))) -> A | Z43: =IF(X43="","",RANK(X43,$X$2:$X$354)) -> 42 | AA43: =IF(X43="","Sairia — sem métrica",IF(PERCENTRANK($X$2:$X$354,X43)<Critérios!$B$6,"Sairia — terço inferior","Fica")) -> Fica | AB43: a avaliar | AD43: candidato | AF43: S055, S200 | AG43: tt1877830 | AH43: =COUNT(G43,I43,K43)+COUNTA(Q43:V43) -> 5 | AI43: =IF(AH43>=3,"Sim","Não") -> Sim | AJ43: =IF(AND(Z43<>"",Z43<=Critérios!$B$9),"Sim","Não") -> Sim
A44: F0043 | B44: Thor: Ragnarok | C44: Thor: Ragnarok | D44: 2017 | E44: Não | F44: Bilheteria (Ancine/Wikipédia) | G44: 6359663 | H44: 99761710 | I44: 853983911 | J44: 9 | K44: 916614 | L44: 7.9 | M44: =IF(G44="","",PERCENTRANK($G$2:$G$354,G44)) -> 0.827 | N44: =IF(I44="","",PERCENTRANK($I$2:$I$354,I44)) -> 0.597 | O44: =IF(K44="","",PERCENTRANK($K$2:$K$354,K44)) -> 0.841 | P44: =COUNT(M44:O44) -> 3 | Q44: 2017 populares #12 | W44: =COUNTA(Q44:V44) -> 1 | X44: =IF(P44=0,"",MIN(1,AVERAGE(M44:O44)+Critérios!$B$5*W44)) -> 0.785 | Y44: =IF(X44="","",IF(X44>=Critérios!$B$7,"A",IF(X44>=Critérios!$B$8,"B","C"))) -> A | Z44: =IF(X44="","",RANK(X44,$X$2:$X$354)) -> 43 | AA44: =IF(X44="","Sairia — sem métrica",IF(PERCENTRANK($X$2:$X$354,X44)<Critérios!$B$6,"Sairia — terço inferior","Fica")) -> Fica | AB44: a avaliar | AD44: candidato | AF44: S050, S203 | AG44: tt3501632 | AH44: =COUNT(G44,I44,K44)+COUNTA(Q44:V44) -> 4 | AI44: =IF(AH44>=3,"Sim","Não") -> Sim | AJ44: =IF(AND(Z44<>"",Z44<=Critérios!$B$9),"Sim","Não") -> Sim
A45: F0044 | B45: Toy Story 3 | C45: Toy Story 3 | D45: 2010 | E45: Não | F45: Bilheteria (Ancine/Wikipédia) | G45: 4351729 | H45: 42384195 | I45: 1066969703 | J45: 1 | K45: 993536 | L45: 8.3 | M45: =IF(G45="","",PERCENTRANK($G$2:$G$354,G45)) -> 0.634 | N45: =IF(I45="","",PERCENTRANK($I$2:$I$354,I45)) -> 0.809 | O45: =IF(K45="","",PERCENTRANK($K$2:$K$354,K45)) -> 0.895 | P45: =COUNT(M45:O45) -> 3 | W45: =COUNTA(Q45:V45) -> 0 | X45: =IF(P45=0,"",MIN(1,AVERAGE(M45:O45)+Critérios!$B$5*W45)) -> 0.77933333 | Y45: =IF(X45="","",IF(X45>=Critérios!$B$7,"A",IF(X45>=Critérios!$B$8,"B","C"))) -> A | Z45: =IF(X45="","",RANK(X45,$X$2:$X$354)) -> 44 | AA45: =IF(X45="","Sairia — sem métrica",IF(PERCENTRANK($X$2:$X$354,X45)<Critérios!$B$6,"Sairia — terço inferior","Fica")) -> Fica | AB45: a avaliar | AD45: candidato | AF45: S043, S204 | AG45: tt0435761 | AH45: =COUNT(G45,I45,K45)+COUNTA(Q45:V45) -> 3 | AI45: =IF(AH45>=3,"Sim","Não") -> Sim | AJ45: =IF(AND(Z45<>"",Z45<=Critérios!$B$9),"Sim","Não") -> Sim
A46: F0045 | B46: Divertida Mente 2 | C46: Inside Out 2 | D46: 2024 | E46: Não | F46: Bilheteria (Ancine/Wikipédia) | G46: 22159705 | H46: 442101148 | I46: 1698863816 | J46: 1 | K46: 262004 | L46: 7.5 | M46: =IF(G46="","",PERCENTRANK($G$2:$G$354,G46)) -> 1 | N46: =IF(I46="","",PERCENTRANK($I$2:$I$354,I46)) -> 0.962 | O46: =IF(K46="","",PERCENTRANK($K$2:$K$354,K46)) -> 0.267 | P46: =COUNT(M46:O46) -> 3 | Q46: 2024 populares #5 | W46: =COUNTA(Q46:V46) -> 1 | X46: =IF(P46=0,"",MIN(1,AVERAGE(M46:O46)+Critérios!$B$5*W46)) -> 0.773 | Y46: =IF(X46="","",IF(X46>=Critérios!$B$7,"A",IF(X46>=Critérios!$B$8,"B","C"))) -> A | Z46: =IF(X46="","",RANK(X46,$X$2:$X$354)) -> 45 | AA46: =IF(X46="","Sairia — sem métrica",IF(PERCENTRANK($X$2:$X$354,X46)<Critérios!$B$6,"Sairia — terço inferior","Fica")) -> Fica | AB46: ambíguo (provável) — conferir | AD46: candidato | AF46: S057, S192, S209 | AG46: tt22022452 | AH46: =COUNT(G46,I46,K46)+COUNTA(Q46:V46) -> 4 | AI46: =IF(AH46>=3,"Sim","Não") -> Sim | AJ46: =IF(AND(Z46<>"",Z46<=Critérios!$B$9),"Sim","Não") -> Sim
A47: F0046 | B47: A Bela e a Fera | C47: Beauty and the Beast | D47: 2017 | E47: Não | F47: Bilheteria (Ancine/Wikipédia) | G47: 8308655 | H47: 130086233 | I47: 1263521126 | J47: 2 | K47: 363573 | L47: 7.1 | M47: =IF(G47="","",PERCENTRANK($G$2:$G$354,G47)) -> 0.912 | N47: =IF(I47="","",PERCENTRANK($I$2:$I$354,I47)) -> 0.886 | O47: =IF(K47="","",PERCENTRANK($K$2:$K$354,K47)) -> 0.423 | P47: =COUNT(M47:O47) -> 3 | Q47: 2017 populares #18 | W47: =COUNTA(Q47:V47) -> 1 | X47: =IF(P47=0,"",MIN(1,AVERAGE(M47:O47)+Critérios!$B$5*W47)) -> 0.77033333 | Y47: =IF(X47="","",IF(X47>=Critérios!$B$7,"A",IF(X47>=Critérios!$B$8,"B","C"))) -> A | Z47: =IF(X47="","",RANK(X47,$X$2:$X$354)) -> 46 | AA47: =IF(X47="","Sairia — sem métrica",IF(PERCENTRANK($X$2:$X$354,X47)<Critérios!$B$6,"Sairia — terço inferior","Fica")) -> Fica | AB47: a avaliar | AD47: candidato | AF47: S050, S191, S203 | AG47: tt2771200 | AH47: =COUNT(G47,I47,K47)+COUNTA(Q47:V47) -> 4 | AI47: =IF(AH47>=3,"Sim","Não") -> Sim | AJ47: =IF(AND(Z47<>"",Z47<=Critérios!$B$9),"Sim","Não") -> Sim
A48: F0047 | B48: Aquaman | C48: Aquaman | D48: 2018 | E48: Não | F48: Bilheteria (Ancine/Wikipédia) | G48: 5584309 | H48: 92326364 | I48: 1148528393 | J48: 5 | K48: 561069 | L48: 6.8 | M48: =IF(G48="","",PERCENTRANK($G$2:$G$354,G48)) -> 0.781 | N48: =IF(I48="","",PERCENTRANK($I$2:$I$354,I48)) -> 0.86 | O48: =IF(K48="","",PERCENTRANK($K$2:$K$354,K48)) -> 0.639 | P48: =COUNT(M48:O48) -> 3 | W48: =COUNTA(Q48:V48) -> 0 | X48: =IF(P48=0,"",MIN(1,AVERAGE(M48:O48)+Critérios!$B$5*W48)) -> 0.76 | Y48: =IF(X48="","",IF(X48>=Critérios!$B$7,"A",IF(X48>=Critérios!$B$8,"B","C"))) -> A | Z48: =IF(X48="","",RANK(X48,$X$2:$X$354)) -> 47 | AA48: =IF(X48="","Sairia — sem métrica",IF(PERCENTRANK($X$2:$X$354,X48)<Critérios!$B$6,"Sairia — terço inferior","Fica")) -> Fica | AB48: a avaliar | AD48: candidato | AF48: S051, S191, S208 | AG48: tt1477834 | AH48: =COUNT(G48,I48,K48)+COUNTA(Q48:V48) -> 3 | AI48: =IF(AH48>=3,"Sim","Não") -> Sim | AJ48: =IF(AND(Z48<>"",Z48<=Critérios!$B$9),"Sim","Não") -> Sim
A49: F0048 | B49: Super Mario Bros.: O Filme | C49: The Super Mario Bros. Movie | D49: 2023 | E49: Não | F49: Bilheteria (Ancine/Wikipédia) | G49: 6564765 | H49: 133245440 | I49: 1360847665 | J49: 2 | K49: 303322 | L49: 7 | M49: =IF(G49="","",PERCENTRANK($G$2:$G$354,G49)) -> 0.84 | N49: =IF(I49="","",PERCENTRANK($I$2:$I$354,I49)) -> 0.915 | O49: =IF(K49="","",PERCENTRANK($K$2:$K$354,K49)) -> 0.341 | P49: =COUNT(M49:O49) -> 3 | Q49: 2023 populares #5 | S49: 2023 #3; 2024 #2 | W49: =COUNTA(Q49:V49) -> 2 | X49: =IF(P49=0,"",MIN(1,AVERAGE(M49:O49)+Critérios!$B$5*W49)) -> 0.75866667 | Y49: =IF(X49="","",IF(X49>=Critérios!$B$7,"A",IF(X49>=Critérios!$B$8,"B","C"))) -> A | Z49: =IF(X49="","",RANK(X49,$X$2:$X$354)) -> 48 | AA49: =IF(X49="","Sairia — sem métrica",IF(PERCENTRANK($X$2:$X$354,X49)<Critérios!$B$6,"Sairia — terço inferior","Fica")) -> Fica | AB49: a avaliar | AD49: candidato | AF49: S056, S201 | AG49: tt6718170 | AH49: =COUNT(G49,I49,K49)+COUNTA(Q49:V49) -> 5 | AI49: =IF(AH49>=3,"Sim","Não") -> Sim | AJ49: =IF(AND(Z49<>"",Z49<=Critérios!$B$9),"Sim","Não") -> Sim
A50: F0049 | B50: Mulher-Maravilha | C50: Wonder Woman | D50: 2017 | E50: Não | F50: Bilheteria (Ancine/Wikipédia) | G50: 7011338 | H50: 109894366 | I50: 822303505 | J50: 10 | K50: 743053 | L50: 7.3 | M50: =IF(G50="","",PERCENTRANK($G$2:$G$354,G50)) -> 0.856 | N50: =IF(I50="","",PERCENTRANK($I$2:$I$354,I50)) -> 0.572 | O50: =IF(K50="","",PERCENTRANK($K$2:$K$354,K50)) -> 0.753 | P50: =COUNT(M50:O50) -> 3 | Q50: 2017 populares #5 | W50: =COUNTA(Q50:V50) -> 1 | X50: =IF(P50=0,"",MIN(1,AVERAGE(M50:O50)+Critérios!$B$5*W50)) -> 0.757 | Y50: =IF(X50="","",IF(X50>=Critérios!$B$7,"A",IF(X50>=Critérios!$B$8,"B","C"))) -> A | Z50: =IF(X50="","",RANK(X50,$X$2:$X$354)) -> 49 | AA50: =IF(X50="","Sairia — sem métrica",IF(PERCENTRANK($X$2:$X$354,X50)<Critérios!$B$6,"Sairia — terço inferior","Fica")) -> Fica | AB50: a avaliar | AD50: candidato | AF50: S050, S203 | AG50: tt0451279 | AH50: =COUNT(G50,I50,K50)+COUNTA(Q50:V50) -> 4 | AI50: =IF(AH50>=3,"Sim","Não") -> Sim | AJ50: =IF(AND(Z50<>"",Z50<=Critérios!$B$9),"Sim","Não") -> Sim
A51: F0050 | B51: Procurando Nemo | C51: Finding Nemo | D51: 2003 | E51: Não | F51: Bilheteria (Ancine/Wikipédia) | G51: 4743030 | H51: 27308124 | I51: 871014978 | J51: 2 | K51: 1228269 | L51: 8.2 | M51: =IF(G51="","",PERCENTRANK($G$2:$G$354,G51)) -> 0.703 | N51: =IF(I51="","",PERCENTRANK($I$2:$I$354,I51)) -> 0.623 | O51: =IF(K51="","",PERCENTRANK($K$2:$K$354,K51)) -> 0.938 | P51: =COUNT(M51:O51) -> 3 | W51: =COUNTA(Q51:V51) -> 0 | X51: =IF(P51=0,"",MIN(1,AVERAGE(M51:O51)+Critérios!$B$5*W51)) -> 0.75466667 | Y51: =IF(X51="","",IF(X51>=Critérios!$B$7,"A",IF(X51>=Critérios!$B$8,"B","C"))) -> A | Z51: =IF(X51="","",RANK(X51,$X$2:$X$354)) -> 50 | AA51: =IF(X51="","Sairia — sem métrica",IF(PERCENTRANK($X$2:$X$354,X51)<Critérios!$B$6,"Sairia — terço inferior","Fica")) -> Fica | AB51: a avaliar | AD51: candidato | AF51: S036, S181 | AG51: tt0266543 | AH51: =COUNT(G51,I51,K51)+COUNTA(Q51:V51) -> 3 | AI51: =IF(AH51>=3,"Sim","Não") -> Sim | AJ51: =IF(AND(Z51<>"",Z51<=Critérios!$B$9),"Sim","Não") -> Sim
A52: F0051 | B52: Harry Potter e a Pedra Filosofal | C52: Harry Potter and the Philosopher's Stone | D52: 2001 | E52: Não | F52: Bilheteria (Ancine/Wikipédia) | G52: 4399487 | H52: 22904233 | I52: 974755371 | J52: 1 | K52: 970153 | L52: 7.7 | M52: =IF(G52="","",PERCENTRANK($G$2:$G$354,G52)) -> 0.647 | N52: =IF(I52="","",PERCENTRANK($I$2:$I$354,I52)) -> 0.737 | O52: =IF(K52="","",PERCENTRANK($K$2:$K$354,K52)) -> 0.878 | P52: =COUNT(M52:O52) -> 3 | W52: =COUNTA(Q52:V52) -> 0 | X52: =IF(P52=0,"",MIN(1,AVERAGE(M52:O52)+Critérios!$B$5*W52)) -> 0.754 | Y52: =IF(X52="","",IF(X52>=Critérios!$B$7,"A",IF(X52>=Critérios!$B$8,"B","C"))) -> A | Z52: =IF(X52="","",RANK(X52,$X$2:$X$354)) -> 51 | AA52: =IF(X52="","Sairia — sem métrica",IF(PERCENTRANK($X$2:$X$354,X52)<Critérios!$B$6,"Sairia — terço inferior","Fica")) -> Fica | AB52: a avaliar | AD52: candidato | AF52: S034, S179 | AG52: tt0241527 | AH52: =COUNT(G52,I52,K52)+COUNTA(Q52:V52) -> 3 | AI52: =IF(AH52>=3,"Sim","Não") -> Sim | AJ52: =IF(AND(Z52<>"",Z52<=Critérios!$B$9),"Sim","Não") -> Não
A53: F0052 | B53: O Senhor dos Anéis: As Duas Torres | C53: The Lord of the Rings: The Two Towers | D53: 2002 | E53: Não | F53: Bilheteria (Ancine/Wikipédia) | G53: 4133452 | H53: 26319044 | I53: 936689735 | J53: 1 | K53: 1990244 | L53: 8.8 | M53: =IF(G53="","",PERCENTRANK($G$2:$G$354,G53)) -> 0.595 | N53: =IF(I53="","",PERCENTRANK($I$2:$I$354,I53)) -> 0.682 | O53: =IF(K53="","",PERCENTRANK($K$2:$K$354,K53)) -> 0.983 | P53: =COUNT(M53:O53) -> 3 | W53: =COUNTA(Q53:V53) -> 0 | X53: =IF(P53=0,"",MIN(1,AVERAGE(M53:O53)+Critérios!$B$5*W53)) -> 0.75333333 | Y53: =IF(X53="","",IF(X53>=Critérios!$B$7,"A",IF(X53>=Critérios!$B$8,"B","C"))) -> A | Z53: =IF(X53="","",RANK(X53,$X$2:$X$354)) -> 52 | AA53: =IF(X53="","Sairia — sem métrica",IF(PERCENTRANK($X$2:$X$354,X53)<Critérios!$B$6,"Sairia — terço inferior","Fica")) -> Fica | AB53: ambíguo (provável) — conferir | AD53: candidato | AF53: S035, S180 | AG53: tt0167261 | AH53: =COUNT(G53,I53,K53)+COUNTA(Q53:V53) -> 3 | AI53: =IF(AH53>=3,"Sim","Não") -> Sim | AJ53: =IF(AND(Z53<>"",Z53<=Critérios!$B$9),"Sim","Não") -> Não
A54: F0053 | B54: O Senhor dos Anéis: A Sociedade do Anel | C54: The Lord of the Rings: The Fellowship of the Ring | D54: 2001 | E54: Não | F54: Bilheteria (Ancine/Wikipédia) | G54: 4286797 | H54: 24560341 | I54: 883726270 | J54: 2 | K54: 2244376 | L54: 8.9 | M54: =IF(G54="","",PERCENTRANK($G$2:$G$354,G54)) -> 0.611 | N54: =IF(I54="","",PERCENTRANK($I$2:$I$354,I54)) -> 0.653 | O54: =IF(K54="","",PERCENTRANK($K$2:$K$354,K54)) -> 0.991 | P54: =COUNT(M54:O54) -> 3 | W54: =COUNTA(Q54:V54) -> 0 | X54: =IF(P54=0,"",MIN(1,AVERAGE(M54:O54)+Critérios!$B$5*W54)) -> 0.75166667 | Y54: =IF(X54="","",IF(X54>=Critérios!$B$7,"A",IF(X54>=Critérios!$B$8,"B","C"))) -> A | Z54: =IF(X54="","",RANK(X54,$X$2:$X$354)) -> 53 | AA54: =IF(X54="","Sairia — sem métrica",IF(PERCENTRANK($X$2:$X$354,X54)<Critérios!$B$6,"Sairia — terço inferior","Fica")) -> Fica | AB54: ambíguo (provável) — conferir | AD54: candidato | AF54: S034, S180 | AG54: tt0120737 | AH54: =COUNT(G54,I54,K54)+COUNTA(Q54:V54) -> 3 | AI54: =IF(AH54>=3,"Sim","Não") -> Sim | AJ54: =IF(AND(Z54<>"",Z54<=Critérios!$B$9),"Sim","Não") -> Não
A55: F0054 | B55: Interestelar | C55: Interstellar | D55: 2014 | E55: Não | F55: Bilheteria (Ancine/Wikipédia) | I55: 677896797 | J55: 10 | K55: 2620054 | L55: 8.7 | M55: =IF(G55="","",PERCENTRANK($G$2:$G$354,G55)) | N55: =IF(I55="","",PERCENTRANK($I$2:$I$354,I55)) -> 0.377 | O55: =IF(K55="","",PERCENTRANK($K$2:$K$354,K55)) -> 0.994 | P55: =COUNT(M55:O55) -> 2 | Q55: populares de todos os tempos #2; populares de todos os tempos #5 | R55: #90 hoje | W55: =COUNTA(Q55:V55) -> 2 | X55: =IF(P55=0,"",MIN(1,AVERAGE(M55:O55)+Critérios!$B$5*W55)) -> 0.7455 | Y55: =IF(X55="","",IF(X55>=Critérios!$B$7,"A",IF(X55>=Critérios!$B$8,"B","C"))) -> A | Z55: =IF(X55="","",RANK(X55,$X$2:$X$354)) -> 54 | AA55: =IF(X55="","Sairia — sem métrica",IF(PERCENTRANK($X$2:$X$354,X55)<Critérios!$B$6,"Sairia — terço inferior","Fica")) -> Fica | AB55: a avaliar | AD55: candidato | AF55: S047 | AG55: tt0816692 | AH55: =COUNT(G55,I55,K55)+COUNTA(Q55:V55) -> 4 | AI55: =IF(AH55>=3,"Sim","Não") -> Sim | AJ55: =IF(AND(Z55<>"",Z55<=Critérios!$B$9),"Sim","Não") -> Não
A56: F0055 | B56: Esquadrão Suicida | C56: Suicide Squad | D56: 2016 | E56: Não | F56: Bilheteria (Ancine/Wikipédia) | G56: 7827788 | H56: 118081264 | I56: 746846894 | J56: 10 | K56: 768318 | L56: 5.9 | M56: =IF(G56="","",PERCENTRANK($G$2:$G$354,G56)) -> 0.892 | N56: =IF(I56="","",PERCENTRANK($I$2:$I$354,I56)) -> 0.47 | O56: =IF(K56="","",PERCENTRANK($K$2:$K$354,K56)) -> 0.773 | P56: =COUNT(M56:O56) -> 3 | Q56: 2016 populares #10 | W56: =COUNTA(Q56:V56) -> 1 | X56: =IF(P56=0,"",MIN(1,AVERAGE(M56:O56)+Critérios!$B$5*W56)) -> 0.74166667 | Y56: =IF(X56="","",IF(X56>=Critérios!$B$7,"A",IF(X56>=Critérios!$B$8,"B","C"))) -> A | Z56: =IF(X56="","",RANK(X56,$X$2:$X$354)) -> 56 | AA56: =IF(X56="","Sairia — sem métrica",IF(PERCENTRANK($X$2:$X$354,X56)<Critérios!$B$6,"Sairia — terço inferior","Fica")) -> Fica | AB56: ambíguo (provável) — conferir | AD56: candidato | AF56: S049, S207 | AG56: tt1386697 | AH56: =COUNT(G56,I56,K56)+COUNTA(Q56:V56) -> 4 | AI56: =IF(AH56>=3,"Sim","Não") -> Sim | AJ56: =IF(AND(Z56<>"",Z56<=Critérios!$B$9),"Sim","Não") -> Não
A57: F0056 | B57: Frozen 2 | C57: Frozen 2 | D57: 2019 | E57: Não | F57: Bilheteria (Ancine/Wikipédia) | G57: 7858713 | H57: 122114844 | I57: 1453026933 | J57: 3 | K57: 224374 | L57: 6.8 | M57: =IF(G57="","",PERCENTRANK($G$2:$G$354,G57)) -> 0.895 | N57: =IF(I57="","",PERCENTRANK($I$2:$I$354,I57)) -> 0.928 | O57: =IF(K57="","",PERCENTRANK($K$2:$K$354,K57)) -> 0.222 | P57: =COUNT(M57:O57) -> 3 | Q57: 2019 populares #45 | S57: 2020 #1; 2021 #4; 2022 #14 | W57: =COUNTA(Q57:V57) -> 2 | X57: =IF(P57=0,"",MIN(1,AVERAGE(M57:O57)+Critérios!$B$5*W57)) -> 0.74166667 | Y57: =IF(X57="","",IF(X57>=Critérios!$B$7,"A",IF(X57>=Critérios!$B$8,"B","C"))) -> A | Z57: =IF(X57="","",RANK(X57,$X$2:$X$354)) -> 55 | AA57: =IF(X57="","Sairia — sem métrica",IF(PERCENTRANK($X$2:$X$354,X57)<Critérios!$B$6,"Sairia — terço inferior","Fica")) -> Fica | AB57: ambíguo (provável) — conferir | AD57: candidato | AF57: S052, S198 | AG57: tt4520988 | AH57: =COUNT(G57,I57,K57)+COUNTA(Q57:V57) -> 5 | AI57: =IF(AH57>=3,"Sim","Não") -> Sim | AJ57: =IF(AND(Z57<>"",Z57<=Critérios!$B$9),"Sim","Não") -> Não
A58: F0057 | B58: Homem-Aranha 2 | C58: Spider-Man 2 | D58: 2004 | E58: Não | F58: Bilheteria (Ancine/Wikipédia) | G58: 7737714 | H58: 48154529 | I58: 783766341 | J58: 3 | K58: 811419 | L58: 7.5 | M58: =IF(G58="","",PERCENTRANK($G$2:$G$354,G58)) -> 0.882 | N58: =IF(I58="","",PERCENTRANK($I$2:$I$354,I58)) -> 0.53 | O58: =IF(K58="","",PERCENTRANK($K$2:$K$354,K58)) -> 0.804 | P58: =COUNT(M58:O58) -> 3 | W58: =COUNTA(Q58:V58) -> 0 | X58: =IF(P58=0,"",MIN(1,AVERAGE(M58:O58)+Critérios!$B$5*W58)) -> 0.73866667 | Y58: =IF(X58="","",IF(X58>=Critérios!$B$7,"A",IF(X58>=Critérios!$B$8,"B","C"))) -> A | Z58: =IF(X58="","",RANK(X58,$X$2:$X$354)) -> 57 | AA58: =IF(X58="","Sairia — sem métrica",IF(PERCENTRANK($X$2:$X$354,X58)<Critérios!$B$6,"Sairia — terço inferior","Fica")) -> Fica | AB58: a avaliar | AD58: candidato | AF58: S037, S182 | AG58: tt0316654 | AH58: =COUNT(G58,I58,K58)+COUNTA(Q58:V58) -> 3 | AI58: =IF(AH58>=3,"Sim","Não") -> Sim | AJ58: =IF(AND(Z58<>"",Z58<=Critérios!$B$9),"Sim","Não") -> Não
A59: F0058 | B59: Homem-Aranha 3 | C59: Spider-Man 3 | D59: 2007 | E59: Não | F59: Bilheteria (Ancine/Wikipédia) | G59: 6141200 | H59: 48941000 | I59: 895871626 | J59: 3 | K59: 722265 | L59: 6.3 | M59: =IF(G59="","",PERCENTRANK($G$2:$G$354,G59)) -> 0.81 | N59: =IF(I59="","",PERCENTRANK($I$2:$I$354,I59)) -> 0.661 | O59: =IF(K59="","",PERCENTRANK($K$2:$K$354,K59)) -> 0.741 | P59: =COUNT(M59:O59) -> 3 | W59: =COUNTA(Q59:V59) -> 0 | X59: =IF(P59=0,"",MIN(1,AVERAGE(M59:O59)+Critérios!$B$5*W59)) -> 0.73733333 | Y59: =IF(X59="","",IF(X59>=Critérios!$B$7,"A",IF(X59>=Critérios!$B$8,"B","C"))) -> A | Z59: =IF(X59="","",RANK(X59,$X$2:$X$354)) -> 58 | AA59: =IF(X59="","Sairia — sem métrica",IF(PERCENTRANK($X$2:$X$354,X59)<Critérios!$B$6,"Sairia — terço inferior","Fica")) -> Fica | AB59: a avaliar | AD59: candidato | AF59: S040, S185 | AG59: tt0413300 | AH59: =COUNT(G59,I59,K59)+COUNTA(Q59:V59) -> 3 | AI59: =IF(AH59>=3,"Sim","Não") -> Sim | AJ59: =IF(AND(Z59<>"",Z59<=Critérios!$B$9),"Sim","Não") -> Não
A60: F0059 | B60: Toy Story 4 | C60: Toy Story 4 | D60: 2019 | E60: Não | F60: Bilheteria (Ancine/Wikipédia) | G60: 7955544 | H60: 124444046 | I60: 1074841294 | J60: 8 | K60: 331762 | L60: 7.6 | M60: =IF(G60="","",PERCENTRANK($G$2:$G$354,G60)) -> 0.902 | N60: =IF(I60="","",PERCENTRANK($I$2:$I$354,I60)) -> 0.814 | O60: =IF(K60="","",PERCENTRANK($K$2:$K$354,K60)) -> 0.395 | P60: =COUNT(M60:O60) -> 3 | Q60: 2019 populares #14 | W60: =COUNTA(Q60:V60) -> 1 | X60: =IF(P60=0,"",MIN(1,AVERAGE(M60:O60)+Critérios!$B$5*W60)) -> 0.73366667 | Y60: =IF(X60="","",IF(X60>=Critérios!$B$7,"A",IF(X60>=Critérios!$B$8,"B","C"))) -> A | Z60: =IF(X60="","",RANK(X60,$X$2:$X$354)) -> 59 | AA60: =IF(X60="","Sairia — sem métrica",IF(PERCENTRANK($X$2:$X$354,X60)<Critérios!$B$6,"Sairia — terço inferior","Fica")) -> Fica | AB60: a avaliar | AD60: candidato | AF60: S052, S208 | AG60: tt1979376 | AH60: =COUNT(G60,I60,K60)+COUNTA(Q60:V60) -> 4 | AI60: =IF(AH60>=3,"Sim","Não") -> Sim | AJ60: =IF(AND(Z60<>"",Z60<=Critérios!$B$9),"Sim","Não") -> Não
A61: F0060 | B61: Oppenheimer | C61: Oppenheimer | D61: 2023 | E61: Não | F61: Bilheteria (Ancine/Wikipédia) | G61: 2937482 | H61: 66571860 | I61: 975811333 | J61: 3 | K61: 1104898 | L61: 8.2 | M61: =IF(G61="","",PERCENTRANK($G$2:$G$354,G61)) -> 0.441 | N61: =IF(I61="","",PERCENTRANK($I$2:$I$354,I61)) -> 0.742 | O61: =IF(K61="","",PERCENTRANK($K$2:$K$354,K61)) -> 0.923 | P61: =COUNT(M61:O61) -> 3 | Q61: 2023 populares #2; 2023 mais bem avaliados #3 | W61: =COUNTA(Q61:V61) -> 1 | X61: =IF(P61=0,"",MIN(1,AVERAGE(M61:O61)+Critérios!$B$5*W61)) -> 0.732 | Y61: =IF(X61="","",IF(X61>=Critérios!$B$7,"A",IF(X61>=Critérios!$B$8,"B","C"))) -> A | Z61: =IF(X61="","",RANK(X61,$X$2:$X$354)) -> 60 | AA61: =IF(X61="","Sairia — sem métrica",IF(PERCENTRANK($X$2:$X$354,X61)<Critérios!$B$6,"Sairia — terço inferior","Fica")) -> Fica | AB61: a avaliar | AD61: candidato | AF61: S056, S201 | AG61: tt15398776 | AH61: =COUNT(G61,I61,K61)+COUNTA(Q61:V61) -> 4 | AI61: =IF(AH61>=3,"Sim","Não") -> Sim | AJ61: =IF(AND(Z61<>"",Z61<=Critérios!$B$9),"Sim","Não") -> Não
A62: F0061 | B62: Velozes e Furiosos 8 | C62: The Fate of the Furious | D62: 2017 | E62: Não | F62: Bilheteria (Ancine/Wikipédia) | G62: 8505215 | H62: 133423662 | I62: 1236005118 | J62: 3 | K62: 279450 | L62: 6.6 | M62: =IF(G62="","",PERCENTRANK($G$2:$G$354,G62)) -> 0.922 | N62: =IF(I62="","",PERCENTRANK($I$2:$I$354,I62)) -> 0.877 | O62: =IF(K62="","",PERCENTRANK($K$2:$K$354,K62)) -> 0.307 | P62: =COUNT(M62:O62) -> 3 | Q62: 2017 populares #50 | W62: =COUNTA(Q62:V62) -> 1 | X62: =IF(P62=0,"",MIN(1,AVERAGE(M62:O62)+Critérios!$B$5*W62)) -> 0.732 | Y62: =IF(X62="","",IF(X62>=Critérios!$B$7,"A",IF(X62>=Critérios!$B$8,"B","C"))) -> A | Z62: =IF(X62="","",RANK(X62,$X$2:$X$354)) -> 60 | AA62: =IF(X62="","Sairia — sem métrica",IF(PERCENTRANK($X$2:$X$354,X62)<Critérios!$B$6,"Sairia — terço inferior","Fica")) -> Fica | AB62: ambíguo (provável) — conferir | AD62: candidato | AF62: S050, S191, S203 | AG62: tt4630562 | AH62: =COUNT(G62,I62,K62)+COUNTA(Q62:V62) -> 4 | AI62: =IF(AH62>=3,"Sim","Não") -> Sim | AJ62: =IF(AND(Z62<>"",Z62<=Critérios!$B$9),"Sim","Não") -> Não
A63: F0062 | B63: Frozen: uma Aventura Congelante | C63: Frozen | D63: 2013 | E63: Não | F63: Bilheteria (Ancine/Wikipédia) | G63: 3931888 | H63: 47341817 | I63: 1280802282 | J63: 1 | K63: 722930 | L63: 7.4 | M63: =IF(G63="","",PERCENTRANK($G$2:$G$354,G63)) -> 0.556 | N63: =IF(I63="","",PERCENTRANK($I$2:$I$354,I63)) -> 0.89 | O63: =IF(K63="","",PERCENTRANK($K$2:$K$354,K63)) -> 0.744 | P63: =COUNT(M63:O63) -> 3 | W63: =COUNTA(Q63:V63) -> 0 | X63: =IF(P63=0,"",MIN(1,AVERAGE(M63:O63)+Critérios!$B$5*W63)) -> 0.73 | Y63: =IF(X63="","",IF(X63>=Critérios!$B$7,"A",IF(X63>=Critérios!$B$8,"B","C"))) -> A | Z63: =IF(X63="","",RANK(X63,$X$2:$X$354)) -> 62 | AA63: =IF(X63="","Sairia — sem métrica",IF(PERCENTRANK($X$2:$X$354,X63)<Critérios!$B$6,"Sairia — terço inferior","Fica")) -> Fica | AB63: ambíguo (provável) — conferir | AD63: candidato | AF63: S046, S206 | AG63: tt2294629 | AH63: =COUNT(G63,I63,K63)+COUNTA(Q63:V63) -> 3 | AI63: =IF(AH63>=3,"Sim","Não") -> Sim | AJ63: =IF(AND(Z63<>"",Z63<=Critérios!$B$9),"Sim","Não") -> Não
A64: F0063 | B64: Jurassic World – Reino Ameaçado | C64: Jurassic World: Fallen Kingdom | D64: 2018 | E64: Não | F64: Bilheteria (Ancine/Wikipédia) | G64: 5258742 | H64: 80619075 | I64: 1308467944 | J64: 3 | K64: 388793 | L64: 6.2 | M64: =IF(G64="","",PERCENTRANK($G$2:$G$354,G64)) -> 0.755 | N64: =IF(I64="","",PERCENTRANK($I$2:$I$354,I64)) -> 0.894 | O64: =IF(K64="","",PERCENTRANK($K$2:$K$354,K64)) -> 0.449 | P64: =COUNT(M64:O64) -> 3 | Q64: 2018 populares #22 | W64: =COUNTA(Q64:V64) -> 1 | X64: =IF(P64=0,"",MIN(1,AVERAGE(M64:O64)+Critérios!$B$5*W64)) -> 0.72933333 | Y64: =IF(X64="","",IF(X64>=Critérios!$B$7,"A",IF(X64>=Critérios!$B$8,"B","C"))) -> A | Z64: =IF(X64="","",RANK(X64,$X$2:$X$354)) -> 63 | AA64: =IF(X64="","Sairia — sem métrica",IF(PERCENTRANK($X$2:$X$354,X64)<Critérios!$B$6,"Sairia — terço inferior","Fica")) -> Fica | AB64: ambíguo (provável) — conferir | AD64: candidato | AF64: S051, S191 | AG64: tt4881806 | AH64: =COUNT(G64,I64,K64)+COUNTA(Q64:V64) -> 4 | AI64: =IF(AH64>=3,"Sim","Não") -> Sim | AJ64: =IF(AND(Z64<>"",Z64<=Critérios!$B$9),"Sim","Não") -> Não
A65: F0064 | B65: Procurando Dory | C65: Finding Dory | D65: 2016 | E65: Não | F65: Bilheteria (Ancine/Wikipédia) | G65: 8189410 | H65: 113497532 | I65: 1029266989 | J65: 3 | K65: 341039 | L65: 7.2 | M65: =IF(G65="","",PERCENTRANK($G$2:$G$354,G65)) -> 0.905 | N65: =IF(I65="","",PERCENTRANK($I$2:$I$354,I65)) -> 0.775 | O65: =IF(K65="","",PERCENTRANK($K$2:$K$354,K65)) -> 0.401 | P65: =COUNT(M65:O65) -> 3 | Q65: 2016 populares #14 | W65: =COUNTA(Q65:V65) -> 1 | X65: =IF(P65=0,"",MIN(1,AVERAGE(M65:O65)+Critérios!$B$5*W65)) -> 0.72366667 | Y65: =IF(X65="","",IF(X65>=Critérios!$B$7,"A",IF(X65>=Critérios!$B$8,"B","C"))) -> A | Z65: =IF(X65="","",RANK(X65,$X$2:$X$354)) -> 64 | AA65: =IF(X65="","Sairia — sem métrica",IF(PERCENTRANK($X$2:$X$354,X65)<Critérios!$B$6,"Sairia — terço inferior","Fica")) -> Fica | AB65: a avaliar | AD65: candidato | AF65: S049, S207 | AG65: tt2277860 | AH65: =COUNT(G65,I65,K65)+COUNTA(Q65:V65) -> 4 | AI65: =IF(AH65>=3,"Sim","Não") -> Sim | AJ65: =IF(AND(Z65<>"",Z65<=Critérios!$B$9),"Sim","Não") -> Não
A66: F0065 | B66: It: A coisa | C66: It | D66: 2017 | E66: Não | F66: Bilheteria (Ancine/Wikipédia) | G66: 4414235 | H66: 61909031 | K66: 712445 | L66: 7.3 | M66: =IF(G66="","",PERCENTRANK($G$2:$G$354,G66)) -> 0.654 | N66: =IF(I66="","",PERCENTRANK($I$2:$I$354,I66)) | O66: =IF(K66="","",PERCENTRANK($K$2:$K$354,K66)) -> 0.73 | P66: =COUNT(M66:O66) -> 2 | Q66: 2017 populares #10 | W66: =COUNTA(Q66:V66) -> 1 | X66: =IF(P66=0,"",MIN(1,AVERAGE(M66:O66)+Critérios!$B$5*W66)) -> 0.722 | Y66: =IF(X66="","",IF(X66>=Critérios!$B$7,"A",IF(X66>=Critérios!$B$8,"B","C"))) -> A | Z66: =IF(X66="","",RANK(X66,$X$2:$X$354)) -> 65 | AA66: =IF(X66="","Sairia — sem métrica",IF(PERCENTRANK($X$2:$X$354,X66)<Critérios!$B$6,"Sairia — terço inferior","Fica")) -> Fica | AB66: a avaliar | AD66: candidato | AF66: S203 | AG66: tt1396484 | AH66: =COUNT(G66,I66,K66)+COUNTA(Q66:V66) -> 3 | AI66: =IF(AH66>=3,"Sim","Não") -> Sim | AJ66: =IF(AND(Z66<>"",Z66<=Critérios!$B$9),"Sim","Não") -> Não
A67: F0066 | B67: Jogos Vorazes | C67: The Hunger Games | D67: 2012 | E67: Não | F67: Bilheteria (Ancine/Wikipédia) | I67: 694394724 | J67: 9 | K67: 1097873 | L67: 7.2 | M67: =IF(G67="","",PERCENTRANK($G$2:$G$354,G67)) | N67: =IF(I67="","",PERCENTRANK($I$2:$I$354,I67)) -> 0.394 | O67: =IF(K67="","",PERCENTRANK($K$2:$K$354,K67)) -> 0.92 | P67: =COUNT(M67:O67) -> 2 | R67: #54 hoje | U67: YPulse 2019-10 (13-18) #1 | W67: =COUNTA(Q67:V67) -> 2 | X67: =IF(P67=0,"",MIN(1,AVERAGE(M67:O67)+Critérios!$B$5*W67)) -> 0.717 | Y67: =IF(X67="","",IF(X67>=Critérios!$B$7,"A",IF(X67>=Critérios!$B$8,"B","C"))) -> A | Z67: =IF(X67="","",RANK(X67,$X$2:$X$354)) -> 66 | AA67: =IF(X67="","Sairia — sem métrica",IF(PERCENTRANK($X$2:$X$354,X67)<Critérios!$B$6,"Sairia — terço inferior","Fica")) -> Fica | AB67: a avaliar | AD67: candidato | AF67: S045 | AG67: tt1392170 | AH67: =COUNT(G67,I67,K67)+COUNTA(Q67:V67) -> 4 | AI67: =IF(AH67>=3,"Sim","Não") -> Sim | AJ67: =IF(AND(Z67<>"",Z67<=Critérios!$B$9),"Sim","Não") -> Não
A68: F0067 | B68: Minions | C68: Minions | D68: 2015 | E68: Não | F68: Bilheteria (Ancine/Wikipédia) | G68: 8919421 | H68: 120059271 | I68: 1159398397 | J68: 5 | K68: 291041 | L68: 6.4 | M68: =IF(G68="","",PERCENTRANK($G$2:$G$354,G68)) -> 0.935 | N68: =IF(I68="","",PERCENTRANK($I$2:$I$354,I68)) -> 0.869 | O68: =IF(K68="","",PERCENTRANK($K$2:$K$354,K68)) -> 0.33 | P68: =COUNT(M68:O68) -> 3 | W68: =COUNTA(Q68:V68) -> 0 | X68: =IF(P68=0,"",MIN(1,AVERAGE(M68:O68)+Critérios!$B$5*W68)) -> 0.71133333 | Y68: =IF(X68="","",IF(X68>=Critérios!$B$7,"A",IF(X68>=Critérios!$B$8,"B","C"))) -> A | Z68: =IF(X68="","",RANK(X68,$X$2:$X$354)) -> 67 | AA68: =IF(X68="","Sairia — sem métrica",IF(PERCENTRANK($X$2:$X$354,X68)<Critérios!$B$6,"Sairia — terço inferior","Fica")) -> Fica | AB68: ambíguo (provável) — conferir | AD68: candidato | AF68: S048, S191, S192, S201, S202 | AG68: tt2293640 | AH68: =COUNT(G68,I68,K68)+COUNTA(Q68:V68) -> 3 | AI68: =IF(AH68>=3,"Sim","Não") -> Sim | AJ68: =IF(AND(Z68<>"",Z68<=Critérios!$B$9),"Sim","Não") -> Não
A69: F0068 | B69: Piratas do Caribe: Navegando em Águas Misteriosas | C69: Pirates of the Caribbean: On Stranger Tides | D69: 2011 | E69: Não | F69: Bilheteria (Ancine/Wikipédia) | G69: 4445040 | H69: 49099468 | I69: 1045713802 | J69: 3 | K69: 615956 | L69: 6.6 | M69: =IF(G69="","",PERCENTRANK($G$2:$G$354,G69)) -> 0.663 | N69: =IF(I69="","",PERCENTRANK($I$2:$I$354,I69)) -> 0.788 | O69: =IF(K69="","",PERCENTRANK($K$2:$K$354,K69)) -> 0.679 | P69: =COUNT(M69:O69) -> 3 | W69: =COUNTA(Q69:V69) -> 0 | X69: =IF(P69=0,"",MIN(1,AVERAGE(M69:O69)+Critérios!$B$5*W69)) -> 0.71 | Y69: =IF(X69="","",IF(X69>=Critérios!$B$7,"A",IF(X69>=Critérios!$B$8,"B","C"))) -> A | Z69: =IF(X69="","",RANK(X69,$X$2:$X$354)) -> 68 | AA69: =IF(X69="","Sairia — sem métrica",IF(PERCENTRANK($X$2:$X$354,X69)<Critérios!$B$6,"Sairia — terço inferior","Fica")) -> Fica | AB69: ambíguo (provável) — conferir | AD69: candidato | AF69: S044, S187 | AG69: tt1298650 | AH69: =COUNT(G69,I69,K69)+COUNTA(Q69:V69) -> 3 | AI69: =IF(AH69>=3,"Sim","Não") -> Sim | AJ69: =IF(AND(Z69<>"",Z69<=Critérios!$B$9),"Sim","Não") -> Não
A70: F0069 | B70: Guardiões da Galáxia Vol. 2 | C70: Guardians of the Galaxy Vol. 2 | D70: 2017 | E70: Não | F70: Bilheteria (Ancine/Wikipédia) | G70: 4207641 | H70: 67529482 | I70: 869087963 | J70: 8 | K70: 849763 | L70: 7.6 | M70: =IF(G70="","",PERCENTRANK($G$2:$G$354,G70)) -> 0.601 | N70: =IF(I70="","",PERCENTRANK($I$2:$I$354,I70)) -> 0.619 | O70: =IF(K70="","",PERCENTRANK($K$2:$K$354,K70)) -> 0.818 | P70: =COUNT(M70:O70) -> 3 | Q70: 2017 populares #6 | W70: =COUNTA(Q70:V70) -> 1 | X70: =IF(P70=0,"",MIN(1,AVERAGE(M70:O70)+Critérios!$B$5*W70)) -> 0.70933333 | Y70: =IF(X70="","",IF(X70>=Critérios!$B$7,"A",IF(X70>=Critérios!$B$8,"B","C"))) -> A | Z70: =IF(X70="","",RANK(X70,$X$2:$X$354)) -> 69 | AA70: =IF(X70="","Sairia — sem métrica",IF(PERCENTRANK($X$2:$X$354,X70)<Critérios!$B$6,"Sairia — terço inferior","Fica")) -> Fica | AB70: ambíguo (provável) — conferir | AD70: candidato | AF70: S050, S203 | AG70: tt3896198 | AH70: =COUNT(G70,I70,K70)+COUNTA(Q70:V70) -> 4 | AI70: =IF(AH70>=3,"Sim","Não") -> Sim | AJ70: =IF(AND(Z70<>"",Z70<=Critérios!$B$9),"Sim","Não") -> Não
A71: F0070 | B71: Meu malvado favorito 2 | C71: Despicable Me 2 | D71: 2013 | E71: Não | F71: Bilheteria (Ancine/Wikipédia) | G71: 6989217 | H71: 80603472 | I71: 971000005 | J71: 3 | K71: 466447 | L71: 7.3 | M71: =IF(G71="","",PERCENTRANK($G$2:$G$354,G71)) -> 0.853 | N71: =IF(I71="","",PERCENTRANK($I$2:$I$354,I71)) -> 0.729 | O71: =IF(K71="","",PERCENTRANK($K$2:$K$354,K71)) -> 0.537 | P71: =COUNT(M71:O71) -> 3 | W71: =COUNTA(Q71:V71) -> 0 | X71: =IF(P71=0,"",MIN(1,AVERAGE(M71:O71)+Critérios!$B$5*W71)) -> 0.70633333 | Y71: =IF(X71="","",IF(X71>=Critérios!$B$7,"A",IF(X71>=Critérios!$B$8,"B","C"))) -> A | Z71: =IF(X71="","",RANK(X71,$X$2:$X$354)) -> 70 | AA71: =IF(X71="","Sairia — sem métrica",IF(PERCENTRANK($X$2:$X$354,X71)<Critérios!$B$6,"Sairia — terço inferior","Fica")) -> Fica | AB71: a avaliar | AD71: candidato | AF71: S046, S193 | AG71: tt1690953 | AH71: =COUNT(G71,I71,K71)+COUNTA(Q71:V71) -> 3 | AI71: =IF(AH71>=3,"Sim","Não") -> Sim | AJ71: =IF(AND(Z71<>"",Z71<=Critérios!$B$9),"Sim","Não") -> Não
A72: F0071 | B72: Harry Potter e o Cálice de Fogo | C72: Harry Potter and the Goblet of Fire | D72: 2005 | E72: Não | F72: Bilheteria (Ancine/Wikipédia) | G72: 4597283 | H72: 30332796 | I72: 895921036 | J72: 1 | K72: 767189 | L72: 7.7 | M72: =IF(G72="","",PERCENTRANK($G$2:$G$354,G72)) -> 0.676 | N72: =IF(I72="","",PERCENTRANK($I$2:$I$354,I72)) -> 0.665 | O72: =IF(K72="","",PERCENTRANK($K$2:$K$354,K72)) -> 0.767 | P72: =COUNT(M72:O72) -> 3 | W72: =COUNTA(Q72:V72) -> 0 | X72: =IF(P72=0,"",MIN(1,AVERAGE(M72:O72)+Critérios!$B$5*W72)) -> 0.70266667 | Y72: =IF(X72="","",IF(X72>=Critérios!$B$7,"A",IF(X72>=Critérios!$B$8,"B","C"))) -> A | Z72: =IF(X72="","",RANK(X72,$X$2:$X$354)) -> 71 | AA72: =IF(X72="","Sairia — sem métrica",IF(PERCENTRANK($X$2:$X$354,X72)<Critérios!$B$6,"Sairia — terço inferior","Fica")) -> Fica | AB72: a avaliar | AD72: candidato | AF72: S038, S183 | AG72: tt0330373 | AH72: =COUNT(G72,I72,K72)+COUNTA(Q72:V72) -> 3 | AI72: =IF(AH72>=3,"Sim","Não") -> Sim | AJ72: =IF(AND(Z72<>"",Z72<=Critérios!$B$9),"Sim","Não") -> Não
A73: F0072 | B73: Piratas do Caribe: O Baú da Morte | C73: Pirates of the Caribbean: Dead Man's Chest | D73: 2006 | E73: Não | F73: Bilheteria (Ancine/Wikipédia) | G73: 3115020 | H73: 23536942 | I73: 1066179725 | J73: 1 | K73: 838771 | L73: 7.4 | M73: =IF(G73="","",PERCENTRANK($G$2:$G$354,G73)) -> 0.474 | N73: =IF(I73="","",PERCENTRANK($I$2:$I$354,I73)) -> 0.805 | O73: =IF(K73="","",PERCENTRANK($K$2:$K$354,K73)) -> 0.813 | P73: =COUNT(M73:O73) -> 3 | W73: =COUNTA(Q73:V73) -> 0 | X73: =IF(P73=0,"",MIN(1,AVERAGE(M73:O73)+Critérios!$B$5*W73)) -> 0.69733333 | Y73: =IF(X73="","",IF(X73>=Critérios!$B$7,"A",IF(X73>=Critérios!$B$8,"B","C"))) -> B | Z73: =IF(X73="","",RANK(X73,$X$2:$X$354)) -> 72 | AA73: =IF(X73="","Sairia — sem métrica",IF(PERCENTRANK($X$2:$X$354,X73)<Critérios!$B$6,"Sairia — terço inferior","Fica")) -> Fica | AB73: ambíguo (provável) — conferir | AD73: candidato | AF73: S039, S184 | AG73: tt0383574 | AH73: =COUNT(G73,I73,K73)+COUNTA(Q73:V73) -> 3 | AI73: =IF(AH73>=3,"Sim","Não") -> Sim | AJ73: =IF(AND(Z73<>"",Z73<=Critérios!$B$9),"Sim","Não") -> Não
A74: F0073 | B74: Zootopia 2 | C74: Zootopia 2 | D74: 2025 | E74: Não | F74: Bilheteria (Ancine/Wikipédia) | G74: 7880000 | H74: 152850000 | I74: 1870309291 | J74: 2 | K74: 157240 | L74: 7.3 | M74: =IF(G74="","",PERCENTRANK($G$2:$G$354,G74)) -> 0.899 | N74: =IF(I74="","",PERCENTRANK($I$2:$I$354,I74)) -> 0.966 | O74: =IF(K74="","",PERCENTRANK($K$2:$K$354,K74)) -> 0.125 | P74: =COUNT(M74:O74) -> 3 | Q74: 2025 populares #24 | W74: =COUNTA(Q74:V74) -> 1 | X74: =IF(P74=0,"",MIN(1,AVERAGE(M74:O74)+Critérios!$B$5*W74)) -> 0.69333333 | Y74: =IF(X74="","",IF(X74>=Critérios!$B$7,"A",IF(X74>=Critérios!$B$8,"B","C"))) -> B | Z74: =IF(X74="","",RANK(X74,$X$2:$X$354)) -> 73 | AA74: =IF(X74="","Sairia — sem métrica",IF(PERCENTRANK($X$2:$X$354,X74)<Critérios!$B$6,"Sairia — terço inferior","Fica")) -> Fica | AB74: ambíguo (provável) — conferir | AD74: candidato | AF74: S058, S188 | AG74: tt26443597 | AH74: =COUNT(G74,I74,K74)+COUNTA(Q74:V74) -> 4 | AI74: =IF(AH74>=3,"Sim","Não") -> Sim | AJ74: =IF(AND(Z74<>"",Z74<=Critérios!$B$9),"Sim","Não") -> Não
A75: F0074 | B75: Harry Potter e as relíquias da morte – Parte 1 | C75: Harry Potter and the Deathly Hallows – Part 1 | D75: 2010 | E75: Não | F75: Bilheteria (Ancine/Wikipédia) | G75: 4401163 | H75: 37655019 | I75: 960897696 | J75: 3 | K75: 677012 | L75: 7.7 | M75: =IF(G75="","",PERCENTRANK($G$2:$G$354,G75)) -> 0.65 | N75: =IF(I75="","",PERCENTRANK($I$2:$I$354,I75)) -> 0.703 | O75: =IF(K75="","",PERCENTRANK($K$2:$K$354,K75)) -> 0.713 | P75: =COUNT(M75:O75) -> 3 | W75: =COUNTA(Q75:V75) -> 0 | X75: =IF(P75=0,"",MIN(1,AVERAGE(M75:O75)+Critérios!$B$5*W75)) -> 0.68866667 | Y75: =IF(X75="","",IF(X75>=Critérios!$B$7,"A",IF(X75>=Critérios!$B$8,"B","C"))) -> B | Z75: =IF(X75="","",RANK(X75,$X$2:$X$354)) -> 74 | AA75: =IF(X75="","Sairia — sem métrica",IF(PERCENTRANK($X$2:$X$354,X75)<Critérios!$B$6,"Sairia — terço inferior","Fica")) -> Fica | AB75: a avaliar | AD75: candidato | AF75: S043, S204 | AG75: tt0926084 | AH75: =COUNT(G75,I75,K75)+COUNTA(Q75:V75) -> 3 | AI75: =IF(AH75>=3,"Sim","Não") -> Sim | AJ75: =IF(AND(Z75<>"",Z75<=Critérios!$B$9),"Sim","Não") -> Não
A76: F0075 | B76: Deadpool 2 | C76: Deadpool 2 | D76: 2018 | E76: Não | F76: Bilheteria (Ancine/Wikipédia) | G76: 4601084 | H76: 66934777 | I76: 785896609 | J76: 9 | K76: 760427 | L76: 7.6 | M76: =IF(G76="","",PERCENTRANK($G$2:$G$354,G76)) -> 0.68 | N76: =IF(I76="","",PERCENTRANK($I$2:$I$354,I76)) -> 0.534 | O76: =IF(K76="","",PERCENTRANK($K$2:$K$354,K76)) -> 0.761 | P76: =COUNT(M76:O76) -> 3 | Q76: 2018 populares #7 | W76: =COUNTA(Q76:V76) -> 1 | X76: =IF(P76=0,"",MIN(1,AVERAGE(M76:O76)+Critérios!$B$5*W76)) -> 0.68833333 | Y76: =IF(X76="","",IF(X76>=Critérios!$B$7,"A",IF(X76>=Critérios!$B$8,"B","C"))) -> B | Z76: =IF(X76="","",RANK(X76,$X$2:$X$354)) -> 75 | AA76: =IF(X76="","Sairia — sem métrica",IF(PERCENTRANK($X$2:$X$354,X76)<Critérios!$B$6,"Sairia — terço inferior","Fica")) -> Fica | AB76: a avaliar | AD76: candidato | AF76: S051, S191 | AG76: tt5463162 | AH76: =COUNT(G76,I76,K76)+COUNTA(Q76:V76) -> 4 | AI76: =IF(AH76>=3,"Sim","Não") -> Sim | AJ76: =IF(AND(Z76<>"",Z76<=Critérios!$B$9),"Sim","Não") -> Não
A77: F0076 | B77: Venom | C77: Venom | D77: 2018 | E77: Não | F77: Bilheteria (Ancine/Wikipédia) | G77: 4605459 | H77: 72243415 | I77: 856085151 | J77: 7 | K77: 619097 | L77: 6.6 | M77: =IF(G77="","",PERCENTRANK($G$2:$G$354,G77)) -> 0.683 | N77: =IF(I77="","",PERCENTRANK($I$2:$I$354,I77)) -> 0.602 | O77: =IF(K77="","",PERCENTRANK($K$2:$K$354,K77)) -> 0.682 | P77: =COUNT(M77:O77) -> 3 | Q77: 2018 populares #24 | W77: =COUNTA(Q77:V77) -> 1 | X77: =IF(P77=0,"",MIN(1,AVERAGE(M77:O77)+Critérios!$B$5*W77)) -> 0.68566667 | Y77: =IF(X77="","",IF(X77>=Critérios!$B$7,"A",IF(X77>=Critérios!$B$8,"B","C"))) -> B | Z77: =IF(X77="","",RANK(X77,$X$2:$X$354)) -> 76 | AA77: =IF(X77="","Sairia — sem métrica",IF(PERCENTRANK($X$2:$X$354,X77)<Critérios!$B$6,"Sairia — terço inferior","Fica")) -> Fica | AB77: a avaliar | AD77: candidato | AF77: S051, S191 | AG77: tt1270797 | AH77: =COUNT(G77,I77,K77)+COUNTA(Q77:V77) -> 4 | AI77: =IF(AH77>=3,"Sim","Não") -> Sim | AJ77: =IF(AND(Z77<>"",Z77<=Critérios!$B$9),"Sim","Não") -> Não
A78: F0077 | B78: Harry Potter e o Enigma do Príncipe | C78: Harry Potter and the Half-Blood Prince | D78: 2009 | E78: Não | F78: Bilheteria (Ancine/Wikipédia) | G78: 4530291 | H78: 36183253 | I78: 933959197 | J78: 2 | K78: 672722 | L78: 7.6 | M78: =IF(G78="","",PERCENTRANK($G$2:$G$354,G78)) -> 0.67 | N78: =IF(I78="","",PERCENTRANK($I$2:$I$354,I78)) -> 0.678 | O78: =IF(K78="","",PERCENTRANK($K$2:$K$354,K78)) -> 0.707 | P78: =COUNT(M78:O78) -> 3 | W78: =COUNTA(Q78:V78) -> 0 | X78: =IF(P78=0,"",MIN(1,AVERAGE(M78:O78)+Critérios!$B$5*W78)) -> 0.685 | Y78: =IF(X78="","",IF(X78>=Critérios!$B$7,"A",IF(X78>=Critérios!$B$8,"B","C"))) -> B | Z78: =IF(X78="","",RANK(X78,$X$2:$X$354)) -> 77 | AA78: =IF(X78="","Sairia — sem métrica",IF(PERCENTRANK($X$2:$X$354,X78)<Critérios!$B$6,"Sairia — terço inferior","Fica")) -> Fica | AB78: a avaliar | AD78: candidato | AF78: S042, S197 | AG78: tt0417741 | AH78: =COUNT(G78,I78,K78)+COUNTA(Q78:V78) -> 3 | AI78: =IF(AH78>=3,"Sim","Não") -> Sim | AJ78: =IF(AND(Z78<>"",Z78<=Critérios!$B$9),"Sim","Não") -> Não
A79: F0078 | B79: Avatar: Fogo e Cinzas | C79: Avatar: Fire and Ash | D79: 2025 | E79: Não | F79: Bilheteria (Ancine/Wikipédia) | G79: 6340000 | H79: 143850000 | I79: 1490386712 | J79: 3 | K79: 214946 | L79: 7.2 | M79: =IF(G79="","",PERCENTRANK($G$2:$G$354,G79)) -> 0.817 | N79: =IF(I79="","",PERCENTRANK($I$2:$I$354,I79)) -> 0.932 | O79: =IF(K79="","",PERCENTRANK($K$2:$K$354,K79)) -> 0.21 | P79: =COUNT(M79:O79) -> 3 | Q79: 2025 populares #22 | W79: =COUNTA(Q79:V79) -> 1 | X79: =IF(P79=0,"",MIN(1,AVERAGE(M79:O79)+Critérios!$B$5*W79)) -> 0.683 | Y79: =IF(X79="","",IF(X79>=Critérios!$B$7,"A",IF(X79>=Critérios!$B$8,"B","C"))) -> B | Z79: =IF(X79="","",RANK(X79,$X$2:$X$354)) -> 78 | AA79: =IF(X79="","Sairia — sem métrica",IF(PERCENTRANK($X$2:$X$354,X79)<Critérios!$B$6,"Sairia — terço inferior","Fica")) -> Fica | AB79: a avaliar | AD79: candidato | AF79: S058, S188 | AG79: tt1757678 | AH79: =COUNT(G79,I79,K79)+COUNTA(Q79:V79) -> 4 | AI79: =IF(AH79>=3,"Sim","Não") -> Sim | AJ79: =IF(AND(Z79<>"",Z79<=Critérios!$B$9),"Sim","Não") -> Não
A80: F0079 | B80: Pantera Negra: Wakanda para Sempre | C80: Black Panther: Wakanda Forever | D80: 2022 | E80: Não | F80: Bilheteria (Ancine/Wikipédia) | G80: 5643868 | H80: 111658278 | I80: 859208836 | J80: 6 | K80: 403932 | L80: 6.6 | M80: =IF(G80="","",PERCENTRANK($G$2:$G$354,G80)) -> 0.784 | N80: =IF(I80="","",PERCENTRANK($I$2:$I$354,I80)) -> 0.61 | O80: =IF(K80="","",PERCENTRANK($K$2:$K$354,K80)) -> 0.46 | P80: =COUNT(M80:O80) -> 3 | Q80: 2022 populares #18 | S80: 2023 #8 | W80: =COUNTA(Q80:V80) -> 2 | X80: =IF(P80=0,"",MIN(1,AVERAGE(M80:O80)+Critérios!$B$5*W80)) -> 0.678 | Y80: =IF(X80="","",IF(X80>=Critérios!$B$7,"A",IF(X80>=Critérios!$B$8,"B","C"))) -> B | Z80: =IF(X80="","",RANK(X80,$X$2:$X$354)) -> 80 | AA80: =IF(X80="","Sairia — sem métrica",IF(PERCENTRANK($X$2:$X$354,X80)<Critérios!$B$6,"Sairia — terço inferior","Fica")) -> Fica | AB80: a avaliar | AD80: candidato | AF80: S055, S200 | AG80: tt9114286 | AH80: =COUNT(G80,I80,K80)+COUNTA(Q80:V80) -> 5 | AI80: =IF(AH80>=3,"Sim","Não") -> Sim | AJ80: =IF(AND(Z80<>"",Z80<=Critérios!$B$9),"Sim","Não") -> Não
A81: F0080 | B81: Harry Potter e a Ordem da Fênix | C81: Harry Potter and the Order of the Phoenix | D81: 2007 | E81: Não | F81: Bilheteria (Ancine/Wikipédia) | G81: 4263800 | H81: 31756000 | I81: 941676843 | J81: 2 | K81: 713589 | L81: 7.5 | M81: =IF(G81="","",PERCENTRANK($G$2:$G$354,G81)) -> 0.605 | N81: =IF(I81="","",PERCENTRANK($I$2:$I$354,I81)) -> 0.691 | O81: =IF(K81="","",PERCENTRANK($K$2:$K$354,K81)) -> 0.739 | P81: =COUNT(M81:O81) -> 3 | W81: =COUNTA(Q81:V81) -> 0 | X81: =IF(P81=0,"",MIN(1,AVERAGE(M81:O81)+Critérios!$B$5*W81)) -> 0.67833333 | Y81: =IF(X81="","",IF(X81>=Critérios!$B$7,"A",IF(X81>=Critérios!$B$8,"B","C"))) -> B | Z81: =IF(X81="","",RANK(X81,$X$2:$X$354)) -> 79 | AA81: =IF(X81="","Sairia — sem métrica",IF(PERCENTRANK($X$2:$X$354,X81)<Critérios!$B$6,"Sairia — terço inferior","Fica")) -> Fica | AB81: a avaliar | AD81: candidato | AF81: S040, S185 | AG81: tt0373889 | AH81: =COUNT(G81,I81,K81)+COUNTA(Q81:V81) -> 3 | AI81: =IF(AH81>=3,"Sim","Não") -> Sim | AJ81: =IF(AND(Z81<>"",Z81<=Critérios!$B$9),"Sim","Não") -> Não
A82: F0081 | B82: Pecadores | C82: Sinners | D82: 2025 | E82: Não | F82: Adicionado por: Letterboxd | K82: 532553 | L82: 7.5 | M82: =IF(G82="","",PERCENTRANK($G$2:$G$354,G82)) | N82: =IF(I82="","",PERCENTRANK($I$2:$I$354,I82)) | O82: =IF(K82="","",PERCENTRANK($K$2:$K$354,K82)) -> 0.616 | P82: =COUNT(M82:O82) -> 1 | Q82: 2025 populares #1; 2025 mais bem avaliados #9 | R82: #64 hoje | W82: =COUNTA(Q82:V82) -> 2 | X82: =IF(P82=0,"",MIN(1,AVERAGE(M82:O82)+Critérios!$B$5*W82)) -> 0.676 | Y82: =IF(X82="","",IF(X82>=Critérios!$B$7,"A",IF(X82>=Critérios!$B$8,"B","C"))) -> B | Z82: =IF(X82="","",RANK(X82,$X$2:$X$354)) -> 81 | AA82: =IF(X82="","Sairia — sem métrica",IF(PERCENTRANK($X$2:$X$354,X82)<Critérios!$B$6,"Sairia — terço inferior","Fica")) -> Fica | AB82: a avaliar | AD82: candidato | AG82: tt31193180 | AH82: =COUNT(G82,I82,K82)+COUNTA(Q82:V82) -> 3 | AI82: =IF(AH82>=3,"Sim","Não") -> Sim | AJ82: =IF(AND(Z82<>"",Z82<=Critérios!$B$9),"Sim","Não") -> Não
A83: F0082 | B83: Duna: Parte Dois | C83: Dune: Part Two | D83: 2024 | E83: Não | F83: Bilheteria (Ancine/Wikipédia) | I83: 715409065 | J83: 7 | K83: 798878 | L83: 8.4 | M83: =IF(G83="","",PERCENTRANK($G$2:$G$354,G83)) | N83: =IF(I83="","",PERCENTRANK($I$2:$I$354,I83)) -> 0.436 | O83: =IF(K83="","",PERCENTRANK($K$2:$K$354,K83)) -> 0.795 | P83: =COUNT(M83:O83) -> 2 | Q83: 2024 populares #1; 2024 mais bem avaliados #1 | V83: Q1 2024 | W83: =COUNTA(Q83:V83) -> 2 | X83: =IF(P83=0,"",MIN(1,AVERAGE(M83:O83)+Critérios!$B$5*W83)) -> 0.6755 | Y83: =IF(X83="","",IF(X83>=Critérios!$B$7,"A",IF(X83>=Critérios!$B$8,"B","C"))) -> B | Z83: =IF(X83="","",RANK(X83,$X$2:$X$354)) -> 82 | AA83: =IF(X83="","Sairia — sem métrica",IF(PERCENTRANK($X$2:$X$354,X83)<Critérios!$B$6,"Sairia — terço inferior","Fica")) -> Fica | AB83: a avaliar | AD83: candidato | AF83: S057 | AG83: tt15239678 | AH83: =COUNT(G83,I83,K83)+COUNTA(Q83:V83) -> 4 | AI83: =IF(AH83>=3,"Sim","Não") -> Sim | AJ83: =IF(AND(Z83<>"",Z83<=Critérios!$B$9),"Sim","Não") -> Não
A84: F0083 | B84: Jumanji: Bem-Vindo à Selva | C84: Jumanji: Welcome to the Jungle | D84: 2017 | E84: Não | F84: Bilheteria (Ancine/Wikipédia) | G84: 4772758 | H84: 74059745 | I84: 962077546 | J84: 5 | K84: 513674 | L84: 6.9 | M84: =IF(G84="","",PERCENTRANK($G$2:$G$354,G84)) -> 0.709 | N84: =IF(I84="","",PERCENTRANK($I$2:$I$354,I84)) -> 0.716 | O84: =IF(K84="","",PERCENTRANK($K$2:$K$354,K84)) -> 0.597 | P84: =COUNT(M84:O84) -> 3 | W84: =COUNTA(Q84:V84) -> 0 | X84: =IF(P84=0,"",MIN(1,AVERAGE(M84:O84)+Critérios!$B$5*W84)) -> 0.674 | Y84: =IF(X84="","",IF(X84>=Critérios!$B$7,"A",IF(X84>=Critérios!$B$8,"B","C"))) -> B | Z84: =IF(X84="","",RANK(X84,$X$2:$X$354)) -> 83 | AA84: =IF(X84="","Sairia — sem métrica",IF(PERCENTRANK($X$2:$X$354,X84)<Critérios!$B$6,"Sairia — terço inferior","Fica")) -> Fica | AB84: a avaliar | AD84: candidato | AF84: S050, S191 | AG84: tt2283362 | AH84: =COUNT(G84,I84,K84)+COUNTA(Q84:V84) -> 3 | AI84: =IF(AH84>=3,"Sim","Não") -> Sim | AJ84: =IF(AND(Z84<>"",Z84<=Critérios!$B$9),"Sim","Não") -> Não
A85: F0084 | B85: Rogue One - Uma História Star Wars | C85: Rogue One: A Star Wars Story | D85: 2016 | E85: Não | F85: Bilheteria (Ancine/Wikipédia) | G85: 2607958 | H85: 43774724 | I85: 1056057273 | J85: 2 | K85: 767467 | L85: 7.8 | M85: =IF(G85="","",PERCENTRANK($G$2:$G$354,G85)) -> 0.363 | N85: =IF(I85="","",PERCENTRANK($I$2:$I$354,I85)) -> 0.797 | O85: =IF(K85="","",PERCENTRANK($K$2:$K$354,K85)) -> 0.77 | P85: =COUNT(M85:O85) -> 3 | Q85: 2016 populares #8 | W85: =COUNTA(Q85:V85) -> 1 | X85: =IF(P85=0,"",MIN(1,AVERAGE(M85:O85)+Critérios!$B$5*W85)) -> 0.67333333 | Y85: =IF(X85="","",IF(X85>=Critérios!$B$7,"A",IF(X85>=Critérios!$B$8,"B","C"))) -> B | Z85: =IF(X85="","",RANK(X85,$X$2:$X$354)) -> 84 | AA85: =IF(X85="","Sairia — sem métrica",IF(PERCENTRANK($X$2:$X$354,X85)<Critérios!$B$6,"Sairia — terço inferior","Fica")) -> Fica | AB85: a avaliar | AD85: candidato | AF85: S049, S207 | AG85: tt3748528 | AH85: =COUNT(G85,I85,K85)+COUNTA(Q85:V85) -> 4 | AI85: =IF(AH85>=3,"Sim","Não") -> Sim | AJ85: =IF(AND(Z85<>"",Z85<=Critérios!$B$9),"Sim","Não") -> Não
A86: F0085 | B86: O Espetacular Homem-Aranha | C86: The Amazing Spider-Man | D86: 2012 | E86: Não | F86: Bilheteria (Ancine/Wikipédia) | G86: 5145603 | H86: 60473881 | I86: 757930663 | J86: 7 | K86: 790730 | L86: 7 | M86: =IF(G86="","",PERCENTRANK($G$2:$G$354,G86)) -> 0.739 | N86: =IF(I86="","",PERCENTRANK($I$2:$I$354,I86)) -> 0.487 | O86: =IF(K86="","",PERCENTRANK($K$2:$K$354,K86)) -> 0.79 | P86: =COUNT(M86:O86) -> 3 | W86: =COUNTA(Q86:V86) -> 0 | X86: =IF(P86=0,"",MIN(1,AVERAGE(M86:O86)+Critérios!$B$5*W86)) -> 0.672 | Y86: =IF(X86="","",IF(X86>=Critérios!$B$7,"A",IF(X86>=Critérios!$B$8,"B","C"))) -> B | Z86: =IF(X86="","",RANK(X86,$X$2:$X$354)) -> 85 | AA86: =IF(X86="","Sairia — sem métrica",IF(PERCENTRANK($X$2:$X$354,X86)<Critérios!$B$6,"Sairia — terço inferior","Fica")) -> Fica | AB86: a avaliar | AD86: candidato | AF86: S045, S205 | AG86: tt0948470 | AH86: =COUNT(G86,I86,K86)+COUNTA(Q86:V86) -> 3 | AI86: =IF(AH86>=3,"Sim","Não") -> Sim | AJ86: =IF(AND(Z86<>"",Z86<=Critérios!$B$9),"Sim","Não") -> Não
A87: F0086 | B87: Piratas do Caribe: No Fim do Mundo | C87: Pirates of the Caribbean: At World's End | D87: 2007 | E87: Não | F87: Bilheteria (Ancine/Wikipédia) | G87: 3826700 | H87: 30837000 | I87: 960996492 | J87: 1 | K87: 754626 | L87: 7.2 | M87: =IF(G87="","",PERCENTRANK($G$2:$G$354,G87)) -> 0.549 | N87: =IF(I87="","",PERCENTRANK($I$2:$I$354,I87)) -> 0.708 | O87: =IF(K87="","",PERCENTRANK($K$2:$K$354,K87)) -> 0.756 | P87: =COUNT(M87:O87) -> 3 | W87: =COUNTA(Q87:V87) -> 0 | X87: =IF(P87=0,"",MIN(1,AVERAGE(M87:O87)+Critérios!$B$5*W87)) -> 0.671 | Y87: =IF(X87="","",IF(X87>=Critérios!$B$7,"A",IF(X87>=Critérios!$B$8,"B","C"))) -> B | Z87: =IF(X87="","",RANK(X87,$X$2:$X$354)) -> 86 | AA87: =IF(X87="","Sairia — sem métrica",IF(PERCENTRANK($X$2:$X$354,X87)<Critérios!$B$6,"Sairia — terço inferior","Fica")) -> Fica | AB87: ambíguo (provável) — conferir | AD87: candidato | AF87: S040, S185 | AG87: tt0449088 | AH87: =COUNT(G87,I87,K87)+COUNTA(Q87:V87) -> 3 | AI87: =IF(AH87>=3,"Sim","Não") -> Sim | AJ87: =IF(AND(Z87<>"",Z87<=Critérios!$B$9),"Sim","Não") -> Não
A88: F0087 | B88: Shrek 2 | C88: Shrek 2 | D88: 2004 | E88: Não | F88: Bilheteria (Ancine/Wikipédia) | G88: 4672046 | H88: 29059376 | I88: 929098316 | J88: 1 | K88: 565278 | L88: 7.4 | M88: =IF(G88="","",PERCENTRANK($G$2:$G$354,G88)) -> 0.693 | N88: =IF(I88="","",PERCENTRANK($I$2:$I$354,I88)) -> 0.674 | O88: =IF(K88="","",PERCENTRANK($K$2:$K$354,K88)) -> 0.645 | P88: =COUNT(M88:O88) -> 3 | W88: =COUNTA(Q88:V88) -> 0 | X88: =IF(P88=0,"",MIN(1,AVERAGE(M88:O88)+Critérios!$B$5*W88)) -> 0.67066667 | Y88: =IF(X88="","",IF(X88>=Critérios!$B$7,"A",IF(X88>=Critérios!$B$8,"B","C"))) -> B | Z88: =IF(X88="","",RANK(X88,$X$2:$X$354)) -> 87 | AA88: =IF(X88="","Sairia — sem métrica",IF(PERCENTRANK($X$2:$X$354,X88)<Critérios!$B$6,"Sairia — terço inferior","Fica")) -> Fica | AB88: a avaliar | AD88: candidato | AF88: S037, S182 | AG88: tt0298148 | AH88: =COUNT(G88,I88,K88)+COUNTA(Q88:V88) -> 3 | AI88: =IF(AH88>=3,"Sim","Não") -> Sim | AJ88: =IF(AND(Z88<>"",Z88<=Critérios!$B$9),"Sim","Não") -> Não
A89: F0088 | B89: Capitão América 2: O soldado invernal | C89: Captain America: The Winter Soldier | D89: 2014 | E89: Não | F89: Bilheteria (Ancine/Wikipédia) | G89: 4621101 | H89: 62818154 | I89: 714421503 | J89: 7 | K89: 993017 | L89: 7.7 | M89: =IF(G89="","",PERCENTRANK($G$2:$G$354,G89)) -> 0.686 | N89: =IF(I89="","",PERCENTRANK($I$2:$I$354,I89)) -> 0.428 | O89: =IF(K89="","",PERCENTRANK($K$2:$K$354,K89)) -> 0.892 | P89: =COUNT(M89:O89) -> 3 | W89: =COUNTA(Q89:V89) -> 0 | X89: =IF(P89=0,"",MIN(1,AVERAGE(M89:O89)+Critérios!$B$5*W89)) -> 0.66866667 | Y89: =IF(X89="","",IF(X89>=Critérios!$B$7,"A",IF(X89>=Critérios!$B$8,"B","C"))) -> B | Z89: =IF(X89="","",RANK(X89,$X$2:$X$354)) -> 88 | AA89: =IF(X89="","Sairia — sem métrica",IF(PERCENTRANK($X$2:$X$354,X89)<Critérios!$B$6,"Sairia — terço inferior","Fica")) -> Fica | AB89: a avaliar | AD89: candidato | AF89: S047, S206 | AG89: tt1843866 | AH89: =COUNT(G89,I89,K89)+COUNTA(Q89:V89) -> 3 | AI89: =IF(AH89>=3,"Sim","Não") -> Sim | AJ89: =IF(AND(Z89<>"",Z89<=Critérios!$B$9),"Sim","Não") -> Não
A90: F0089 | B90: Cidade de Deus | C90: City of God | D90: 2002 | E90: Sim | F90: Bilheteria (Ancine/Wikipédia) | G90: 3370871 | H90: 18693153 | K90: 884642 | L90: 8.6 | M90: =IF(G90="","",PERCENTRANK($G$2:$G$354,G90)) -> 0.513 | N90: =IF(I90="","",PERCENTRANK($I$2:$I$354,I90)) | O90: =IF(K90="","",PERCENTRANK($K$2:$K$354,K90)) -> 0.824 | P90: =COUNT(M90:O90) -> 2 | W90: =COUNTA(Q90:V90) -> 0 | X90: =IF(P90=0,"",MIN(1,AVERAGE(M90:O90)+Critérios!$B$5*W90)) -> 0.6685 | Y90: =IF(X90="","",IF(X90>=Critérios!$B$7,"A",IF(X90>=Critérios!$B$8,"B","C"))) -> B | Z90: =IF(X90="","",RANK(X90,$X$2:$X$354)) -> 89 | AA90: =IF(X90="","Sairia — sem métrica",IF(PERCENTRANK($X$2:$X$354,X90)<Critérios!$B$6,"Sairia — terço inferior","Fica")) -> Fica | AB90: a avaliar | AC90: Resgatado manualmente (lista aprovada em 13/10/2026) | AD90: candidato | AF90: S180, S190, S194 | AG90: tt0317248 | AH90: =COUNT(G90,I90,K90)+COUNTA(Q90:V90) -> 2 | AI90: =IF(AH90>=3,"Sim","Não") -> Não | AJ90: =IF(AND(Z90<>"",Z90<=Critérios!$B$9),"Sim","Não") -> Não
A91: F0090 | B91: Divertida Mente | C91: Inside Out | D91: 2015 | E91: Não | F91: Bilheteria (Ancine/Wikipédia) | G91: 3780325 | H91: 45644493 | I91: 858811174 | J91: 7 | K91: 935709 | L91: 8.1 | M91: =IF(G91="","",PERCENTRANK($G$2:$G$354,G91)) -> 0.542 | N91: =IF(I91="","",PERCENTRANK($I$2:$I$354,I91)) -> 0.606 | O91: =IF(K91="","",PERCENTRANK($K$2:$K$354,K91)) -> 0.852 | P91: =COUNT(M91:O91) -> 3 | W91: =COUNTA(Q91:V91) -> 0 | X91: =IF(P91=0,"",MIN(1,AVERAGE(M91:O91)+Critérios!$B$5*W91)) -> 0.66666667 | Y91: =IF(X91="","",IF(X91>=Critérios!$B$7,"A",IF(X91>=Critérios!$B$8,"B","C"))) -> B | Z91: =IF(X91="","",RANK(X91,$X$2:$X$354)) -> 90 | AA91: =IF(X91="","Sairia — sem métrica",IF(PERCENTRANK($X$2:$X$354,X91)<Critérios!$B$6,"Sairia — terço inferior","Fica")) -> Fica | AB91: ambíguo (provável) — conferir | AD91: candidato | AF91: S048, S202 | AG91: tt2096673 | AH91: =COUNT(G91,I91,K91)+COUNTA(Q91:V91) -> 3 | AI91: =IF(AH91>=3,"Sim","Não") -> Sim | AJ91: =IF(AND(Z91<>"",Z91<=Critérios!$B$9),"Sim","Não") -> Não
A92: F0091 | B92: Harry Potter e a Câmara Secreta | C92: Harry Potter and the Chamber of Secrets | D92: 2002 | E92: Não | F92: Bilheteria (Ancine/Wikipédia) | G92: 4050416 | H92: 22961410 | I92: 878979634 | J92: 2 | K92: 780187 | L92: 7.5 | M92: =IF(G92="","",PERCENTRANK($G$2:$G$354,G92)) -> 0.578 | N92: =IF(I92="","",PERCENTRANK($I$2:$I$354,I92)) -> 0.644 | O92: =IF(K92="","",PERCENTRANK($K$2:$K$354,K92)) -> 0.776 | P92: =COUNT(M92:O92) -> 3 | W92: =COUNTA(Q92:V92) -> 0 | X92: =IF(P92=0,"",MIN(1,AVERAGE(M92:O92)+Critérios!$B$5*W92)) -> 0.666 | Y92: =IF(X92="","",IF(X92>=Critérios!$B$7,"A",IF(X92>=Critérios!$B$8,"B","C"))) -> B | Z92: =IF(X92="","",RANK(X92,$X$2:$X$354)) -> 91 | AA92: =IF(X92="","Sairia — sem métrica",IF(PERCENTRANK($X$2:$X$354,X92)<Critérios!$B$6,"Sairia — terço inferior","Fica")) -> Fica | AB92: a avaliar | AD92: candidato | AF92: S035, S180 | AG92: tt0295297 | AH92: =COUNT(G92,I92,K92)+COUNTA(Q92:V92) -> 3 | AI92: =IF(AH92>=3,"Sim","Não") -> Sim | AJ92: =IF(AND(Z92<>"",Z92<=Critérios!$B$9),"Sim","Não") -> Não
A93: F0092 | B93: O Menu | C93: The Menu | D93: 2022 | E93: Não | F93: Adicionado por: Letterboxd | K93: 518661 | L93: 7.1 | M93: =IF(G93="","",PERCENTRANK($G$2:$G$354,G93)) | N93: =IF(I93="","",PERCENTRANK($I$2:$I$354,I93)) | O93: =IF(K93="","",PERCENTRANK($K$2:$K$354,K93)) -> 0.605 | P93: =COUNT(M93:O93) -> 1 | Q93: 2022 populares #21 | R93: #109 hoje | W93: =COUNTA(Q93:V93) -> 2 | X93: =IF(P93=0,"",MIN(1,AVERAGE(M93:O93)+Critérios!$B$5*W93)) -> 0.665 | Y93: =IF(X93="","",IF(X93>=Critérios!$B$7,"A",IF(X93>=Critérios!$B$8,"B","C"))) -> B | Z93: =IF(X93="","",RANK(X93,$X$2:$X$354)) -> 92 | AA93: =IF(X93="","Sairia — sem métrica",IF(PERCENTRANK($X$2:$X$354,X93)<Critérios!$B$6,"Sairia — terço inferior","Fica")) -> Fica | AB93: a avaliar | AD93: candidato | AG93: tt9764362 | AH93: =COUNT(G93,I93,K93)+COUNTA(Q93:V93) -> 3 | AI93: =IF(AH93>=3,"Sim","Não") -> Sim | AJ93: =IF(AND(Z93<>"",Z93<=Critérios!$B$9),"Sim","Não") -> Não
A94: F0093 | B94: Moana - Um Mar de Aventuras | C94: Moana | D94: 2017 | E94: Não | F94: Bilheteria (Ancine/Wikipédia) | G94: 5147838 | H94: 71598597 | K94: 451706 | L94: 7.6 | M94: =IF(G94="","",PERCENTRANK($G$2:$G$354,G94)) -> 0.745 | N94: =IF(I94="","",PERCENTRANK($I$2:$I$354,I94)) | O94: =IF(K94="","",PERCENTRANK($K$2:$K$354,K94)) -> 0.523 | P94: =COUNT(M94:O94) -> 2 | Q94: 2016 populares #41; 2016 mais bem avaliados #13 | W94: =COUNTA(Q94:V94) -> 1 | X94: =IF(P94=0,"",MIN(1,AVERAGE(M94:O94)+Critérios!$B$5*W94)) -> 0.664 | Y94: =IF(X94="","",IF(X94>=Critérios!$B$7,"A",IF(X94>=Critérios!$B$8,"B","C"))) -> B | Z94: =IF(X94="","",RANK(X94,$X$2:$X$354)) -> 93 | AA94: =IF(X94="","Sairia — sem métrica",IF(PERCENTRANK($X$2:$X$354,X94)<Critérios!$B$6,"Sairia — terço inferior","Fica")) -> Fica | AB94: a avaliar | AD94: candidato | AF94: S203 | AG94: tt3521164 | AH94: =COUNT(G94,I94,K94)+COUNTA(Q94:V94) -> 3 | AI94: =IF(AH94>=3,"Sim","Não") -> Sim | AJ94: =IF(AND(Z94<>"",Z94<=Critérios!$B$9),"Sim","Não") -> Não
A95: F0094 | B95: X-Men: Dias de um Futuro Esquecido | C95: X-Men: Days of Future Past | D95: 2014 | E95: Não | F95: Bilheteria (Ancine/Wikipédia) | G95: 4923664 | H95: 64417536 | I95: 746045700 | J95: 6 | K95: 799717 | L95: 7.9 | M95: =IF(G95="","",PERCENTRANK($G$2:$G$354,G95)) -> 0.722 | N95: =IF(I95="","",PERCENTRANK($I$2:$I$354,I95)) -> 0.466 | O95: =IF(K95="","",PERCENTRANK($K$2:$K$354,K95)) -> 0.798 | P95: =COUNT(M95:O95) -> 3 | W95: =COUNTA(Q95:V95) -> 0 | X95: =IF(P95=0,"",MIN(1,AVERAGE(M95:O95)+Critérios!$B$5*W95)) -> 0.662 | Y95: =IF(X95="","",IF(X95>=Critérios!$B$7,"A",IF(X95>=Critérios!$B$8,"B","C"))) -> B | Z95: =IF(X95="","",RANK(X95,$X$2:$X$354)) -> 94 | AA95: =IF(X95="","Sairia — sem métrica",IF(PERCENTRANK($X$2:$X$354,X95)<Critérios!$B$6,"Sairia — terço inferior","Fica")) -> Fica | AB95: ambíguo (provável) — conferir | AD95: candidato | AF95: S047, S206 | AG95: tt1877832 | AH95: =COUNT(G95,I95,K95)+COUNTA(Q95:V95) -> 3 | AI95: =IF(AH95>=3,"Sim","Não") -> Sim | AJ95: =IF(AND(Z95<>"",Z95<=Critérios!$B$9),"Sim","Não") -> Não
A96: F0095 | B96: Thor: Amor e Trovão | C96: Thor: Love and Thunder | D96: 2022 | E96: Não | F96: Bilheteria (Ancine/Wikipédia) | G96: 6351493 | H96: 123255058 | I96: 760928081 | J96: 8 | K96: 476886 | L96: 6.1 | M96: =IF(G96="","",PERCENTRANK($G$2:$G$354,G96)) -> 0.82 | N96: =IF(I96="","",PERCENTRANK($I$2:$I$354,I96)) -> 0.504 | O96: =IF(K96="","",PERCENTRANK($K$2:$K$354,K96)) -> 0.56 | P96: =COUNT(M96:O96) -> 3 | Q96: 2022 populares #7 | W96: =COUNTA(Q96:V96) -> 1 | X96: =IF(P96=0,"",MIN(1,AVERAGE(M96:O96)+Critérios!$B$5*W96)) -> 0.658 | Y96: =IF(X96="","",IF(X96>=Critérios!$B$7,"A",IF(X96>=Critérios!$B$8,"B","C"))) -> B | Z96: =IF(X96="","",RANK(X96,$X$2:$X$354)) -> 95 | AA96: =IF(X96="","Sairia — sem métrica",IF(PERCENTRANK($X$2:$X$354,X96)<Critérios!$B$6,"Sairia — terço inferior","Fica")) -> Fica | AB96: a avaliar | AD96: candidato | AF96: S055, S200 | AG96: tt10648342 | AH96: =COUNT(G96,I96,K96)+COUNTA(Q96:V96) -> 4 | AI96: =IF(AH96>=3,"Sim","Não") -> Sim | AJ96: =IF(AND(Z96<>"",Z96<=Critérios!$B$9),"Sim","Não") -> Não
A97: F0096 | B97: Aladdin | C97: Aladdin | D97: 2019 | E97: Não | F97: Bilheteria (Ancine/Wikipédia) | G97: 4788803 | H97: 80060751 | I97: 1051693953 | J97: 9 | K97: 320359 | L97: 6.9 | M97: =IF(G97="","",PERCENTRANK($G$2:$G$354,G97)) -> 0.712 | N97: =IF(I97="","",PERCENTRANK($I$2:$I$354,I97)) -> 0.792 | O97: =IF(K97="","",PERCENTRANK($K$2:$K$354,K97)) -> 0.378 | P97: =COUNT(M97:O97) -> 3 | Q97: 2019 populares #29 | W97: =COUNTA(Q97:V97) -> 1 | X97: =IF(P97=0,"",MIN(1,AVERAGE(M97:O97)+Critérios!$B$5*W97)) -> 0.65733333 | Y97: =IF(X97="","",IF(X97>=Critérios!$B$7,"A",IF(X97>=Critérios!$B$8,"B","C"))) -> B | Z97: =IF(X97="","",RANK(X97,$X$2:$X$354)) -> 96 | AA97: =IF(X97="","Sairia — sem métrica",IF(PERCENTRANK($X$2:$X$354,X97)<Critérios!$B$6,"Sairia — terço inferior","Fica")) -> Fica | AB97: a avaliar | AD97: candidato | AF97: S052, S208 | AG97: tt6139732 | AH97: =COUNT(G97,I97,K97)+COUNTA(Q97:V97) -> 4 | AI97: =IF(AH97>=3,"Sim","Não") -> Sim | AJ97: =IF(AND(Z97<>"",Z97<=Critérios!$B$9),"Sim","Não") -> Não
A98: F0097 | B98: Zootopia - Essa Cidade é o Bicho | C98: Zootopia | D98: 2016 | E98: Não | F98: Bilheteria (Ancine/Wikipédia) | G98: 2824226 | H98: 38578458 | I98: 1023784195 | J98: 4 | K98: 651499 | L98: 8 | M98: =IF(G98="","",PERCENTRANK($G$2:$G$354,G98)) -> 0.412 | N98: =IF(I98="","",PERCENTRANK($I$2:$I$354,I98)) -> 0.767 | O98: =IF(K98="","",PERCENTRANK($K$2:$K$354,K98)) -> 0.699 | P98: =COUNT(M98:O98) -> 3 | Q98: 2016 populares #3 | W98: =COUNTA(Q98:V98) -> 1 | X98: =IF(P98=0,"",MIN(1,AVERAGE(M98:O98)+Critérios!$B$5*W98)) -> 0.656 | Y98: =IF(X98="","",IF(X98>=Critérios!$B$7,"A",IF(X98>=Critérios!$B$8,"B","C"))) -> B | Z98: =IF(X98="","",RANK(X98,$X$2:$X$354)) -> 97 | AA98: =IF(X98="","Sairia — sem métrica",IF(PERCENTRANK($X$2:$X$354,X98)<Critérios!$B$6,"Sairia — terço inferior","Fica")) -> Fica | AB98: ambíguo (provável) — conferir | AD98: candidato | AF98: S049, S207 | AG98: tt2948356 | AH98: =COUNT(G98,I98,K98)+COUNTA(Q98:V98) -> 4 | AI98: =IF(AH98>=3,"Sim","Não") -> Sim | AJ98: =IF(AND(Z98<>"",Z98<=Critérios!$B$9),"Sim","Não") -> Não
A99: F0098 | B99: Capitão América: O Primeiro Vingador | C99: Captain America: The First Avenger | D99: 2011 | E99: Não | F99: Bilheteria (Ancine/Wikipédia) | G99: 2841148 | H99: 33209899 | K99: 990930 | L99: 6.9 | M99: =IF(G99="","",PERCENTRANK($G$2:$G$354,G99)) -> 0.422 | N99: =IF(I99="","",PERCENTRANK($I$2:$I$354,I99)) | O99: =IF(K99="","",PERCENTRANK($K$2:$K$354,K99)) -> 0.889 | P99: =COUNT(M99:O99) -> 2 | W99: =COUNTA(Q99:V99) -> 0 | X99: =IF(P99=0,"",MIN(1,AVERAGE(M99:O99)+Critérios!$B$5*W99)) -> 0.6555 | Y99: =IF(X99="","",IF(X99>=Critérios!$B$7,"A",IF(X99>=Critérios!$B$8,"B","C"))) -> B | Z99: =IF(X99="","",RANK(X99,$X$2:$X$354)) -> 98 | AA99: =IF(X99="","Sairia — sem métrica",IF(PERCENTRANK($X$2:$X$354,X99)<Critérios!$B$6,"Sairia — terço inferior","Fica")) -> Fica | AB99: a avaliar | AC99: Resgatado manualmente (lista aprovada em 13/10/2026) | AD99: candidato | AF99: S187 | AG99: tt0458339 | AH99: =COUNT(G99,I99,K99)+COUNTA(Q99:V99) -> 2 | AI99: =IF(AH99>=3,"Sim","Não") -> Não | AJ99: =IF(AND(Z99<>"",Z99<=Critérios!$B$9),"Sim","Não") -> Não
A100: F0099 | B100: 007 – Operação Skyfall | C100: Skyfall | D100: 2012 | E100: Não | F100: Bilheteria (Ancine/Wikipédia) | G100: 2550914 | H100: 29696175 | I100: 1108561013 | J100: 2 | K100: 781902 | L100: 7.8 | M100: =IF(G100="","",PERCENTRANK($G$2:$G$354,G100)) -> 0.346 | N100: =IF(I100="","",PERCENTRANK($I$2:$I$354,I100)) -> 0.835 | O100: =IF(K100="","",PERCENTRANK($K$2:$K$354,K100)) -> 0.781 | P100: =COUNT(M100:O100) -> 3 | W100: =COUNTA(Q100:V100) -> 0 | X100: =IF(P100=0,"",MIN(1,AVERAGE(M100:O100)+Critérios!$B$5*W100)) -> 0.654 | Y100: =IF(X100="","",IF(X100>=Critérios!$B$7,"A",IF(X100>=Critérios!$B$8,"B","C"))) -> B | Z100: =IF(X100="","",RANK(X100,$X$2:$X$354)) -> 99 | AA100: =IF(X100="","Sairia — sem métrica",IF(PERCENTRANK($X$2:$X$354,X100)<Critérios!$B$6,"Sairia — terço inferior","Fica")) -> Fica | AB100: a avaliar | AD100: candidato | AF100: S045, S205 | AG100: tt1074638 | AH100: =COUNT(G100,I100,K100)+COUNTA(Q100:V100) -> 3 | AI100: =IF(AH100>=3,"Sim","Não") -> Sim | AJ100: =IF(AND(Z100<>"",Z100<=Critérios!$B$9),"Sim","Não") -> Não
...

Sheet Séries
A1: ID | B1: Título no Brasil | C1: Título original | D1: Ano de estreia | E1: Origem / canal | F1: Origem na base | G1: Votos no IMDb | H1: Nota IMDb | I1: Netflix: views 91 dias (maior temporada) | J1: Netflix: posição no Top 10 histórico | K1: Audiência média por temporada (maior) | L1: Tipo da audiência média | M1: Nielsen: melhor posição | N1: Nielsen: tamanho da lista | O1: Nielsen: aparições | P1: Percentil votos IMDb | Q1: Pontuação Netflix | R1: Pontuação Nielsen | S1: Pontuação audiência média | T1: Audiência oficial (melhor) | U1: Nº de métricas | V1: Selo Geração Z | W1: Selo Parrot BR | X1: Selo Whip Media | Y1: Selo JustWatch BR | Z1: Nº de selos | AA1: Índice | AB1: Faixa | AC1: Posição | AD1: Terço inferior da base final (informativo) | AE1: Protagonista (preliminar) | AF1: Alertas de conteúdo | AG1: Conferir | AH1: Status | AI1: Notas editoriais | AJ1: Fontes | AK1: IMDb ID | AL1: Nº de bases em que aparece | AM1: Presente em ≥3 bases | AN1: Seleção Sucessos
A2: S0001 | B2: Stranger Things | C2: Stranger Things | D2: 2016 | E2: Netflix | F2: Audiência oficial (coleta) | G2: 1746147 | H2: 8.6 | I2: 140700000 | J2: 3 | M2: 1 | N2: 30 | O2: 2022 #1; 2025 #3; 2025 #1 | P2: =IF(G2="","",PERCENTRANK($G$2:$G$85,G2)) -> 0.976 | Q2: =IF(J2="","",1-(J2-1)/20) -> 0.9 | R2: =IF(M2="","",1-(M2-1)/(2*N2)) -> 1 | S2: =IF(K2="","",0.5+0.5*PERCENTRANK($K$2:$K$85,K2)) | T2: =IF(COUNT(Q2:S2)=0,"",MAX(Q2:S2)) -> 1 | U2: =COUNT(P2,T2) -> 2 | V2: YPulse 2024-02 (13-17) #1; YPulse 2024-02 (18-24) #3; YPulse Media Consumption Monitor 2022-10 (Gen Z (faixa não explicitada; amostra 13-39)) #1; YPulse 2023-11 (13-17); YPulse 2023-11 (18-24); YPulse 2024-09 (Gen Z teens and young adults (faixa não explicitada)); YPulse 2025-02 (Gen Z (faixa não explicitada)); YPulse 2016-09 (teens (13-17 presumido; amostra 13-33)); UCLA Center for Scholars & Storytellers 2025-10 (10-24) #1; UCLA Teens & Screens 2023 2023-10 (10-24); Morning Consult 2022-12 (13-25) #6 | W2: 2020 (ano) #1; fev 2020 #2 | X2: semana encerrada 19 jun 2022 #3 (United States); semana encerrada 17 jul 2022 #1 (United States); semana encerrada 24 jul 2022 #3 (United States) | Y2: #144 hoje | Z2: =COUNTA(V2:Y2) -> 4 | AA2: =IF(U2=0,"",MIN(1,AVERAGE(P2,T2)+Critérios!$B$5*Z2)) -> 1 | AB2: =IF(AA2="","",IF(AA2>=Critérios!$B$7,"A",IF(AA2>=Critérios!$B$8,"B","C"))) -> A | AC2: =IF(AA2="","",RANK(AA2,$AA$2:$AA$85)) -> 1 | AD2: =IF(AA2="","Sairia — sem métrica",IF(PERCENTRANK($AA$2:$AA$85,AA2)<Critérios!$B$6,"Sairia — terço inferior","Fica")) -> Fica | AE2: coral/antologia | AH2: candidato | AJ2: S030 | AK2: tt4574334 | AL2: =COUNT(G2)+IF(OR(I2<>"",K2<>""),1,0)+IF(M2<>"",1,0)+COUNTA(V2:Y2) -> 7 | AM2: =IF(AL2>=3,"Sim","Não") -> Sim | AN2: =IF(AND(AC2<>"",AC2<=Critérios!$B$9),"Sim","Não") -> Sim
A3: S0002 | B3: The Big Bang Theory | C3: The Big Bang Theory | D3: 2007 | E3: CBS | F3: Audiência oficial (coleta) | G3: 948462 | H3: 8.1 | K3: 20360000 | M3: 1 | N3: 40 | O3: 2009-10 #14; 2010-11 #14; 2011-12 #8; 2012-13 #3; 2013-14 #3; 2014-15 #2; 2015-16 #3; 2016-17 #1; 2017-18 #1; 2018-19 #2; 2023 #6; 2024 #7; 2025 #8 | P3: =IF(G3="","",PERCENTRANK($G$2:$G$85,G3)) -> 0.904 | Q3: =IF(J3="","",1-(J3-1)/20) | R3: =IF(M3="","",1-(M3-1)/(2*N3)) -> 1 | S3: =IF(K3="","",0.5+0.5*PERCENTRANK($K$2:$K$85,K3)) -> 0.9375 | T3: =IF(COUNT(Q3:S3)=0,"",MAX(Q3:S3)) -> 1 | U3: =COUNT(P3,T3) -> 2 | W3: Q1 2022 #21; Q2 2023 #25 | Y3: #92 hoje | Z3: =COUNTA(V3:Y3) -> 2 | AA3: =IF(U3=0,"",MIN(1,AVERAGE(P3,T3)+Critérios!$B$5*Z3)) -> 1 | AB3: =IF(AA3="","",IF(AA3>=Critérios!$B$7,"A",IF(AA3>=Critérios!$B$8,"B","C"))) -> A | AC3: =IF(AA3="","",RANK(AA3,$AA$2:$AA$85)) -> 1 | AD3: =IF(AA3="","Sairia — sem métrica",IF(PERCENTRANK($AA$2:$AA$85,AA3)<Critérios!$B$6,"Sairia — terço inferior","Fica")) -> Fica | AE3: coral/antologia | AH3: candidato | AJ3: S021 | AK3: tt0898266 | AL3: =COUNT(G3)+IF(OR(I3<>"",K3<>""),1,0)+IF(M3<>"",1,0)+COUNTA(V3:Y3) -> 5 | AM3: =IF(AL3>=3,"Sim","Não") -> Sim | AN3: =IF(AND(AC3<>"",AC3<=Critérios!$B$9),"Sim","Não") -> Sim
A4: S0003 | B4: The Boys | C4: The Boys | D4: 2019 | E4: Prime Video | F4: Audiência oficial (coleta) | G4: 1030960 | H4: 8.5 | M4: 3 | N4: 30 | O4: 2022 #11; 2024 #3 | P4: =IF(G4="","",PERCENTRANK($G$2:$G$85,G4)) -> 0.928 | Q4: =IF(J4="","",1-(J4-1)/20) | R4: =IF(M4="","",1-(M4-1)/(2*N4)) -> 0.96666667 | S4: =IF(K4="","",0.5+0.5*PERCENTRANK($K$2:$K$85,K4)) | T4: =IF(COUNT(Q4:S4)=0,"",MAX(Q4:S4)) -> 0.96666667 | U4: =COUNT(P4,T4) -> 2 | V4: YPulse 2024-02 (18-24) #8 | W4: 2020 (ano); ago 2020; fev 2021 | X4: semana encerrada 19 jun 2022 #1 (United States); semana encerrada 17 jul 2022 #3 (United States); semana encerrada 24 jul 2022 #6 (United States); 2020 (ano) #1 (United States) | Z4: =COUNTA(V4:Y4) -> 3 | AA4: =IF(U4=0,"",MIN(1,AVERAGE(P4,T4)+Critérios!$B$5*Z4)) -> 1 | AB4: =IF(AA4="","",IF(AA4>=Critérios!$B$7,"A",IF(AA4>=Critérios!$B$8,"B","C"))) -> A | AC4: =IF(AA4="","",RANK(AA4,$AA$2:$AA$85)) -> 1 | AD4: =IF(AA4="","Sairia — sem métrica",IF(PERCENTRANK($AA$2:$AA$85,AA4)<Critérios!$B$6,"Sairia — terço inferior","Fica")) -> Fica | AE4: coral/antologia | AF4: Classificação alta — pistas suaves | AH4: candidato | AJ4: S024 | AK4: tt1190634 | AL4: =COUNT(G4)+IF(OR(I4<>"",K4<>""),1,0)+IF(M4<>"",1,0)+COUNTA(V4:Y4) -> 5 | AM4: =IF(AL4>=3,"Sim","Não") -> Sim | AN4: =IF(AND(AC4<>"",AC4<=Critérios!$B$9),"Sim","Não") -> Sim
A5: S0004 | B5: The Office | C5: The Office | D5: 2005 | E5: NBC | F5: Audiência oficial (coleta) | G5: 854849 | H5: 9 | K5: 9000000 | M5: 1 | N5: 30 | O5: 2020 #1 | P5: =IF(G5="","",PERCENTRANK($G$2:$G$85,G5)) -> 0.88 | Q5: =IF(J5="","",1-(J5-1)/20) | R5: =IF(M5="","",1-(M5-1)/(2*N5)) -> 1 | S5: =IF(K5="","",0.5+0.5*PERCENTRANK($K$2:$K$85,K5)) -> 0.719 | T5: =IF(COUNT(Q5:S5)=0,"",MAX(Q5:S5)) -> 1 | U5: =COUNT(P5,T5) -> 2 | V5: YPulse 2020-05 (Gen Z (subgrupos 13-18 e 19-25 só em imagem)) #3 | Y5: #74 hoje | Z5: =COUNTA(V5:Y5) -> 2 | AA5: =IF(U5=0,"",MIN(1,AVERAGE(P5,T5)+Critérios!$B$5*Z5)) -> 1 | AB5: =IF(AA5="","",IF(AA5>=Critérios!$B$7,"A",IF(AA5>=Critérios!$B$8,"B","C"))) -> A | AC5: =IF(AA5="","",RANK(AA5,$AA$2:$AA$85)) -> 1 | AD5: =IF(AA5="","Sairia — sem métrica",IF(PERCENTRANK($AA$2:$AA$85,AA5)<Critérios!$B$6,"Sairia — terço inferior","Fica")) -> Fica | AE5: coral/antologia | AH5: candidato | AJ5: S022 | AK5: tt0386676 | AL5: =COUNT(G5)+IF(OR(I5<>"",K5<>""),1,0)+IF(M5<>"",1,0)+COUNTA(V5:Y5) -> 5 | AM5: =IF(AL5>=3,"Sim","Não") -> Sim | AN5: =IF(AND(AC5<>"",AC5<=Critérios!$B$9),"Sim","Não") -> Sim
A6: S0005 | B6: Round 6 | C6: Squid Game | D6: 2021 | E6: Netflix | F6: Audiência oficial (coleta) | G6: 779793 | H6: 7.9 | I6: 265200000 | J6: 1 | M6: 2 | N6: 30 | O6: 2021 #2; 2025 #2 | P6: =IF(G6="","",PERCENTRANK($G$2:$G$85,G6)) -> 0.843 | Q6: =IF(J6="","",1-(J6-1)/20) -> 1 | R6: =IF(M6="","",1-(M6-1)/(2*N6)) -> 0.98333333 | S6: =IF(K6="","",0.5+0.5*PERCENTRANK($K$2:$K$85,K6)) | T6: =IF(COUNT(Q6:S6)=0,"",MAX(Q6:S6)) -> 1 | U6: =COUNT(P6,T6) -> 2 | V6: YPulse 2025-02 (Gen Z (faixa não explicitada)); YPulse 2025-09 (Gen Z (faixa não explicitada)); UCLA Teens & Screens 2025 (top 25) 2025-10 (10-24) | X6: semana 18–24 out 2021 #2 (France); semana 25–31 out 2021 #3 (Italy); semana 1–7 nov 2021 #4 (Spain); semana 8–14 nov 2021 #5 (Germany); semana 15–21 nov 2021 #8 (France) | Z6: =COUNTA(V6:Y6) -> 2 | AA6: =IF(U6=0,"",MIN(1,AVERAGE(P6,T6)+Critérios!$B$5*Z6)) -> 0.9815 | AB6: =IF(AA6="","",IF(AA6>=Critérios!$B$7,"A",IF(AA6>=Critérios!$B$8,"B","C"))) -> A | AC6: =IF(AA6="","",RANK(AA6,$AA$2:$AA$85)) -> 5 | AD6: =IF(AA6="","Sairia — sem métrica",IF(PERCENTRANK($AA$2:$AA$85,AA6)<Critérios!$B$6,"Sairia — terço inferior","Fica")) -> Fica | AE6: claro | AH6: candidato | AJ6: S031 | AK6: tt10919420 | AL6: =COUNT(G6)+IF(OR(I6<>"",K6<>""),1,0)+IF(M6<>"",1,0)+COUNTA(V6:Y6) -> 5 | AM6: =IF(AL6>=3,"Sim","Não") -> Sim | AN6: =IF(AND(AC6<>"",AC6<=Critérios!$B$9),"Sim","Não") -> Sim
A7: S0006 | B7: The Walking Dead | C7: The Walking Dead | D7: 2010 | E7: AMC | F7: Audiência oficial (coleta) | G7: 1218228 | H7: 8.1 | K7: 14380000 | P7: =IF(G7="","",PERCENTRANK($G$2:$G$85,G7)) -> 0.964 | Q7: =IF(J7="","",1-(J7-1)/20) | R7: =IF(M7="","",1-(M7-1)/(2*N7)) | S7: =IF(K7="","",0.5+0.5*PERCENTRANK($K$2:$K$85,K7)) -> 0.8125 | T7: =IF(COUNT(Q7:S7)=0,"",MAX(Q7:S7)) -> 0.8125 | U7: =COUNT(P7,T7) -> 2 | V7: YPulse Media Consumption Monitor 2022-10 (Gen Z (faixa não explicitada; amostra 13-39)) #5; YPulse 2017-10 (Gen Z (faixa não explicitada; amostra 13-35)); YPulse 2016-09 (teens (13-17 presumido; amostra 13-33)) #1 | W7: 09 fev–09 mar 2023 #4 | Y7: #106 hoje | Z7: =COUNTA(V7:Y7) -> 3 | AA7: =IF(U7=0,"",MIN(1,AVERAGE(P7,T7)+Critérios!$B$5*Z7)) -> 0.97825 | AB7: =IF(AA7="","",IF(AA7>=Critérios!$B$7,"A",IF(AA7>=Critérios!$B$8,"B","C"))) -> A | AC7: =IF(AA7="","",RANK(AA7,$AA$2:$AA$85)) -> 6 | AD7: =IF(AA7="","Sairia — sem métrica",IF(PERCENTRANK($AA$2:$AA$85,AA7)<Critérios!$B$6,"Sairia — terço inferior","Fica")) -> Fica | AE7: coral/antologia | AF7: Classificação alta — pistas suaves | AH7: candidato | AJ7: S028 | AK7: tt1520211 | AL7: =COUNT(G7)+IF(OR(I7<>"",K7<>""),1,0)+IF(M7<>"",1,0)+COUNTA(V7:Y7) -> 5 | AM7: =IF(AL7>=3,"Sim","Não") -> Sim | AN7: =IF(AND(AC7<>"",AC7<=Critérios!$B$9),"Sim","Não") -> Sim
A8: S0007 | B8: Game of Thrones | C8: Game of Thrones | D8: 2011 | E8: HBO | F8: Audiência oficial (coleta) | G8: 2673165 | H8: 9.2 | K8: 11990000 | P8: =IF(G8="","",PERCENTRANK($G$2:$G$85,G8)) -> 0.988 | Q8: =IF(J8="","",1-(J8-1)/20) | R8: =IF(M8="","",1-(M8-1)/(2*N8)) | S8: =IF(K8="","",0.5+0.5*PERCENTRANK($K$2:$K$85,K8)) -> 0.7815 | T8: =IF(COUNT(Q8:S8)=0,"",MAX(Q8:S8)) -> 0.7815 | U8: =COUNT(P8,T8) -> 2 | V8: UCLA Teens & Screens 2025 (top 25) 2025-10 (10-24) | W8: 09 fev–09 mar 2023 #5 | Z8: =COUNTA(V8:Y8) -> 2 | AA8: =IF(U8=0,"",MIN(1,AVERAGE(P8,T8)+Critérios!$B$5*Z8)) -> 0.94475 | AB8: =IF(AA8="","",IF(AA8>=Critérios!$B$7,"A",IF(AA8>=Critérios!$B$8,"B","C"))) -> A | AC8: =IF(AA8="","",RANK(AA8,$AA$2:$AA$85)) -> 7 | AD8: =IF(AA8="","Sairia — sem métrica",IF(PERCENTRANK($AA$2:$AA$85,AA8)<Critérios!$B$6,"Sairia — terço inferior","Fica")) -> Fica | AE8: coral/antologia | AF8: Classificação alta — pistas suaves | AH8: candidato | AJ8: S006, S025 | AK8: tt0944947 | AL8: =COUNT(G8)+IF(OR(I8<>"",K8<>""),1,0)+IF(M8<>"",1,0)+COUNTA(V8:Y8) -> 4 | AM8: =IF(AL8>=3,"Sim","Não") -> Sim | AN8: =IF(AND(AC8<>"",AC8<=Critérios!$B$9),"Sim","Não") -> Sim
A9: S0008 | B9: Chernobyl | C9: Chernobyl | D9: 2019 | E9: HBO | F9: Curadoria | G9: 1070491 | H9: 9.3 | P9: =IF(G9="","",PERCENTRANK($G$2:$G$85,G9)) -> 0.94 | Q9: =IF(J9="","",1-(J9-1)/20) | R9: =IF(M9="","",1-(M9-1)/(2*N9)) | S9: =IF(K9="","",0.5+0.5*PERCENTRANK($K$2:$K$85,K9)) | T9: =IF(COUNT(Q9:S9)=0,"",MAX(Q9:S9)) | U9: =COUNT(P9,T9) -> 1 | Z9: =COUNTA(V9:Y9) -> 0 | AA9: =IF(U9=0,"",MIN(1,AVERAGE(P9,T9)+Critérios!$B$5*Z9)) -> 0.94 | AB9: =IF(AA9="","",IF(AA9>=Critérios!$B$7,"A",IF(AA9>=Critérios!$B$8,"B","C"))) -> A | AC9: =IF(AA9="","",RANK(AA9,$AA$2:$AA$85)) -> 8 | AD9: =IF(AA9="","Sairia — sem métrica",IF(PERCENTRANK($AA$2:$AA$85,AA9)<Critérios!$B$6,"Sairia — terço inferior","Fica")) -> Fica | AE9: a avaliar | AF9: Evento real | AG9: Resgatada manualmente (lista aprovada em 13/10/2026); conferir ano e título no Brasil | AH9: candidato | AK9: tt7366338 | AL9: =COUNT(G9)+IF(OR(I9<>"",K9<>""),1,0)+IF(M9<>"",1,0)+COUNTA(V9:Y9) -> 1 | AM9: =IF(AL9>=3,"Sim","Não") -> Não | AN9: =IF(AND(AC9<>"",AC9<=Critérios!$B$9),"Sim","Não") -> Sim
A10: S0009 | B10: The Last of Us | C10: The Last of Us | D10: 2023 | E10: HBO | F10: Audiência oficial (coleta) | G10: 753398 | H10: 8.4 | K10: 37000000 | P10: =IF(G10="","",PERCENTRANK($G$2:$G$85,G10)) -> 0.819 | Q10: =IF(J10="","",1-(J10-1)/20) | R10: =IF(M10="","",1-(M10-1)/(2*N10)) | S10: =IF(K10="","",0.5+0.5*PERCENTRANK($K$2:$K$85,K10)) -> 1 | T10: =IF(COUNT(Q10:S10)=0,"",MAX(Q10:S10)) -> 1 | U10: =COUNT(P10,T10) -> 2 | W10: 09 fev–09 mar 2023 #1 | Z10: =COUNTA(V10:Y10) -> 1 | AA10: =IF(U10=0,"",MIN(1,AVERAGE(P10,T10)+Critérios!$B$5*Z10)) -> 0.9395 | AB10: =IF(AA10="","",IF(AA10>=Critérios!$B$7,"A",IF(AA10>=Critérios!$B$8,"B","C"))) -> A | AC10: =IF(AA10="","",RANK(AA10,$AA$2:$AA$85)) -> 9 | AD10: =IF(AA10="","Sairia — sem métrica",IF(PERCENTRANK($AA$2:$AA$85,AA10)<Critérios!$B$6,"Sairia — terço inferior","Fica")) -> Fica | AE10: dupla | AH10: candidato | AJ10: S026 | AK10: tt3581920 | AL10: =COUNT(G10)+IF(OR(I10<>"",K10<>""),1,0)+IF(M10<>"",1,0)+COUNTA(V10:Y10) -> 3 | AM10: =IF(AL10>=3,"Sim","Não") -> Sim | AN10: =IF(AND(AC10<>"",AC10<=Critérios!$B$9),"Sim","Não") -> Sim
A11: S0010 | B11: The Mandalorian | C11: The Mandalorian | D11: 2019 | E11: Disney+ | F11: Audiência oficial (coleta) | G11: 667949 | H11: 8.6 | M11: 5 | N11: 30 | O11: 2020 #13; 2020 #5; 2023 #8 | P11: =IF(G11="","",PERCENTRANK($G$2:$G$85,G11)) -> 0.735 | Q11: =IF(J11="","",1-(J11-1)/20) | R11: =IF(M11="","",1-(M11-1)/(2*N11)) -> 0.93333333 | S11: =IF(K11="","",0.5+0.5*PERCENTRANK($K$2:$K$85,K11)) | T11: =IF(COUNT(Q11:S11)=0,"",MAX(Q11:S11)) -> 0.93333333 | U11: =COUNT(P11,T11) -> 2 | W11: 2020 (ano); nov 2020–jan 2021; 09 fev–09 mar 2023 #3 | X11: 2020 (ano) #1 (United States); 1 jan–30 nov 2023 #1 (United States) | Z11: =COUNTA(V11:Y11) -> 2 | AA11: =IF(U11=0,"",MIN(1,AVERAGE(P11,T11)+Critérios!$B$5*Z11)) -> 0.89416667 | AB11: =IF(AA11="","",IF(AA11>=Critérios!$B$7,"A",IF(AA11>=Critérios!$B$8,"B","C"))) -> A | AC11: =IF(AA11="","",RANK(AA11,$AA$2:$AA$85)) -> 10 | AD11: =IF(AA11="","Sairia — sem métrica",IF(PERCENTRANK($AA$2:$AA$85,AA11)<Critérios!$B$6,"Sairia — terço inferior","Fica")) -> Fica | AE11: claro | AH11: candidato | AJ11: S027 | AK11: tt8111088 | AL11: =COUNT(G11)+IF(OR(I11<>"",K11<>""),1,0)+IF(M11<>"",1,0)+COUNTA(V11:Y11) -> 4 | AM11: =IF(AL11>=3,"Sim","Não") -> Sim | AN11: =IF(AND(AC11<>"",AC11<=Critérios!$B$9),"Sim","Não") -> Sim
A12: S0011 | B12: Better Call Saul | C12: Better Call Saul | D12: 2015 | E12: AMC | F12: Curadoria | G12: 870449 | H12: 9 | P12: =IF(G12="","",PERCENTRANK($G$2:$G$85,G12)) -> 0.892 | Q12: =IF(J12="","",1-(J12-1)/20) | R12: =IF(M12="","",1-(M12-1)/(2*N12)) | S12: =IF(K12="","",0.5+0.5*PERCENTRANK($K$2:$K$85,K12)) | T12: =IF(COUNT(Q12:S12)=0,"",MAX(Q12:S12)) | U12: =COUNT(P12,T12) -> 1 | Z12: =COUNTA(V12:Y12) -> 0 | AA12: =IF(U12=0,"",MIN(1,AVERAGE(P12,T12)+Critérios!$B$5*Z12)) -> 0.892 | AB12: =IF(AA12="","",IF(AA12>=Critérios!$B$7,"A",IF(AA12>=Critérios!$B$8,"B","C"))) -> A | AC12: =IF(AA12="","",RANK(AA12,$AA$2:$AA$85)) -> 11 | AD12: =IF(AA12="","Sairia — sem métrica",IF(PERCENTRANK($AA$2:$AA$85,AA12)<Critérios!$B$6,"Sairia — terço inferior","Fica")) -> Fica | AE12: claro | AG12: Resgatada manualmente (lista aprovada em 13/10/2026); conferir ano e título no Brasil | AH12: candidato | AK12: tt3032476 | AL12: =COUNT(G12)+IF(OR(I12<>"",K12<>""),1,0)+IF(M12<>"",1,0)+COUNTA(V12:Y12) -> 1 | AM12: =IF(AL12>=3,"Sim","Não") -> Não | AN12: =IF(AND(AC12<>"",AC12<=Critérios!$B$9),"Sim","Não") -> Sim
A13: S0012 | B13: Sherlock | C13: Sherlock | D13: 2010 | E13: BBC One | F13: Audiência oficial (coleta) | G13: 1102781 | H13: 9 | K13: 11820000 | P13: =IF(G13="","",PERCENTRANK($G$2:$G$85,G13)) -> 0.952 | Q13: =IF(J13="","",1-(J13-1)/20) | R13: =IF(M13="","",1-(M13-1)/(2*N13)) | S13: =IF(K13="","",0.5+0.5*PERCENTRANK($K$2:$K$85,K13)) -> 0.75 | T13: =IF(COUNT(Q13:S13)=0,"",MAX(Q13:S13)) -> 0.75 | U13: =COUNT(P13,T13) -> 2 | Y13: #148 hoje | Z13: =COUNTA(V13:Y13) -> 1 | AA13: =IF(U13=0,"",MIN(1,AVERAGE(P13,T13)+Critérios!$B$5*Z13)) -> 0.881 | AB13: =IF(AA13="","",IF(AA13>=Critérios!$B$7,"A",IF(AA13>=Critérios!$B$8,"B","C"))) -> A | AC13: =IF(AA13="","",RANK(AA13,$AA$2:$AA$85)) -> 12 | AD13: =IF(AA13="","Sairia — sem métrica",IF(PERCENTRANK($AA$2:$AA$85,AA13)<Critérios!$B$6,"Sairia — terço inferior","Fica")) -> Fica | AE13: claro | AH13: candidato | AJ13: S019 | AK13: tt1475582 | AL13: =COUNT(G13)+IF(OR(I13<>"",K13<>""),1,0)+IF(M13<>"",1,0)+COUNTA(V13:Y13) -> 3 | AM13: =IF(AL13>=3,"Sim","Não") -> Sim | AN13: =IF(AND(AC13<>"",AC13<=Critérios!$B$9),"Sim","Não") -> Sim
A14: S0013 | B14: Breaking Bad | C14: Breaking Bad | D14: 2008 | E14: AMC | F14: Audiência oficial (coleta) | G14: 2690329 | H14: 9.5 | K14: 6040000 | P14: =IF(G14="","",PERCENTRANK($G$2:$G$85,G14)) -> 1 | Q14: =IF(J14="","",1-(J14-1)/20) | R14: =IF(M14="","",1-(M14-1)/(2*N14)) | S14: =IF(K14="","",0.5+0.5*PERCENTRANK($K$2:$K$85,K14)) -> 0.6875 | T14: =IF(COUNT(Q14:S14)=0,"",MAX(Q14:S14)) -> 0.6875 | U14: =COUNT(P14,T14) -> 2 | Y14: #48 hoje | Z14: =COUNTA(V14:Y14) -> 1 | AA14: =IF(U14=0,"",MIN(1,AVERAGE(P14,T14)+Critérios!$B$5*Z14)) -> 0.87375 | AB14: =IF(AA14="","",IF(AA14>=Critérios!$B$7,"A",IF(AA14>=Critérios!$B$8,"B","C"))) -> A | AC14: =IF(AA14="","",RANK(AA14,$AA$2:$AA$85)) -> 13 | AD14: =IF(AA14="","Sairia — sem métrica",IF(PERCENTRANK($AA$2:$AA$85,AA14)<Critérios!$B$6,"Sairia — terço inferior","Fica")) -> Fica | AE14: claro | AF14: Classificação alta — pistas suaves | AH14: candidato | AJ14: S005, S011 | AK14: tt0903747 | AL14: =COUNT(G14)+IF(OR(I14<>"",K14<>""),1,0)+IF(M14<>"",1,0)+COUNTA(V14:Y14) -> 3 | AM14: =IF(AL14>=3,"Sim","Não") -> Sim | AN14: =IF(AND(AC14<>"",AC14<=Critérios!$B$9),"Sim","Não") -> Sim
A15: S0014 | B15: Attack on Titan | C15: Attack on Titan | D15: 2013 | E15: MBS (anime) | F15: Curadoria | G15: 752978 | H15: 9.1 | P15: =IF(G15="","",PERCENTRANK($G$2:$G$85,G15)) -> 0.807 | Q15: =IF(J15="","",1-(J15-1)/20) | R15: =IF(M15="","",1-(M15-1)/(2*N15)) | S15: =IF(K15="","",0.5+0.5*PERCENTRANK($K$2:$K$85,K15)) | T15: =IF(COUNT(Q15:S15)=0,"",MAX(Q15:S15)) | U15: =COUNT(P15,T15) -> 1 | W15: Q1 2022 #1 | Y15: #93 hoje | Z15: =COUNTA(V15:Y15) -> 2 | AA15: =IF(U15=0,"",MIN(1,AVERAGE(P15,T15)+Critérios!$B$5*Z15)) -> 0.867 | AB15: =IF(AA15="","",IF(AA15>=Critérios!$B$7,"A",IF(AA15>=Critérios!$B$8,"B","C"))) -> A | AC15: =IF(AA15="","",RANK(AA15,$AA$2:$AA$85)) -> 14 | AD15: =IF(AA15="","Sairia — sem métrica",IF(PERCENTRANK($AA$2:$AA$85,AA15)<Critérios!$B$6,"Sairia — terço inferior","Fica")) -> Fica | AE15: claro | AG15: conferir ano e título no Brasil | AH15: candidato | AK15: tt2560140 | AL15: =COUNT(G15)+IF(OR(I15<>"",K15<>""),1,0)+IF(M15<>"",1,0)+COUNTA(V15:Y15) -> 3 | AM15: =IF(AL15>=3,"Sim","Não") -> Sim | AN15: =IF(AND(AC15<>"",AC15<=Critérios!$B$9),"Sim","Não") -> Sim
A16: S0015 | B16: True Detective | C16: True Detective | D16: 2014 | E16: HBO | F16: Curadoria | G16: 774987 | H16: 8.8 | P16: =IF(G16="","",PERCENTRANK($G$2:$G$85,G16)) -> 0.831 | Q16: =IF(J16="","",1-(J16-1)/20) | R16: =IF(M16="","",1-(M16-1)/(2*N16)) | S16: =IF(K16="","",0.5+0.5*PERCENTRANK($K$2:$K$85,K16)) | T16: =IF(COUNT(Q16:S16)=0,"",MAX(Q16:S16)) | U16: =COUNT(P16,T16) -> 1 | Y16: #56 hoje | Z16: =COUNTA(V16:Y16) -> 1 | AA16: =IF(U16=0,"",MIN(1,AVERAGE(P16,T16)+Critérios!$B$5*Z16)) -> 0.861 | AB16: =IF(AA16="","",IF(AA16>=Critérios!$B$7,"A",IF(AA16>=Critérios!$B$8,"B","C"))) -> A | AC16: =IF(AA16="","",RANK(AA16,$AA$2:$AA$85)) -> 15 | AD16: =IF(AA16="","Sairia — sem métrica",IF(PERCENTRANK($AA$2:$AA$85,AA16)<Critérios!$B$6,"Sairia — terço inferior","Fica")) -> Fica | AE16: dupla | AG16: Resgatada manualmente (lista aprovada em 13/10/2026); conferir ano e título no Brasil | AH16: candidato | AK16: tt2356777 | AL16: =COUNT(G16)+IF(OR(I16<>"",K16<>""),1,0)+IF(M16<>"",1,0)+COUNTA(V16:Y16) -> 2 | AM16: =IF(AL16>=3,"Sim","Não") -> Não | AN16: =IF(AND(AC16<>"",AC16<=Critérios!$B$9),"Sim","Não") -> Sim
A17: S0016 | B17: Sobrenatural | C17: Supernatural | D17: 2005 | E17: The WB / The CW | F17: Audiência oficial (coleta) | G17: 550684 | H17: 8.4 | K17: 3810000 | M17: 7 | N17: 30 | O17: 2020 #7; 2022 #11; 2022 #8; 2023 #10 | P17: =IF(G17="","",PERCENTRANK($G$2:$G$85,G17)) -> 0.639 | Q17: =IF(J17="","",1-(J17-1)/20) | R17: =IF(M17="","",1-(M17-1)/(2*N17)) -> 0.9 | S17: =IF(K17="","",0.5+0.5*PERCENTRANK($K$2:$K$85,K17)) -> 0.625 | T17: =IF(COUNT(Q17:S17)=0,"",MAX(Q17:S17)) -> 0.9 | U17: =COUNT(P17,T17) -> 2 | V17: YPulse 2016-09 (teens (13-17 presumido; amostra 13-33)) | W17: Q2 2023 #10 | Y17: #36 hoje | Z17: =COUNTA(V17:Y17) -> 3 | AA17: =IF(U17=0,"",MIN(1,AVERAGE(P17,T17)+Critérios!$B$5*Z17)) -> 0.8595 | AB17: =IF(AA17="","",IF(AA17>=Critérios!$B$7,"A",IF(AA17>=Critérios!$B$8,"B","C"))) -> A | AC17: =IF(AA17="","",RANK(AA17,$AA$2:$AA$85)) -> 16 | AD17: =IF(AA17="","Sairia — sem métrica",IF(PERCENTRANK($AA$2:$AA$85,AA17)<Critérios!$B$6,"Sairia — terço inferior","Fica")) -> Fica | AE17: dupla | AH17: candidato | AJ17: S020 | AK17: tt0460681 | AL17: =COUNT(G17)+IF(OR(I17<>"",K17<>""),1,0)+IF(M17<>"",1,0)+COUNTA(V17:Y17) -> 6 | AM17: =IF(AL17>=3,"Sim","Não") -> Sim | AN17: =IF(AND(AC17<>"",AC17<=Critérios!$B$9),"Sim","Não") -> Sim
A18: S0017 | B18: Suits | C18: Suits | D18: 2011 | F18: Adicionado por: Nielsen | G18: 551397 | H18: 8.4 | M18: 1 | N18: 30 | O18: 2023 #1 | P18: =IF(G18="","",PERCENTRANK($G$2:$G$85,G18)) -> 0.651 | Q18: =IF(J18="","",1-(J18-1)/20) | R18: =IF(M18="","",1-(M18-1)/(2*N18)) -> 1 | S18: =IF(K18="","",0.5+0.5*PERCENTRANK($K$2:$K$85,K18)) | T18: =IF(COUNT(Q18:S18)=0,"",MAX(Q18:S18)) -> 1 | U18: =COUNT(P18,T18) -> 2 | Y18: #157 hoje | Z18: =COUNTA(V18:Y18) -> 1 | AA18: =IF(U18=0,"",MIN(1,AVERAGE(P18,T18)+Critérios!$B$5*Z18)) -> 0.8555 | AB18: =IF(AA18="","",IF(AA18>=Critérios!$B$7,"A",IF(AA18>=Critérios!$B$8,"B","C"))) -> A | AC18: =IF(AA18="","",RANK(AA18,$AA$2:$AA$85)) -> 17 | AD18: =IF(AA18="","Sairia — sem métrica",IF(PERCENTRANK($AA$2:$AA$85,AA18)<Critérios!$B$6,"Sairia — terço inferior","Fica")) -> Fica | AE18: a avaliar | AH18: candidato | AK18: tt1632701 | AL18: =COUNT(G18)+IF(OR(I18<>"",K18<>""),1,0)+IF(M18<>"",1,0)+COUNTA(V18:Y18) -> 3 | AM18: =IF(AL18>=3,"Sim","Não") -> Sim | AN18: =IF(AND(AC18<>"",AC18<=Critérios!$B$9),"Sim","Não") -> Sim
A19: S0018 | B19: Black Mirror | C19: Black Mirror | D19: 2011 | E19: Channel 4 / Netflix | F19: Curadoria | G19: 751499 | H19: 8.7 | P19: =IF(G19="","",PERCENTRANK($G$2:$G$85,G19)) -> 0.795 | Q19: =IF(J19="","",1-(J19-1)/20) | R19: =IF(M19="","",1-(M19-1)/(2*N19)) | S19: =IF(K19="","",0.5+0.5*PERCENTRANK($K$2:$K$85,K19)) | T19: =IF(COUNT(Q19:S19)=0,"",MAX(Q19:S19)) | U19: =COUNT(P19,T19) -> 1 | X19: 1 jan–30 nov 2023 #6 (United States) | Y19: #139 hoje | Z19: =COUNTA(V19:Y19) -> 2 | AA19: =IF(U19=0,"",MIN(1,AVERAGE(P19,T19)+Critérios!$B$5*Z19)) -> 0.855 | AB19: =IF(AA19="","",IF(AA19>=Critérios!$B$7,"A",IF(AA19>=Critérios!$B$8,"B","C"))) -> A | AC19: =IF(AA19="","",RANK(AA19,$AA$2:$AA$85)) -> 18 | AD19: =IF(AA19="","Sairia — sem métrica",IF(PERCENTRANK($AA$2:$AA$85,AA19)<Critérios!$B$6,"Sairia — terço inferior","Fica")) -> Fica | AE19: coral/antologia | AG19: conferir ano e título no Brasil | AH19: candidato | AK19: tt2085059 | AL19: =COUNT(G19)+IF(OR(I19<>"",K19<>""),1,0)+IF(M19<>"",1,0)+COUNTA(V19:Y19) -> 3 | AM19: =IF(AL19>=3,"Sim","Não") -> Sim | AN19: =IF(AND(AC19<>"",AC19<=Critérios!$B$9),"Sim","Não") -> Sim
A20: S0019 | B20: Wandinha | C20: Wednesday | D20: 2022 | E20: Netflix | F20: Audiência oficial (coleta) | G20: 511554 | H20: 8 | I20: 252100000 | J20: 1 | M20: 3 | N20: 30 | O20: 2022 #12; 2022 #3; 2025 #3 | P20: =IF(G20="","",PERCENTRANK($G$2:$G$85,G20)) -> 0.627 | Q20: =IF(J20="","",1-(J20-1)/20) -> 1 | R20: =IF(M20="","",1-(M20-1)/(2*N20)) -> 0.96666667 | S20: =IF(K20="","",0.5+0.5*PERCENTRANK($K$2:$K$85,K20)) | T20: =IF(COUNT(Q20:S20)=0,"",MAX(Q20:S20)) -> 1 | U20: =COUNT(P20,T20) -> 2 | V20: UCLA Center for Scholars & Storytellers 2025-10 (10-24) #2 | Z20: =COUNTA(V20:Y20) -> 1 | AA20: =IF(U20=0,"",MIN(1,AVERAGE(P20,T20)+Critérios!$B$5*Z20)) -> 0.8435 | AB20: =IF(AA20="","",IF(AA20>=Critérios!$B$7,"A",IF(AA20>=Critérios!$B$8,"B","C"))) -> A | AC20: =IF(AA20="","",RANK(AA20,$AA$2:$AA$85)) -> 19 | AD20: =IF(AA20="","Sairia — sem métrica",IF(PERCENTRANK($AA$2:$AA$85,AA20)<Critérios!$B$6,"Sairia — terço inferior","Fica")) -> Fica | AE20: claro | AH20: candidato | AJ20: S030 | AK20: tt13443470 | AL20: =COUNT(G20)+IF(OR(I20<>"",K20<>""),1,0)+IF(M20<>"",1,0)+COUNTA(V20:Y20) -> 4 | AM20: =IF(AL20>=3,"Sim","Não") -> Sim | AN20: =IF(AND(AC20<>"",AC20<=Critérios!$B$9),"Sim","Não") -> Sim
A21: S0020 | B21: Rick e Morty | C21: Rick and Morty | D21: 2013 | F21: Adicionado por: Geração Z | G21: 715759 | H21: 9 | P21: =IF(G21="","",PERCENTRANK($G$2:$G$85,G21)) -> 0.783 | Q21: =IF(J21="","",1-(J21-1)/20) | R21: =IF(M21="","",1-(M21-1)/(2*N21)) | S21: =IF(K21="","",0.5+0.5*PERCENTRANK($K$2:$K$85,K21)) | T21: =IF(COUNT(Q21:S21)=0,"",MAX(Q21:S21)) | U21: =COUNT(P21,T21) -> 1 | V21: YPulse 2024-02 (18-24) #5; YPulse Media Consumption Monitor 2022-10 (Gen Z (faixa não explicitada; amostra 13-39)) #3; YPulse 2020-05 (13-18 e 19-25); YPulse 2017-10 (Gen Z (faixa não explicitada; amostra 13-35)) | Y21: #66 hoje | Z21: =COUNTA(V21:Y21) -> 2 | AA21: =IF(U21=0,"",MIN(1,AVERAGE(P21,T21)+Critérios!$B$5*Z21)) -> 0.843 | AB21: =IF(AA21="","",IF(AA21>=Critérios!$B$7,"A",IF(AA21>=Critérios!$B$8,"B","C"))) -> A | AC21: =IF(AA21="","",RANK(AA21,$AA$2:$AA$85)) -> 20 | AD21: =IF(AA21="","Sairia — sem métrica",IF(PERCENTRANK($AA$2:$AA$85,AA21)<Critérios!$B$6,"Sairia — terço inferior","Fica")) -> Fica | AE21: a avaliar | AH21: candidato | AK21: tt2861424 | AL21: =COUNT(G21)+IF(OR(I21<>"",K21<>""),1,0)+IF(M21<>"",1,0)+COUNTA(V21:Y21) -> 3 | AM21: =IF(AL21>=3,"Sim","Não") -> Sim | AN21: =IF(AND(AC21<>"",AC21<=Critérios!$B$9),"Sim","Não") -> Sim
A22: S0021 | B22: Grey's Anatomy | C22: Grey's Anatomy | D22: 2005 | E22: ABC | F22: Audiência oficial (coleta) | G22: 378772 | H22: 7.6 | K22: 21070000 | M22: 2 | N22: 30 | O22: 2004-05 #8; 2005-06 #5; 2006-07 #7; 2007-08 #9; 2008-09 #10; 2009-10 #11; 2010-11 #17; 2011-12 #21; 2012-13 #18; 2013-14 #11; 2014-15 #17; 2015-16 #11; 2016-17 #16; 2017-18 #12; 2018-19 #20; 2019-20 #22; 2020 #2; 2021 #3; 2022 #6; 2022 #3; 2023 #4; 2024 #2; 2025 #2 | P22: =IF(G22="","",PERCENTRANK($G$2:$G$85,G22)) -> 0.518 | Q22: =IF(J22="","",1-(J22-1)/20) | R22: =IF(M22="","",1-(M22-1)/(2*N22)) -> 0.98333333 | S22: =IF(K22="","",0.5+0.5*PERCENTRANK($K$2:$K$85,K22)) -> 0.969 | T22: =IF(COUNT(Q22:S22)=0,"",MAX(Q22:S22)) -> 0.98333333 | U22: =COUNT(P22,T22) -> 2 | V22: YPulse 2024-02 (13-17) #5; YPulse 2024-02 (18-24) #1; YPulse Media Consumption Monitor 2022-10 (Gen Z (faixa não explicitada; amostra 13-39)) #7; YPulse 2025-02 (Gen Z (faixa não explicitada)); YPulse 2018-10 (18-24) | W22: nov 2020–jan 2021; 2022 (ano) #6; Q1 2024 | Y22: #37 hoje | Z22: =COUNTA(V22:Y22) -> 3 | AA22: =IF(U22=0,"",MIN(1,AVERAGE(P22,T22)+Critérios!$B$5*Z22)) -> 0.84066667 | AB22: =IF(AA22="","",IF(AA22>=Critérios!$B$7,"A",IF(AA22>=Critérios!$B$8,"B","C"))) -> A | AC22: =IF(AA22="","",RANK(AA22,$AA$2:$AA$85)) -> 21 | AD22: =IF(AA22="","Sairia — sem métrica",IF(PERCENTRANK($AA$2:$AA$85,AA22)<Critérios!$B$6,"Sairia — terço inferior","Fica")) -> Fica | AE22: claro | AH22: candidato | AJ22: S007 | AK22: tt0413573 | AL22: =COUNT(G22)+IF(OR(I22<>"",K22<>""),1,0)+IF(M22<>"",1,0)+COUNTA(V22:Y22) -> 6 | AM22: =IF(AL22>=3,"Sim","Não") -> Sim | AN22: =IF(AND(AC22<>"",AC22<=Critérios!$B$9),"Sim","Não") -> Sim
A23: S0022 | B23: Lucifer | C23: Lucifer | D23: 2016 | E23: FOX / Netflix | F23: Curadoria | G23: 398892 | H23: 8 | M23: 1 | N23: 30 | O23: 2020 #8; 2020 #2; 2021 #1 | P23: =IF(G23="","",PERCENTRANK($G$2:$G$85,G23)) -> 0.554 | Q23: =IF(J23="","",1-(J23-1)/20) | R23: =IF(M23="","",1-(M23-1)/(2*N23)) -> 1 | S23: =IF(K23="","",0.5+0.5*PERCENTRANK($K$2:$K$85,K23)) | T23: =IF(COUNT(Q23:S23)=0,"",MAX(Q23:S23)) -> 1 | U23: =COUNT(P23,T23) -> 2 | W23: ago 2020 #2 | X23: semana 25–31 out 2021 #4 (Italy); semana 8–14 nov 2021 #1 (Germany); semana 15–21 nov 2021 #7 (France); 2020 (ano) #1 (United States) | Z23: =COUNTA(V23:Y23) -> 2 | AA23: =IF(U23=0,"",MIN(1,AVERAGE(P23,T23)+Critérios!$B$5*Z23)) -> 0.837 | AB23: =IF(AA23="","",IF(AA23>=Critérios!$B$7,"A",IF(AA23>=Critérios!$B$8,"B","C"))) -> A | AC23: =IF(AA23="","",RANK(AA23,$AA$2:$AA$85)) -> 22 | AD23: =IF(AA23="","Sairia — sem métrica",IF(PERCENTRANK($AA$2:$AA$85,AA23)<Critérios!$B$6,"Sairia — terço inferior","Fica")) -> Fica | AE23: claro | AG23: conferir ano e título no Brasil | AH23: candidato | AK23: tt4052886 | AL23: =COUNT(G23)+IF(OR(I23<>"",K23<>""),1,0)+IF(M23<>"",1,0)+COUNTA(V23:Y23) -> 4 | AM23: =IF(AL23>=3,"Sim","Não") -> Sim | AN23: =IF(AND(AC23<>"",AC23<=Critérios!$B$9),"Sim","Não") -> Sim
A24: S0023 | B24: La Casa de Papel | C24: Money Heist (La casa de papel) | D24: 2017 | E24: Netflix | F24: Audiência oficial (coleta) | G24: 621465 | H24: 8.2 | I24: 106000000 | J24: 4 | P24: =IF(G24="","",PERCENTRANK($G$2:$G$85,G24)) -> 0.699 | Q24: =IF(J24="","",1-(J24-1)/20) -> 0.85 | R24: =IF(M24="","",1-(M24-1)/(2*N24)) | S24: =IF(K24="","",0.5+0.5*PERCENTRANK($K$2:$K$85,K24)) | T24: =IF(COUNT(Q24:S24)=0,"",MAX(Q24:S24)) -> 0.85 | U24: =COUNT(P24,T24) -> 2 | W24: 2018 (ano) #1 | X24: semana 29 nov–5 dez 2021 #1 (Spain) | Z24: =COUNTA(V24:Y24) -> 2 | AA24: =IF(U24=0,"",MIN(1,AVERAGE(P24,T24)+Critérios!$B$5*Z24)) -> 0.8345 | AB24: =IF(AA24="","",IF(AA24>=Critérios!$B$7,"A",IF(AA24>=Critérios!$B$8,"B","C"))) -> A | AC24: =IF(AA24="","",RANK(AA24,$AA$2:$AA$85)) -> 23 | AD24: =IF(AA24="","Sairia — sem métrica",IF(PERCENTRANK($AA$2:$AA$85,AA24)<Critérios!$B$6,"Sairia — terço inferior","Fica")) -> Fica | AE24: coral/antologia | AH24: candidato | AJ24: S031 | AK24: tt6468322 | AL24: =COUNT(G24)+IF(OR(I24<>"",K24<>""),1,0)+IF(M24<>"",1,0)+COUNTA(V24:Y24) -> 4 | AM24: =IF(AL24>=3,"Sim","Não") -> Sim | AN24: =IF(AND(AC24<>"",AC24<=Critérios!$B$9),"Sim","Não") -> Sim
A25: S0024 | B25: Dr. House | C25: House | D25: 2004 | E25: FOX | F25: Audiência oficial (coleta) | G25: 602297 | H25: 8.7 | K25: 19400000 | M25: 8 | N25: 40 | O25: 2004-05 #23; 2005-06 #9; 2006-07 #8; 2007-08 #8; 2008-09 #17; 2009-10 #22 | P25: =IF(G25="","",PERCENTRANK($G$2:$G$85,G25)) -> 0.687 | Q25: =IF(J25="","",1-(J25-1)/20) | R25: =IF(M25="","",1-(M25-1)/(2*N25)) -> 0.9125 | S25: =IF(K25="","",0.5+0.5*PERCENTRANK($K$2:$K$85,K25)) -> 0.9065 | T25: =IF(COUNT(Q25:S25)=0,"",MAX(Q25:S25)) -> 0.9125 | U25: =COUNT(P25,T25) -> 2 | Y25: #146 hoje | Z25: =COUNTA(V25:Y25) -> 1 | AA25: =IF(U25=0,"",MIN(1,AVERAGE(P25,T25)+Critérios!$B$5*Z25)) -> 0.82975 | AB25: =IF(AA25="","",IF(AA25>=Critérios!$B$7,"A",IF(AA25>=Critérios!$B$8,"B","C"))) -> A | AC25: =IF(AA25="","",RANK(AA25,$AA$2:$AA$85)) -> 24 | AD25: =IF(AA25="","Sairia — sem métrica",IF(PERCENTRANK($AA$2:$AA$85,AA25)<Critérios!$B$6,"Sairia — terço inferior","Fica")) -> Fica | AE25: claro | AH25: candidato | AJ25: S015 | AK25: tt0412142 | AL25: =COUNT(G25)+IF(OR(I25<>"",K25<>""),1,0)+IF(M25<>"",1,0)+COUNTA(V25:Y25) -> 4 | AM25: =IF(AL25>=3,"Sim","Não") -> Sim | AN25: =IF(AND(AC25<>"",AC25<=Critérios!$B$9),"Sim","Não") -> Sim
A26: S0025 | B26: Lost | C26: Lost | D26: 2004 | E26: ABC | F26: Audiência oficial (coleta) | G26: 684188 | H26: 8.3 | K26: 17840000 | M26: 13 | N26: 40 | O26: 2004-05 #13; 2005-06 #18; 2006-07 #22; 2007-08 #20; 2008-09 #29; 2009-10 #24 | P26: =IF(G26="","",PERCENTRANK($G$2:$G$85,G26)) -> 0.771 | Q26: =IF(J26="","",1-(J26-1)/20) | R26: =IF(M26="","",1-(M26-1)/(2*N26)) -> 0.85 | S26: =IF(K26="","",0.5+0.5*PERCENTRANK($K$2:$K$85,K26)) -> 0.875 | T26: =IF(COUNT(Q26:S26)=0,"",MAX(Q26:S26)) -> 0.875 | U26: =COUNT(P26,T26) -> 2 | Z26: =COUNTA(V26:Y26) -> 0 | AA26: =IF(U26=0,"",MIN(1,AVERAGE(P26,T26)+Critérios!$B$5*Z26)) -> 0.823 | AB26: =IF(AA26="","",IF(AA26>=Critérios!$B$7,"A",IF(AA26>=Critérios!$B$8,"B","C"))) -> A | AC26: =IF(AA26="","",RANK(AA26,$AA$2:$AA$85)) -> 25 | AD26: =IF(AA26="","Sairia — sem métrica",IF(PERCENTRANK($AA$2:$AA$85,AA26)<Critérios!$B$6,"Sairia — terço inferior","Fica")) -> Fica | AE26: coral/antologia | AH26: candidato | AJ26: S016 | AK26: tt0411008 | AL26: =COUNT(G26)+IF(OR(I26<>"",K26<>""),1,0)+IF(M26<>"",1,0)+COUNTA(V26:Y26) -> 3 | AM26: =IF(AL26>=3,"Sim","Não") -> Sim | AN26: =IF(AND(AC26<>"",AC26<=Critérios!$B$9),"Sim","Não") -> Sim
A27: S0026 | B27: Ozark | C27: Ozark | D27: 2017 | E27: Netflix | F27: Curadoria | G27: 400954 | H27: 8.4 | M27: 1 | N27: 30 | O27: 2020 #4; 2020 #1; 2022 #4; 2022 #2 | P27: =IF(G27="","",PERCENTRANK($G$2:$G$85,G27)) -> 0.566 | Q27: =IF(J27="","",1-(J27-1)/20) | R27: =IF(M27="","",1-(M27-1)/(2*N27)) -> 1 | S27: =IF(K27="","",0.5+0.5*PERCENTRANK($K$2:$K$85,K27)) | T27: =IF(COUNT(Q27:S27)=0,"",MAX(Q27:S27)) -> 1 | U27: =COUNT(P27,T27) -> 2 | X27: semana 17–23 jan 2022 #4 (Germany); semana 17–23 jan 2022 #1 (United States); semana encerrada 20 fev 2022 #6 (United States); semana encerrada 19 jun 2022 #10 (United States); 2020 (ano) #3 (United States) | Z27: =COUNTA(V27:Y27) -> 1 | AA27: =IF(U27=0,"",MIN(1,AVERAGE(P27,T27)+Critérios!$B$5*Z27)) -> 0.813 | AB27: =IF(AA27="","",IF(AA27>=Critérios!$B$7,"A",IF(AA27>=Critérios!$B$8,"B","C"))) -> A | AC27: =IF(AA27="","",RANK(AA27,$AA$2:$AA$85)) -> 26 | AD27: =IF(AA27="","Sairia — sem métrica",IF(PERCENTRANK($AA$2:$AA$85,AA27)<Critérios!$B$6,"Sairia — terço inferior","Fica")) -> Fica | AE27: claro | AG27: conferir ano e título no Brasil | AH27: candidato | AK27: tt5071412 | AL27: =COUNT(G27)+IF(OR(I27<>"",K27<>""),1,0)+IF(M27<>"",1,0)+COUNTA(V27:Y27) -> 3 | AM27: =IF(AL27>=3,"Sim","Não") -> Sim | AN27: =IF(AND(AC27<>"",AC27<=Critérios!$B$9),"Sim","Não") -> Sim
A28: S0027 | B28: The Witcher | C28: The Witcher | D28: 2019 | E28: Netflix | F28: Curadoria | G28: 626335 | H28: 7.8 | M28: 15 | N28: 30 | O28: 2021 #15 | P28: =IF(G28="","",PERCENTRANK($G$2:$G$85,G28)) -> 0.711 | Q28: =IF(J28="","",1-(J28-1)/20) | R28: =IF(M28="","",1-(M28-1)/(2*N28)) -> 0.76666667 | S28: =IF(K28="","",0.5+0.5*PERCENTRANK($K$2:$K$85,K28)) | T28: =IF(COUNT(Q28:S28)=0,"",MAX(Q28:S28)) -> 0.76666667 | U28: =COUNT(P28,T28) -> 2 | W28: fev 2020 #3 | X28: semana 3–9 jan 2022 #2 (United States); 1 jan–30 nov 2023 #10 (United States) | Z28: =COUNTA(V28:Y28) -> 2 | AA28: =IF(U28=0,"",MIN(1,AVERAGE(P28,T28)+Critérios!$B$5*Z28)) -> 0.79883333 | AB28: =IF(AA28="","",IF(AA28>=Critérios!$B$7,"A",IF(AA28>=Critérios!$B$8,"B","C"))) -> A | AC28: =IF(AA28="","",RANK(AA28,$AA$2:$AA$85)) -> 27 | AD28: =IF(AA28="","Sairia — sem métrica",IF(PERCENTRANK($AA$2:$AA$85,AA28)<Critérios!$B$6,"Sairia — terço inferior","Fica")) -> Fica | AE28: claro | AG28: conferir ano e título no Brasil | AH28: candidato | AK28: tt5180504 | AL28: =COUNT(G28)+IF(OR(I28<>"",K28<>""),1,0)+IF(M28<>"",1,0)+COUNTA(V28:Y28) -> 4 | AM28: =IF(AL28>=3,"Sim","Não") -> Sim | AN28: =IF(AND(AC28<>"",AC28<=Critérios!$B$9),"Sim","Não") -> Sim
A29: S0028 | B29: Fallout | C29: Fallout | D29: 2024 | E29: Prime Video | F29: Curadoria | G29: 405527 | H29: 8.3 | M29: 5 | N29: 30 | O29: 2024 #5 | P29: =IF(G29="","",PERCENTRANK($G$2:$G$85,G29)) -> 0.578 | Q29: =IF(J29="","",1-(J29-1)/20) | R29: =IF(M29="","",1-(M29-1)/(2*N29)) -> 0.93333333 | S29: =IF(K29="","",0.5+0.5*PERCENTRANK($K$2:$K$85,K29)) | T29: =IF(COUNT(Q29:S29)=0,"",MAX(Q29:S29)) -> 0.93333333 | U29: =COUNT(P29,T29) -> 2 | X29: semana encerrada 12 mai 2024 #5 (United States) | Z29: =COUNTA(V29:Y29) -> 1 | AA29: =IF(U29=0,"",MIN(1,AVERAGE(P29,T29)+Critérios!$B$5*Z29)) -> 0.78566667 | AB29: =IF(AA29="","",IF(AA29>=Critérios!$B$7,"A",IF(AA29>=Critérios!$B$8,"B","C"))) -> A | AC29: =IF(AA29="","",RANK(AA29,$AA$2:$AA$85)) -> 28 | AD29: =IF(AA29="","Sairia — sem métrica",IF(PERCENTRANK($AA$2:$AA$85,AA29)<Critérios!$B$6,"Sairia — terço inferior","Fica")) -> Fica | AE29: a avaliar | AG29: conferir ano e título no Brasil | AH29: candidato | AK29: tt12637874 | AL29: =COUNT(G29)+IF(OR(I29<>"",K29<>""),1,0)+IF(M29<>"",1,0)+COUNTA(V29:Y29) -> 3 | AM29: =IF(AL29>=3,"Sim","Não") -> Sim | AN29: =IF(AND(AC29<>"",AC29<=Critérios!$B$9),"Sim","Não") -> Sim
A30: S0029 | B30: Dexter | C30: Dexter | D30: 2006 | E30: Showtime | F30: Audiência oficial (coleta) | G30: 959262 | H30: 8.6 | K30: 2360000 | P30: =IF(G30="","",PERCENTRANK($G$2:$G$85,G30)) -> 0.916 | Q30: =IF(J30="","",1-(J30-1)/20) | R30: =IF(M30="","",1-(M30-1)/(2*N30)) | S30: =IF(K30="","",0.5+0.5*PERCENTRANK($K$2:$K$85,K30)) -> 0.53125 | T30: =IF(COUNT(Q30:S30)=0,"",MAX(Q30:S30)) -> 0.53125 | U30: =COUNT(P30,T30) -> 2 | V30: UCLA Teens & Screens 2025 (top 25) 2025-10 (10-24) | Y30: #107 hoje | Z30: =COUNTA(V30:Y30) -> 2 | AA30: =IF(U30=0,"",MIN(1,AVERAGE(P30,T30)+Critérios!$B$5*Z30)) -> 0.783625 | AB30: =IF(AA30="","",IF(AA30>=Critérios!$B$7,"A",IF(AA30>=Critérios!$B$8,"B","C"))) -> A | AC30: =IF(AA30="","",RANK(AA30,$AA$2:$AA$85)) -> 29 | AD30: =IF(AA30="","Sairia — sem métrica",IF(PERCENTRANK($AA$2:$AA$85,AA30)<Critérios!$B$6,"Sairia — terço inferior","Fica")) -> Fica | AE30: claro | AF30: Classificação alta — pistas suaves | AH30: candidato | AJ30: S012 | AK30: tt0773262 | AL30: =COUNT(G30)+IF(OR(I30<>"",K30<>""),1,0)+IF(M30<>"",1,0)+COUNTA(V30:Y30) -> 4 | AM30: =IF(AL30>=3,"Sim","Não") -> Sim | AN30: =IF(AND(AC30<>"",AC30<=Critérios!$B$9),"Sim","Não") -> Sim
A31: S0030 | B31: Reacher | C31: Reacher | D31: 2022 | E31: Prime Video | F31: Curadoria | G31: 323748 | H31: 8 | M31: 5 | N31: 30 | O31: 2024 #10; 2025 #5 | P31: =IF(G31="","",PERCENTRANK($G$2:$G$85,G31)) -> 0.446 | Q31: =IF(J31="","",1-(J31-1)/20) | R31: =IF(M31="","",1-(M31-1)/(2*N31)) -> 0.93333333 | S31: =IF(K31="","",0.5+0.5*PERCENTRANK($K$2:$K$85,K31)) | T31: =IF(COUNT(Q31:S31)=0,"",MAX(Q31:S31)) -> 0.93333333 | U31: =COUNT(P31,T31) -> 2 | V31: YPulse 2024-02 (18-24) #10 | X31: semana encerrada 20 fev 2022 #7 (United States) | Y31: #6 hoje | Z31: =COUNTA(V31:Y31) -> 3 | AA31: =IF(U31=0,"",MIN(1,AVERAGE(P31,T31)+Critérios!$B$5*Z31)) -> 0.77966667 | AB31: =IF(AA31="","",IF(AA31>=Critérios!$B$7,"A",IF(AA31>=Critérios!$B$8,"B","C"))) -> A | AC31: =IF(AA31="","",RANK(AA31,$AA$2:$AA$85)) -> 30 | AD31: =IF(AA31="","Sairia — sem métrica",IF(PERCENTRANK($AA$2:$AA$85,AA31)<Critérios!$B$6,"Sairia — terço inferior","Fica")) -> Fica | AE31: claro | AG31: conferir ano e título no Brasil | AH31: candidato | AK31: tt9288030 | AL31: =COUNT(G31)+IF(OR(I31<>"",K31<>""),1,0)+IF(M31<>"",1,0)+COUNTA(V31:Y31) -> 5 | AM31: =IF(AL31>=3,"Sim","Não") -> Sim | AN31: =IF(AND(AC31<>"",AC31<=Critérios!$B$9),"Sim","Não") -> Sim
A32: S0031 | B32: Peaky Blinders: Sangue, Apostas e Navalhas | C32: Peaky Blinders | D32: 2013 | E32: BBC Two / BBC One | F32: Audiência oficial (coleta) | G32: 796047 | H32: 8.7 | K32: 5870000 | P32: =IF(G32="","",PERCENTRANK($G$2:$G$85,G32)) -> 0.867 | Q32: =IF(J32="","",1-(J32-1)/20) | R32: =IF(M32="","",1-(M32-1)/(2*N32)) | S32: =IF(K32="","",0.5+0.5*PERCENTRANK($K$2:$K$85,K32)) -> 0.6565 | T32: =IF(COUNT(Q32:S32)=0,"",MAX(Q32:S32)) -> 0.6565 | U32: =COUNT(P32,T32) -> 2 | Z32: =COUNTA(V32:Y32) -> 0 | AA32: =IF(U32=0,"",MIN(1,AVERAGE(P32,T32)+Critérios!$B$5*Z32)) -> 0.76175 | AB32: =IF(AA32="","",IF(AA32>=Critérios!$B$7,"A",IF(AA32>=Critérios!$B$8,"B","C"))) -> A | AC32: =IF(AA32="","",RANK(AA32,$AA$2:$AA$85)) -> 31 | AD32: =IF(AA32="","Sairia — sem métrica",IF(PERCENTRANK($AA$2:$AA$85,AA32)<Critérios!$B$6,"Sairia — terço inferior","Fica")) -> Fica | AE32: claro | AF32: Classificação alta — pistas suaves | AG32: Resgatada manualmente (lista aprovada em 13/10/2026) | AH32: candidato | AJ32: S017 | AK32: tt2442560 | AL32: =COUNT(G32)+IF(OR(I32<>"",K32<>""),1,0)+IF(M32<>"",1,0)+COUNTA(V32:Y32) -> 2 | AM32: =IF(AL32>=3,"Sim","Não") -> Não | AN32: =IF(AND(AC32<>"",AC32<=Critérios!$B$9),"Sim","Não") -> Sim
A33: S0032 | B33: Prison Break | C33: Prison Break | D33: 2005 | E33: FOX | F33: Curadoria | G33: 682499 | H33: 8.3 | P33: =IF(G33="","",PERCENTRANK($G$2:$G$85,G33)) -> 0.759 | Q33: =IF(J33="","",1-(J33-1)/20) | R33: =IF(M33="","",1-(M33-1)/(2*N33)) | S33: =IF(K33="","",0.5+0.5*PERCENTRANK($K$2:$K$85,K33)) | T33: =IF(COUNT(Q33:S33)=0,"",MAX(Q33:S33)) | U33: =COUNT(P33,T33) -> 1 | Z33: =COUNTA(V33:Y33) -> 0 | AA33: =IF(U33=0,"",MIN(1,AVERAGE(P33,T33)+Critérios!$B$5*Z33)) -> 0.759 | AB33: =IF(AA33="","",IF(AA33>=Critérios!$B$7,"A",IF(AA33>=Critérios!$B$8,"B","C"))) -> A | AC33: =IF(AA33="","",RANK(AA33,$AA$2:$AA$85)) -> 32 | AD33: =IF(AA33="","Sairia — sem métrica",IF(PERCENTRANK($AA$2:$AA$85,AA33)<Critérios!$B$6,"Sairia — terço inferior","Fica")) -> Fica | AE33: a avaliar | AG33: Resgatada manualmente (lista aprovada em 13/10/2026); conferir ano e título no Brasil | AH33: candidato | AK33: tt0455275 | AL33: =COUNT(G33)+IF(OR(I33<>"",K33<>""),1,0)+IF(M33<>"",1,0)+COUNTA(V33:Y33) -> 1 | AM33: =IF(AL33>=3,"Sim","Não") -> Não | AN33: =IF(AND(AC33<>"",AC33<=Critérios!$B$9),"Sim","Não") -> Sim
A34: S0033 | B34: How I Met Your Mother | C34: How I Met Your Mother | D34: 2005 | E34: CBS | F34: Curadoria | G34: 791279 | H34: 8.3 | M34: 28 | N34: 40 | O34: 2013-14 #28 | P34: =IF(G34="","",PERCENTRANK($G$2:$G$85,G34)) -> 0.855 | Q34: =IF(J34="","",1-(J34-1)/20) | R34: =IF(M34="","",1-(M34-1)/(2*N34)) -> 0.6625 | S34: =IF(K34="","",0.5+0.5*PERCENTRANK($K$2:$K$85,K34)) | T34: =IF(COUNT(Q34:S34)=0,"",MAX(Q34:S34)) -> 0.6625 | U34: =COUNT(P34,T34) -> 2 | Z34: =COUNTA(V34:Y34) -> 0 | AA34: =IF(U34=0,"",MIN(1,AVERAGE(P34,T34)+Critérios!$B$5*Z34)) -> 0.75875 | AB34: =IF(AA34="","",IF(AA34>=Critérios!$B$7,"A",IF(AA34>=Critérios!$B$8,"B","C"))) -> A | AC34: =IF(AA34="","",RANK(AA34,$AA$2:$AA$85)) -> 33 | AD34: =IF(AA34="","Sairia — sem métrica",IF(PERCENTRANK($AA$2:$AA$85,AA34)<Critérios!$B$6,"Sairia — terço inferior","Fica")) -> Fica | AE34: claro | AG34: Resgatada manualmente (lista aprovada em 13/10/2026); conferir ano e título no Brasil | AH34: candidato | AK34: tt0460649 | AL34: =COUNT(G34)+IF(OR(I34<>"",K34<>""),1,0)+IF(M34<>"",1,0)+COUNTA(V34:Y34) -> 2 | AM34: =IF(AL34>=3,"Sim","Não") -> Não | AN34: =IF(AND(AC34<>"",AC34<=Critérios!$B$9),"Sim","Não") -> Sim
A35: S0034 | B35: WandaVision | C35: WandaVision | D35: 2021 | E35: Disney+ | F35: Curadoria | G35: 426953 | H35: 7.9 | M35: 14 | N35: 30 | O35: 2021 #14 | P35: =IF(G35="","",PERCENTRANK($G$2:$G$85,G35)) -> 0.59 | Q35: =IF(J35="","",1-(J35-1)/20) | R35: =IF(M35="","",1-(M35-1)/(2*N35)) -> 0.78333333 | S35: =IF(K35="","",0.5+0.5*PERCENTRANK($K$2:$K$85,K35)) | T35: =IF(COUNT(Q35:S35)=0,"",MAX(Q35:S35)) -> 0.78333333 | U35: =COUNT(P35,T35) -> 2 | W35: 2021 (ano) #1; fev 2021 #1; ago 2021; fev 2022 | X35: 19–21 mar 2021 #4 (Germany); 19–21 mar 2021 #5 (Italy); 19–21 mar 2021 #4 (Spain) | Z35: =COUNTA(V35:Y35) -> 2 | AA35: =IF(U35=0,"",MIN(1,AVERAGE(P35,T35)+Critérios!$B$5*Z35)) -> 0.74666667 | AB35: =IF(AA35="","",IF(AA35>=Critérios!$B$7,"A",IF(AA35>=Critérios!$B$8,"B","C"))) -> A | AC35: =IF(AA35="","",RANK(AA35,$AA$2:$AA$85)) -> 34 | AD35: =IF(AA35="","Sairia — sem métrica",IF(PERCENTRANK($AA$2:$AA$85,AA35)<Critérios!$B$6,"Sairia — terço inferior","Fica")) -> Fica | AE35: dupla | AG35: conferir ano e título no Brasil | AH35: candidato | AK35: tt9140560 | AL35: =COUNT(G35)+IF(OR(I35<>"",K35<>""),1,0)+IF(M35<>"",1,0)+COUNTA(V35:Y35) -> 4 | AM35: =IF(AL35>=3,"Sim","Não") -> Sim | AN35: =IF(AND(AC35<>"",AC35<=Critérios!$B$9),"Sim","Não") -> Sim
A36: S0035 | B36: Você | C36: You | D36: 2018 | E36: Lifetime / Netflix | F36: Curadoria | G36: 377230 | H36: 7.6 | M36: 6 | N36: 30 | O36: 2020 #20; 2021 #6 | P36: =IF(G36="","",PERCENTRANK($G$2:$G$85,G36)) -> 0.506 | Q36: =IF(J36="","",1-(J36-1)/20) | R36: =IF(M36="","",1-(M36-1)/(2*N36)) -> 0.91666667 | S36: =IF(K36="","",0.5+0.5*PERCENTRANK($K$2:$K$85,K36)) | T36: =IF(COUNT(Q36:S36)=0,"",MAX(Q36:S36)) -> 0.91666667 | U36: =COUNT(P36,T36) -> 2 | X36: semana 18–24 out 2021 #1 (France); semana 25–31 out 2021 #2 (Italy); semana 1–7 nov 2021 #1 (Spain); semana 8–14 nov 2021 #2 (Germany); semana 15–21 nov 2021 #3 (France); semana 22–28 nov 2021 #5 (Italy); semana 29 nov–5 dez 2021 #6 (Spain); 2020 (ano) #4 (United States); 1 jan–30 nov 2023 #4 (United States) | Z36: =COUNTA(V36:Y36) -> 1 | AA36: =IF(U36=0,"",MIN(1,AVERAGE(P36,T36)+Critérios!$B$5*Z36)) -> 0.74133333 | AB36: =IF(AA36="","",IF(AA36>=Critérios!$B$7,"A",IF(AA36>=Critérios!$B$8,"B","C"))) -> A | AC36: =IF(AA36="","",RANK(AA36,$AA$2:$AA$85)) -> 35 | AD36: =IF(AA36="","Sairia — sem métrica",IF(PERCENTRANK($AA$2:$AA$85,AA36)<Critérios!$B$6,"Sairia — terço inferior","Fica")) -> Fica | AE36: claro | AF36: Classificação alta — pistas suaves | AG36: conferir ano e título no Brasil | AH36: candidato | AK36: tt7335184 | AL36: =COUNT(G36)+IF(OR(I36<>"",K36<>""),1,0)+IF(M36<>"",1,0)+COUNTA(V36:Y36) -> 3 | AM36: =IF(AL36>=3,"Sim","Não") -> Sim | AN36: =IF(AND(AC36<>"",AC36<=Critérios!$B$9),"Sim","Não") -> Sim
A37: S0036 | B37: Vikings | C37: Vikings | D37: 2013 | E37: History | F37: Curadoria | G37: 651727 | H37: 8.5 | P37: =IF(G37="","",PERCENTRANK($G$2:$G$85,G37)) -> 0.723 | Q37: =IF(J37="","",1-(J37-1)/20) | R37: =IF(M37="","",1-(M37-1)/(2*N37)) | S37: =IF(K37="","",0.5+0.5*PERCENTRANK($K$2:$K$85,K37)) | T37: =IF(COUNT(Q37:S37)=0,"",MAX(Q37:S37)) | U37: =COUNT(P37,T37) -> 1 | Z37: =COUNTA(V37:Y37) -> 0 | AA37: =IF(U37=0,"",MIN(1,AVERAGE(P37,T37)+Critérios!$B$5*Z37)) -> 0.723 | AB37: =IF(AA37="","",IF(AA37>=Critérios!$B$7,"A",IF(AA37>=Critérios!$B$8,"B","C"))) -> A | AC37: =IF(AA37="","",RANK(AA37,$AA$2:$AA$85)) -> 36 | AD37: =IF(AA37="","Sairia — sem métrica",IF(PERCENTRANK($AA$2:$AA$85,AA37)<Critérios!$B$6,"Sairia — terço inferior","Fica")) -> Fica | AE37: claro | AG37: Resgatada manualmente (lista aprovada em 13/10/2026); conferir ano e título no Brasil | AH37: candidato | AK37: tt2306299 | AL37: =COUNT(G37)+IF(OR(I37<>"",K37<>""),1,0)+IF(M37<>"",1,0)+COUNTA(V37:Y37) -> 1 | AM37: =IF(AL37>=3,"Sim","Não") -> Não | AN37: =IF(AND(AC37<>"",AC37<=Critérios!$B$9),"Sim","Não") -> Sim
A38: S0037 | B38: Cobra Kai | C38: Cobra Kai | D38: 2018 | E38: YouTube Red / Netflix | F38: Curadoria | G38: 247445 | H38: 8.4 | M38: 4 | N38: 30 | O38: 2021 #7; 2022 #14; 2022 #4 | P38: =IF(G38="","",PERCENTRANK($G$2:$G$85,G38)) -> 0.361 | Q38: =IF(J38="","",1-(J38-1)/20) | R38: =IF(M38="","",1-(M38-1)/(2*N38)) -> 0.95 | S38: =IF(K38="","",0.5+0.5*PERCENTRANK($K$2:$K$85,K38)) | T38: =IF(COUNT(Q38:S38)=0,"",MAX(Q38:S38)) -> 0.95 | U38: =COUNT(P38,T38) -> 2 | V38: YPulse Media Consumption Monitor 2022-10 (Gen Z (faixa não explicitada; amostra 13-39)) #2 | X38: semana 3–9 jan 2022 #1 (United States) | Z38: =COUNTA(V38:Y38) -> 2 | AA38: =IF(U38=0,"",MIN(1,AVERAGE(P38,T38)+Critérios!$B$5*Z38)) -> 0.7155 | AB38: =IF(AA38="","",IF(AA38>=Critérios!$B$7,"A",IF(AA38>=Critérios!$B$8,"B","C"))) -> A | AC38: =IF(AA38="","",RANK(AA38,$AA$2:$AA$85)) -> 37 | AD38: =IF(AA38="","Sairia — sem métrica",IF(PERCENTRANK($AA$2:$AA$85,AA38)<Critérios!$B$6,"Sairia — terço inferior","Fica")) -> Fica | AE38: dupla | AG38: conferir ano e título no Brasil | AH38: candidato | AK38: tt7221388 | AL38: =COUNT(G38)+IF(OR(I38<>"",K38<>""),1,0)+IF(M38<>"",1,0)+COUNTA(V38:Y38) -> 4 | AM38: =IF(AL38>=3,"Sim","Não") -> Sim | AN38: =IF(AND(AC38<>"",AC38<=Critérios!$B$9),"Sim","Não") -> Sim
A39: S0038 | B39: A Casa do Dragão | C39: House of the Dragon | D39: 2022 | E39: HBO | F39: Audiência oficial (coleta) | G39: 574470 | H39: 8.2 | P39: =IF(G39="","",PERCENTRANK($G$2:$G$85,G39)) -> 0.675 | Q39: =IF(J39="","",1-(J39-1)/20) | R39: =IF(M39="","",1-(M39-1)/(2*N39)) | S39: =IF(K39="","",0.5+0.5*PERCENTRANK($K$2:$K$85,K39)) | T39: =IF(COUNT(Q39:S39)=0,"",MAX(Q39:S39)) | U39: =COUNT(P39,T39) -> 1 | Y39: #27 hoje | Z39: =COUNTA(V39:Y39) -> 1 | AA39: =IF(U39=0,"",MIN(1,AVERAGE(P39,T39)+Critérios!$B$5*Z39)) -> 0.705 | AB39: =IF(AA39="","",IF(AA39>=Critérios!$B$7,"A",IF(AA39>=Critérios!$B$8,"B","C"))) -> A | AC39: =IF(AA39="","",RANK(AA39,$AA$2:$AA$85)) -> 38 | AD39: =IF(AA39="","Sairia — sem métrica",IF(PERCENTRANK($AA$2:$AA$85,AA39)<Critérios!$B$6,"Sairia — terço inferior","Fica")) -> Fica | AE39: a avaliar | AF39: Classificação alta — pistas suaves | AG39: Resgatada manualmente (lista aprovada em 13/10/2026) | AH39: candidato | AJ39: S009 | AK39: tt11198330 | AL39: =COUNT(G39)+IF(OR(I39<>"",K39<>""),1,0)+IF(M39<>"",1,0)+COUNTA(V39:Y39) -> 2 | AM39: =IF(AL39>=3,"Sim","Não") -> Não | AN39: =IF(AND(AC39<>"",AC39<=Critérios!$B$9),"Sim","Não") -> Sim
A40: S0039 | B40: Criminal Minds | C40: Criminal Minds | D40: 2005 | E40: CBS | F40: Curadoria | G40: 243934 | H40: 8.1 | M40: 1 | N40: 30 | O40: 2005-06 #27; 2006-07 #18; 2007-08 #18; 2008-09 #11; 2009-10 #14; 2010-11 #10; 2011-12 #13; 2012-13 #17; 2013-14 #13; 2014-15 #8; 2015-16 #13; 2016-17 #17; 2017-18 #25; 2020 #3; 2021 #1; 2022 #7; 2022 #4; 2024 #9; 2025 #10 | P40: =IF(G40="","",PERCENTRANK($G$2:$G$85,G40)) -> 0.349 | Q40: =IF(J40="","",1-(J40-1)/20) | R40: =IF(M40="","",1-(M40-1)/(2*N40)) -> 1 | S40: =IF(K40="","",0.5+0.5*PERCENTRANK($K$2:$K$85,K40)) | T40: =IF(COUNT(Q40:S40)=0,"",MAX(Q40:S40)) -> 1 | U40: =COUNT(P40,T40) -> 2 | Y40: #67 hoje | Z40: =COUNTA(V40:Y40) -> 1 | AA40: =IF(U40=0,"",MIN(1,AVERAGE(P40,T40)+Critérios!$B$5*Z40)) -> 0.7045 | AB40: =IF(AA40="","",IF(AA40>=Critérios!$B$7,"A",IF(AA40>=Critérios!$B$8,"B","C"))) -> A | AC40: =IF(AA40="","",RANK(AA40,$AA$2:$AA$85)) -> 39 | AD40: =IF(AA40="","Sairia — sem métrica",IF(PERCENTRANK($AA$2:$AA$85,AA40)<Critérios!$B$6,"Sairia — terço inferior","Fica")) -> Fica | AE40: coral/antologia | AG40: conferir ano e título no Brasil | AH40: candidato | AK40: tt0452046 | AL40: =COUNT(G40)+IF(OR(I40<>"",K40<>""),1,0)+IF(M40<>"",1,0)+COUNTA(V40:Y40) -> 3 | AM40: =IF(AL40>=3,"Sim","Não") -> Sim | AN40: =IF(AND(AC40<>"",AC40<=Critérios!$B$9),"Sim","Não") -> Sim
A41: S0040 | B41: Bridgerton | C41: Bridgerton | D41: 2020 | E41: Netflix | F41: Audiência oficial (coleta) | G41: 234013 | H41: 7.5 | I41: 113300000 | J41: 8 | M41: 1 | N41: 30 | O41: 2021 #5; 2022 #5; 2024 #1 | P41: =IF(G41="","",PERCENTRANK($G$2:$G$85,G41)) -> 0.337 | Q41: =IF(J41="","",1-(J41-1)/20) -> 0.65 | R41: =IF(M41="","",1-(M41-1)/(2*N41)) -> 1 | S41: =IF(K41="","",0.5+0.5*PERCENTRANK($K$2:$K$85,K41)) | T41: =IF(COUNT(Q41:S41)=0,"",MAX(Q41:S41)) -> 1 | U41: =COUNT(P41,T41) -> 2 | W41: 2021 (ano); ago 2021 | Z41: =COUNTA(V41:Y41) -> 1 | AA41: =IF(U41=0,"",MIN(1,AVERAGE(P41,T41)+Critérios!$B$5*Z41)) -> 0.6985 | AB41: =IF(AA41="","",IF(AA41>=Critérios!$B$7,"A",IF(AA41>=Critérios!$B$8,"B","C"))) -> B | AC41: =IF(AA41="","",RANK(AA41,$AA$2:$AA$85)) -> 40 | AD41: =IF(AA41="","Sairia — sem métrica",IF(PERCENTRANK($AA$2:$AA$85,AA41)<Critérios!$B$6,"Sairia — terço inferior","Fica")) -> Fica | AE41: coral/antologia | AH41: candidato | AJ41: S030 | AK41: tt8740790 | AL41: =COUNT(G41)+IF(OR(I41<>"",K41<>""),1,0)+IF(M41<>"",1,0)+COUNTA(V41:Y41) -> 4 | AM41: =IF(AL41>=3,"Sim","Não") -> Sim | AN41: =IF(AND(AC41<>"",AC41<=Critérios!$B$9),"Sim","Não") -> Sim
A42: S0041 | B42: O Mentalista | C42: The Mentalist | D42: 2008 | F42: Adicionado por: Nielsen | G42: 256303 | H42: 8.2 | M42: 6 | N42: 40 | O42: 2008-09 #6; 2009-10 #6; 2010-11 #8; 2011-12 #9; 2012-13 #18; 2013-14 #23; 2014-15 #25 | P42: =IF(G42="","",PERCENTRANK($G$2:$G$85,G42)) -> 0.398 | Q42: =IF(J42="","",1-(J42-1)/20) | R42: =IF(M42="","",1-(M42-1)/(2*N42)) -> 0.9375 | S42: =IF(K42="","",0.5+0.5*PERCENTRANK($K$2:$K$85,K42)) | T42: =IF(COUNT(Q42:S42)=0,"",MAX(Q42:S42)) -> 0.9375 | U42: =COUNT(P42,T42) -> 2 | Y42: #18 hoje | Z42: =COUNTA(V42:Y42) -> 1 | AA42: =IF(U42=0,"",MIN(1,AVERAGE(P42,T42)+Critérios!$B$5*Z42)) -> 0.69775 | AB42: =IF(AA42="","",IF(AA42>=Critérios!$B$7,"A",IF(AA42>=Critérios!$B$8,"B","C"))) -> B | AC42: =IF(AA42="","",RANK(AA42,$AA$2:$AA$85)) -> 41 | AD42: =IF(AA42="","Sairia — sem métrica",IF(PERCENTRANK($AA$2:$AA$85,AA42)<Critérios!$B$6,"Sairia — terço inferior","Fica")) -> Fica | AE42: a avaliar | AH42: candidato | AK42: tt1196946 | AL42: =COUNT(G42)+IF(OR(I42<>"",K42<>""),1,0)+IF(M42<>"",1,0)+COUNTA(V42:Y42) -> 3 | AM42: =IF(AL42>=3,"Sim","Não") -> Sim | AN42: =IF(AND(AC42<>"",AC42<=Critérios!$B$9),"Sim","Não") -> Sim
A43: S0042 | B43: O Conto da Aia | C43: The Handmaid's Tale | D43: 2017 | F43: Adicionado por: Nielsen | G43: 305999 | H43: 8.3 | M43: 10 | N43: 30 | O43: 2021 #10 | P43: =IF(G43="","",PERCENTRANK($G$2:$G$85,G43)) -> 0.422 | Q43: =IF(J43="","",1-(J43-1)/20) | R43: =IF(M43="","",1-(M43-1)/(2*N43)) -> 0.85 | S43: =IF(K43="","",0.5+0.5*PERCENTRANK($K$2:$K$85,K43)) | T43: =IF(COUNT(Q43:S43)=0,"",MAX(Q43:S43)) -> 0.85 | U43: =COUNT(P43,T43) -> 2 | X43: 2020 (ano) #2 (United States) | Y43: #28 hoje | Z43: =COUNTA(V43:Y43) -> 2 | AA43: =IF(U43=0,"",MIN(1,AVERAGE(P43,T43)+Critérios!$B$5*Z43)) -> 0.696 | AB43: =IF(AA43="","",IF(AA43>=Critérios!$B$7,"A",IF(AA43>=Critérios!$B$8,"B","C"))) -> B | AC43: =IF(AA43="","",RANK(AA43,$AA$2:$AA$85)) -> 42 | AD43: =IF(AA43="","Sairia — sem métrica",IF(PERCENTRANK($AA$2:$AA$85,AA43)<Critérios!$B$6,"Sairia — terço inferior","Fica")) -> Fica | AE43: a avaliar | AH43: candidato | AK43: tt5834204 | AL43: =COUNT(G43)+IF(OR(I43<>"",K43<>""),1,0)+IF(M43<>"",1,0)+COUNTA(V43:Y43) -> 4 | AM43: =IF(AL43>=3,"Sim","Não") -> Sim | AN43: =IF(AND(AC43<>"",AC43<=Critérios!$B$9),"Sim","Não") -> Sim
A44: S0043 | B44: Dark | C44: Dark | D44: 2017 | E44: Netflix (Alemanha) | F44: Curadoria | G44: 565004 | H44: 8.7 | P44: =IF(G44="","",PERCENTRANK($G$2:$G$85,G44)) -> 0.663 | Q44: =IF(J44="","",1-(J44-1)/20) | R44: =IF(M44="","",1-(M44-1)/(2*N44)) | S44: =IF(K44="","",0.5+0.5*PERCENTRANK($K$2:$K$85,K44)) | T44: =IF(COUNT(Q44:S44)=0,"",MAX(Q44:S44)) | U44: =COUNT(P44,T44) -> 1 | W44: ago 2020 #3 | Z44: =COUNTA(V44:Y44) -> 1 | AA44: =IF(U44=0,"",MIN(1,AVERAGE(P44,T44)+Critérios!$B$5*Z44)) -> 0.693 | AB44: =IF(AA44="","",IF(AA44>=Critérios!$B$7,"A",IF(AA44>=Critérios!$B$8,"B","C"))) -> B | AC44: =IF(AA44="","",RANK(AA44,$AA$2:$AA$85)) -> 43 | AD44: =IF(AA44="","Sairia — sem métrica",IF(PERCENTRANK($AA$2:$AA$85,AA44)<Critérios!$B$6,"Sairia — terço inferior","Fica")) -> Fica | AE44: claro | AG44: Resgatada manualmente (lista aprovada em 13/10/2026); conferir ano e título no Brasil | AH44: candidato | AK44: tt5753856 | AL44: =COUNT(G44)+IF(OR(I44<>"",K44<>""),1,0)+IF(M44<>"",1,0)+COUNTA(V44:Y44) -> 2 | AM44: =IF(AL44>=3,"Sim","Não") -> Não | AN44: =IF(AND(AC44<>"",AC44<=Critérios!$B$9),"Sim","Não") -> Sim
A45: S0044 | B45: Euphoria | C45: Euphoria | D45: 2019 | E45: HBO | F45: Audiência oficial (coleta) | G45: 326495 | H45: 8.1 | K45: 16300000 | P45: =IF(G45="","",PERCENTRANK($G$2:$G$85,G45)) -> 0.458 | Q45: =IF(J45="","",1-(J45-1)/20) | R45: =IF(M45="","",1-(M45-1)/(2*N45)) | S45: =IF(K45="","",0.5+0.5*PERCENTRANK($K$2:$K$85,K45)) -> 0.844 | T45: =IF(COUNT(Q45:S45)=0,"",MAX(Q45:S45)) -> 0.844 | U45: =COUNT(P45,T45) -> 2 | V45: YPulse Media Consumption Monitor 2022-10 (Gen Z (faixa não explicitada; amostra 13-39)) #6 | Z45: =COUNTA(V45:Y45) -> 1 | AA45: =IF(U45=0,"",MIN(1,AVERAGE(P45,T45)+Critérios!$B$5*Z45)) -> 0.681 | AB45: =IF(AA45="","",IF(AA45>=Critérios!$B$7,"A",IF(AA45>=Critérios!$B$8,"B","C"))) -> B | AC45: =IF(AA45="","",RANK(AA45,$AA$2:$AA$85)) -> 44 | AD45: =IF(AA45="","Sairia — sem métrica",IF(PERCENTRANK($AA$2:$AA$85,AA45)<Critérios!$B$6,"Sairia — terço inferior","Fica")) -> Fica | AE45: claro | AF45: Classificação alta — pistas suaves | AH45: candidato | AJ45: S003 | AK45: tt8772296 | AL45: =COUNT(G45)+IF(OR(I45<>"",K45<>""),1,0)+IF(M45<>"",1,0)+COUNTA(V45:Y45) -> 3 | AM45: =IF(AL45>=3,"Sim","Não") -> Sim | AN45: =IF(AND(AC45<>"",AC45<=Critérios!$B$9),"Sim","Não") -> Sim
A46: S0045 | B46: The Umbrella Academy | C46: The Umbrella Academy | D46: 2019 | E46: Netflix | F46: Curadoria | G46: 318857 | H46: 7.8 | M46: 13 | N46: 30 | O46: 2020 #16; 2022 #13 | P46: =IF(G46="","",PERCENTRANK($G$2:$G$85,G46)) -> 0.434 | Q46: =IF(J46="","",1-(J46-1)/20) | R46: =IF(M46="","",1-(M46-1)/(2*N46)) -> 0.8 | S46: =IF(K46="","",0.5+0.5*PERCENTRANK($K$2:$K$85,K46)) | T46: =IF(COUNT(Q46:S46)=0,"",MAX(Q46:S46)) -> 0.8 | U46: =COUNT(P46,T46) -> 2 | W46: ago 2020 #1; fev 2021 | X46: semana encerrada 17 jul 2022 #5 (United States); semana encerrada 24 jul 2022 #5 (United States); 2020 (ano) #2 (United States) | Z46: =COUNTA(V46:Y46) -> 2 | AA46: =IF(U46=0,"",MIN(1,AVERAGE(P46,T46)+Critérios!$B$5*Z46)) -> 0.677 | AB46: =IF(AA46="","",IF(AA46>=Critérios!$B$7,"A",IF(AA46>=Critérios!$B$8,"B","C"))) -> B | AC46: =IF(AA46="","",RANK(AA46,$AA$2:$AA$85)) -> 45 | AD46: =IF(AA46="","Sairia — sem métrica",IF(PERCENTRANK($AA$2:$AA$85,AA46)<Critérios!$B$6,"Sairia — terço inferior","Fica")) -> Fica | AE46: coral/antologia | AG46: conferir ano e título no Brasil | AH46: candidato | AK46: tt1312171 | AL46: =COUNT(G46)+IF(OR(I46<>"",K46<>""),1,0)+IF(M46<>"",1,0)+COUNTA(V46:Y46) -> 4 | AM46: =IF(AL46>=3,"Sim","Não") -> Sim | AN46: =IF(AND(AC46<>"",AC46<=Critérios!$B$9),"Sim","Não") -> Sim
A47: S0046 | B47: Loki | C47: Loki | D47: 2021 | E47: Disney+ | F47: Curadoria | G47: 491219 | H47: 8.2 | P47: =IF(G47="","",PERCENTRANK($G$2:$G$85,G47)) -> 0.614 | Q47: =IF(J47="","",1-(J47-1)/20) | R47: =IF(M47="","",1-(M47-1)/(2*N47)) | S47: =IF(K47="","",0.5+0.5*PERCENTRANK($K$2:$K$85,K47)) | T47: =IF(COUNT(Q47:S47)=0,"",MAX(Q47:S47)) | U47: =COUNT(P47,T47) -> 1 | W47: ago 2021 #1 | X47: 1 jan–30 nov 2023 #2 (United States) | Z47: =COUNTA(V47:Y47) -> 2 | AA47: =IF(U47=0,"",MIN(1,AVERAGE(P47,T47)+Critérios!$B$5*Z47)) -> 0.674 | AB47: =IF(AA47="","",IF(AA47>=Critérios!$B$7,"A",IF(AA47>=Critérios!$B$8,"B","C"))) -> B | AC47: =IF(AA47="","",RANK(AA47,$AA$2:$AA$85)) -> 46 | AD47: =IF(AA47="","Sairia — sem métrica",IF(PERCENTRANK($AA$2:$AA$85,AA47)<Critérios!$B$6,"Sairia — terço inferior","Fica")) -> Fica | AE47: claro | AG47: conferir ano e título no Brasil | AH47: candidato | AK47: tt9140554 | AL47: =COUNT(G47)+IF(OR(I47<>"",K47<>""),1,0)+IF(M47<>"",1,0)+COUNTA(V47:Y47) -> 3 | AM47: =IF(AL47>=3,"Sim","Não") -> Sim | AN47: =IF(AND(AC47<>"",AC47<=Critérios!$B$9),"Sim","Não") -> Sim
A48: S0047 | B48: O Gambito da Rainha | C48: The Queen's Gambit | D48: 2020 | E48: Netflix | F48: Audiência oficial (coleta) | G48: 681356 | H48: 8.5 | I48: 112800000 | J48: 9 | P48: =IF(G48="","",PERCENTRANK($G$2:$G$85,G48)) -> 0.747 | Q48: =IF(J48="","",1-(J48-1)/20) -> 0.6 | R48: =IF(M48="","",1-(M48-1)/(2*N48)) | S48: =IF(K48="","",0.5+0.5*PERCENTRANK($K$2:$K$85,K48)) | T48: =IF(COUNT(Q48:S48)=0,"",MAX(Q48:S48)) -> 0.6 | U48: =COUNT(P48,T48) -> 2 | Z48: =COUNTA(V48:Y48) -> 0 | AA48: =IF(U48=0,"",MIN(1,AVERAGE(P48,T48)+Critérios!$B$5*Z48)) -> 0.6735 | AB48: =IF(AA48="","",IF(AA48>=Critérios!$B$7,"A",IF(AA48>=Critérios!$B$8,"B","C"))) -> B | AC48: =IF(AA48="","",RANK(AA48,$AA$2:$AA$85)) -> 47 | AD48: =IF(AA48="","Sairia — sem métrica",IF(PERCENTRANK($AA$2:$AA$85,AA48)<Critérios!$B$6,"Sairia — terço inferior","Fica")) -> Fica | AE48: claro | AG48: Resgatada manualmente (lista aprovada em 13/10/2026) | AH48: candidato | AJ48: S030 | AK48: tt10048342 | AL48: =COUNT(G48)+IF(OR(I48<>"",K48<>""),1,0)+IF(M48<>"",1,0)+COUNTA(V48:Y48) -> 2 | AM48: =IF(AL48>=3,"Sim","Não") -> Não | AN48: =IF(AND(AC48<>"",AC48<=Critérios!$B$9),"Sim","Não") -> Sim
A49: S0048 | B49: Pessoa de Interesse | C49: Person of Interest | D49: 2011 | F49: Adicionado por: Nielsen | G49: 217379 | H49: 8.5 | M49: 5 | N49: 40 | O49: 2011-12 #12; 2012-13 #5; 2013-14 #7; 2014-15 #20 | P49: =IF(G49="","",PERCENTRANK($G$2:$G$85,G49)) -> 0.313 | Q49: =IF(J49="","",1-(J49-1)/20) | R49: =IF(M49="","",1-(M49-1)/(2*N49)) -> 0.95 | S49: =IF(K49="","",0.5+0.5*PERCENTRANK($K$2:$K$85,K49)) | T49: =IF(COUNT(Q49:S49)=0,"",MAX(Q49:S49)) -> 0.95 | U49: =COUNT(P49,T49) -> 2 | Y49: #80 hoje | Z49: =COUNTA(V49:Y49) -> 1 | AA49: =IF(U49=0,"",MIN(1,AVERAGE(P49,T49)+Critérios!$B$5*Z49)) -> 0.6615 | AB49: =IF(AA49="","",IF(AA49>=Critérios!$B$7,"A",IF(AA49>=Critérios!$B$8,"B","C"))) -> B | AC49: =IF(AA49="","",RANK(AA49,$AA$2:$AA$85)) -> 48 | AD49: =IF(AA49="","Sairia — sem métrica",IF(PERCENTRANK($AA$2:$AA$85,AA49)<Critérios!$B$6,"Sairia — terço inferior","Fica")) -> Fica | AE49: a avaliar | AH49: candidato | AK49: tt1839578 | AL49: =COUNT(G49)+IF(OR(I49<>"",K49<>""),1,0)+IF(M49<>"",1,0)+COUNTA(V49:Y49) -> 3 | AM49: =IF(AL49>=3,"Sim","Não") -> Sim | AN49: =IF(AND(AC49<>"",AC49<=Critérios!$B$9),"Sim","Não") -> Sim
A50: S0049 | B50: The Vampire Diaries | C50: The Vampire Diaries | D50: 2009 | E50: The CW | F50: Audiência oficial (coleta) | G50: 390307 | H50: 7.7 | K50: 3660000 | M50: 15 | N50: 30 | O50: 2020 #15 | P50: =IF(G50="","",PERCENTRANK($G$2:$G$85,G50)) -> 0.542 | Q50: =IF(J50="","",1-(J50-1)/20) | R50: =IF(M50="","",1-(M50-1)/(2*N50)) -> 0.76666667 | S50: =IF(K50="","",0.5+0.5*PERCENTRANK($K$2:$K$85,K50)) -> 0.594 | T50: =IF(COUNT(Q50:S50)=0,"",MAX(Q50:S50)) -> 0.76666667 | U50: =COUNT(P50,T50) -> 2 | Z50: =COUNTA(V50:Y50) -> 0 | AA50: =IF(U50=0,"",MIN(1,AVERAGE(P50,T50)+Critérios!$B$5*Z50)) -> 0.65433333 | AB50: =IF(AA50="","",IF(AA50>=Critérios!$B$7,"A",IF(AA50>=Critérios!$B$8,"B","C"))) -> B | AC50: =IF(AA50="","",RANK(AA50,$AA$2:$AA$85)) -> 49 | AD50: =IF(AA50="","Sairia — sem métrica",IF(PERCENTRANK($AA$2:$AA$85,AA50)<Critérios!$B$6,"Sairia — terço inferior","Fica")) -> Fica | AE50: claro | AH50: candidato | AJ50: S023 | AK50: tt1405406 | AL50: =COUNT(G50)+IF(OR(I50<>"",K50<>""),1,0)+IF(M50<>"",1,0)+COUNTA(V50:Y50) -> 3 | AM50: =IF(AL50>=3,"Sim","Não") -> Sim | AN50: =IF(AND(AC50<>"",AC50<=Critérios!$B$9),"Sim","Não") -> Sim
A51: S0050 | B51: Ginny & Georgia | C51: Ginny & Georgia | D51: 2021 | E51: Netflix | F51: Curadoria | G51: 111423 | H51: 7.5 | M51: 3 | N51: 30 | O51: 2023 #3; 2025 #6 | P51: =IF(G51="","",PERCENTRANK($G$2:$G$85,G51)) -> 0.181 | Q51: =IF(J51="","",1-(J51-1)/20) | R51: =IF(M51="","",1-(M51-1)/(2*N51)) -> 0.96666667 | S51: =IF(K51="","",0.5+0.5*PERCENTRANK($K$2:$K$85,K51)) | T51: =IF(COUNT(Q51:S51)=0,"",MAX(Q51:S51)) -> 0.96666667 | U51: =COUNT(P51,T51) -> 2 | V51: YPulse 2024-02 (13-17) #9 | X51: 19–21 mar 2021 #4 (France); 19–21 mar 2021 #4 (Italy) | Z51: =COUNTA(V51:Y51) -> 2 | AA51: =IF(U51=0,"",MIN(1,AVERAGE(P51,T51)+Critérios!$B$5*Z51)) -> 0.63383333 | AB51: =IF(AA51="","",IF(AA51>=Critérios!$B$7,"A",IF(AA51>=Critérios!$B$8,"B","C"))) -> B | AC51: =IF(AA51="","",RANK(AA51,$AA$2:$AA$85)) -> 50 | AD51: =IF(AA51="","Sairia — sem métrica",IF(PERCENTRANK($AA$2:$AA$85,AA51)<Critérios!$B$6,"Sairia — terço inferior","Fica")) -> Fica | AE51: dupla | AG51: conferir ano e título no Brasil | AH51: candidato | AK51: tt10813940 | AL51: =COUNT(G51)+IF(OR(I51<>"",K51<>""),1,0)+IF(M51<>"",1,0)+COUNTA(V51:Y51) -> 4 | AM51: =IF(AL51>=3,"Sim","Não") -> Sim | AN51: =IF(AND(AC51<>"",AC51<=Critérios!$B$9),"Sim","Não") -> Sim
A52: S0051 | B52: This Is Us | C52: This Is Us | D52: 2016 | E52: NBC | F52: Curadoria | G52: 177132 | H52: 8.7 | M52: 4 | N52: 40 | O52: 2016-17 #6; 2017-18 #4; 2018-19 #6; 2019-20 #8 | P52: =IF(G52="","",PERCENTRANK($G$2:$G$85,G52)) -> 0.241 | Q52: =IF(J52="","",1-(J52-1)/20) | R52: =IF(M52="","",1-(M52-1)/(2*N52)) -> 0.9625 | S52: =IF(K52="","",0.5+0.5*PERCENTRANK($K$2:$K$85,K52)) | T52: =IF(COUNT(Q52:S52)=0,"",MAX(Q52:S52)) -> 0.9625 | U52: =COUNT(P52,T52) -> 2 | V52: YPulse 2018-10 (13-17) #1; YPulse 2018-10 (18-24) #1 | Z52: =COUNTA(V52:Y52) -> 1 | AA52: =IF(U52=0,"",MIN(1,AVERAGE(P52,T52)+Critérios!$B$5*Z52)) -> 0.63175 | AB52: =IF(AA52="","",IF(AA52>=Critérios!$B$7,"A",IF(AA52>=Critérios!$B$8,"B","C"))) -> B | AC52: =IF(AA52="","",RANK(AA52,$AA$2:$AA$85)) -> 51 | AD52: =IF(AA52="","Sairia — sem métrica",IF(PERCENTRANK($AA$2:$AA$85,AA52)<Critérios!$B$6,"Sairia — terço inferior","Fica")) -> Fica | AE52: coral/antologia | AG52: conferir ano e título no Brasil | AH52: candidato | AK52: tt5555260 | AL52: =COUNT(G52)+IF(OR(I52<>"",K52<>""),1,0)+IF(M52<>"",1,0)+COUNTA(V52:Y52) -> 3 | AM52: =IF(AL52>=3,"Sim","Não") -> Sim | AN52: =IF(AND(AC52<>"",AC52<=Critérios!$B$9),"Sim","Não") -> Não
A53: S0052 | B53: Jovem Sheldon | C53: Young Sheldon | D53: 2017 | F53: Adicionado por: Nielsen | G53: 153642 | H53: 7.8 | M53: 4 | N53: 40 | O53: 2017-18 #6; 2018-19 #4; 2019-20 #9; 2024 #6 | P53: =IF(G53="","",PERCENTRANK($G$2:$G$85,G53)) -> 0.229 | Q53: =IF(J53="","",1-(J53-1)/20) | R53: =IF(M53="","",1-(M53-1)/(2*N53)) -> 0.9625 | S53: =IF(K53="","",0.5+0.5*PERCENTRANK($K$2:$K$85,K53)) | T53: =IF(COUNT(Q53:S53)=0,"",MAX(Q53:S53)) -> 0.9625 | U53: =COUNT(P53,T53) -> 2 | V53: YPulse 2024-02 (13-17) #2; YPulse 2024-02 (18-24) #4 | Z53: =COUNTA(V53:Y53) -> 1 | AA53: =IF(U53=0,"",MIN(1,AVERAGE(P53,T53)+Critérios!$B$5*Z53)) -> 0.62575 | AB53: =IF(AA53="","",IF(AA53>=Critérios!$B$7,"A",IF(AA53>=Critérios!$B$8,"B","C"))) -> B | AC53: =IF(AA53="","",RANK(AA53,$AA$2:$AA$85)) -> 52 | AD53: =IF(AA53="","Sairia — sem métrica",IF(PERCENTRANK($AA$2:$AA$85,AA53)<Critérios!$B$6,"Sairia — terço inferior","Fica")) -> Fica | AE53: a avaliar | AH53: candidato | AK53: tt6226232 | AL53: =COUNT(G53)+IF(OR(I53<>"",K53<>""),1,0)+IF(M53<>"",1,0)+COUNTA(V53:Y53) -> 3 | AM53: =IF(AL53>=3,"Sim","Não") -> Sim | AN53: =IF(AND(AC53<>"",AC53<=Critérios!$B$9),"Sim","Não") -> Não
A54: S0053 | B54: Heroes | C54: Heroes | D54: 2006 | E54: NBC | F54: Curadoria | G54: 267015 | H54: 7.5 | M54: 22 | N54: 40 | O54: 2006-07 #23; 2007-08 #22 | P54: =IF(G54="","",PERCENTRANK($G$2:$G$85,G54)) -> 0.41 | Q54: =IF(J54="","",1-(J54-1)/20) | R54: =IF(M54="","",1-(M54-1)/(2*N54)) -> 0.7375 | S54: =IF(K54="","",0.5+0.5*PERCENTRANK($K$2:$K$85,K54)) | T54: =IF(COUNT(Q54:S54)=0,"",MAX(Q54:S54)) -> 0.7375 | U54: =COUNT(P54,T54) -> 2 | Y54: #120 hoje | Z54: =COUNTA(V54:Y54) -> 1 | AA54: =IF(U54=0,"",MIN(1,AVERAGE(P54,T54)+Critérios!$B$5*Z54)) -> 0.60375 | AB54: =IF(AA54="","",IF(AA54>=Critérios!$B$7,"A",IF(AA54>=Critérios!$B$8,"B","C"))) -> B | AC54: =IF(AA54="","",RANK(AA54,$AA$2:$AA$85)) -> 53 | AD54: =IF(AA54="","Sairia — sem métrica",IF(PERCENTRANK($AA$2:$AA$85,AA54)<Critérios!$B$6,"Sairia — terço inferior","Fica")) -> Fica | AE54: coral/antologia | AG54: conferir ano e título no Brasil | AH54: candidato | AK54: tt0813715 | AL54: =COUNT(G54)+IF(OR(I54<>"",K54<>""),1,0)+IF(M54<>"",1,0)+COUNTA(V54:Y54) -> 3 | AM54: =IF(AL54>=3,"Sim","Não") -> Sim | AN54: =IF(AND(AC54<>"",AC54<=Critérios!$B$9),"Sim","Não") -> Não
A55: S0054 | B55: Outer Banks | C55: Outer Banks | D55: 2020 | E55: Netflix | F55: Curadoria | G55: 115724 | H55: 7.5 | M55: 9 | N55: 30 | O55: 2021 #11; 2023 #9 | P55: =IF(G55="","",PERCENTRANK($G$2:$G$85,G55)) -> 0.193 | Q55: =IF(J55="","",1-(J55-1)/20) | R55: =IF(M55="","",1-(M55-1)/(2*N55)) -> 0.86666667 | S55: =IF(K55="","",0.5+0.5*PERCENTRANK($K$2:$K$85,K55)) | T55: =IF(COUNT(Q55:S55)=0,"",MAX(Q55:S55)) -> 0.86666667 | U55: =COUNT(P55,T55) -> 2 | V55: YPulse Media Consumption Monitor 2022-10 (Gen Z (faixa não explicitada; amostra 13-39)) #4; YPulse 2023-04 (Gen Z (faixa não explicitada)) #1; YPulse 2025-02 (Gen Z (faixa não explicitada)); YPulse 2020-05 (Gen Z (subgrupos 13-18 e 19-25 só em imagem)) #1 | Y55: #69 hoje | Z55: =COUNTA(V55:Y55) -> 2 | AA55: =IF(U55=0,"",MIN(1,AVERAGE(P55,T55)+Critérios!$B$5*Z55)) -> 0.58983333 | AB55: =IF(AA55="","",IF(AA55>=Critérios!$B$7,"A",IF(AA55>=Critérios!$B$8,"B","C"))) -> B | AC55: =IF(AA55="","",RANK(AA55,$AA$2:$AA$85)) -> 54 | AD55: =IF(AA55="","Sairia — sem métrica",IF(PERCENTRANK($AA$2:$AA$85,AA55)<Critérios!$B$6,"Sairia — terço inferior","Fica")) -> Fica | AE55: claro | AG55: conferir ano e título no Brasil | AH55: candidato | AK55: tt10293938 | AL55: =COUNT(G55)+IF(OR(I55<>"",K55<>""),1,0)+IF(M55<>"",1,0)+COUNTA(V55:Y55) -> 4 | AM55: =IF(AL55>=3,"Sim","Não") -> Sim | AN55: =IF(AND(AC55<>"",AC55<=Critérios!$B$9),"Sim","Não") -> Não
A56: S0055 | B56: Bob's Burgers | C56: Bob's Burgers | D56: 2011 | F56: Adicionado por: Nielsen | G56: 104033 | H56: 8.2 | M56: 4 | N56: 30 | O56: 2024 #4; 2025 #6 | P56: =IF(G56="","",PERCENTRANK($G$2:$G$85,G56)) -> 0.169 | Q56: =IF(J56="","",1-(J56-1)/20) | R56: =IF(M56="","",1-(M56-1)/(2*N56)) -> 0.95 | S56: =IF(K56="","",0.5+0.5*PERCENTRANK($K$2:$K$85,K56)) | T56: =IF(COUNT(Q56:S56)=0,"",MAX(Q56:S56)) -> 0.95 | U56: =COUNT(P56,T56) -> 2 | V56: YPulse 2024-02 (13-17) #8 | Z56: =COUNTA(V56:Y56) -> 1 | AA56: =IF(U56=0,"",MIN(1,AVERAGE(P56,T56)+Critérios!$B$5*Z56)) -> 0.5895 | AB56: =IF(AA56="","",IF(AA56>=Critérios!$B$7,"A",IF(AA56>=Critérios!$B$8,"B","C"))) -> B | AC56: =IF(AA56="","",RANK(AA56,$AA$2:$AA$85)) -> 55 | AD56: =IF(AA56="","Sairia — sem métrica",IF(PERCENTRANK($AA$2:$AA$85,AA56)<Critérios!$B$6,"Sairia — terço inferior","Fica")) -> Fica | AE56: a avaliar | AH56: candidato | AK56: tt1561755 | AL56: =COUNT(G56)+IF(OR(I56<>"",K56<>""),1,0)+IF(M56<>"",1,0)+COUNTA(V56:Y56) -> 3 | AM56: =IF(AL56>=3,"Sim","Não") -> Sim | AN56: =IF(AND(AC56<>"",AC56<=Critérios!$B$9),"Sim","Não") -> Não
A57: S0056 | B57: Avatar: A Lenda de Aang | C57: Avatar: The Last Airbender | D57: 2005 | E57: Nickelodeon | F57: Audiência oficial (coleta) | G57: 458130 | H57: 9.3 | K57: 1100000 | P57: =IF(G57="","",PERCENTRANK($G$2:$G$85,G57)) -> 0.602 | Q57: =IF(J57="","",1-(J57-1)/20) | R57: =IF(M57="","",1-(M57-1)/(2*N57)) | S57: =IF(K57="","",0.5+0.5*PERCENTRANK($K$2:$K$85,K57)) -> 0.5 | T57: =IF(COUNT(Q57:S57)=0,"",MAX(Q57:S57)) -> 0.5 | U57: =COUNT(P57,T57) -> 2 | X57: semana encerrada 17 mar 2024 #8 (United States) | Z57: =COUNTA(V57:Y57) -> 1 | AA57: =IF(U57=0,"",MIN(1,AVERAGE(P57,T57)+Critérios!$B$5*Z57)) -> 0.581 | AB57: =IF(AA57="","",IF(AA57>=Critérios!$B$7,"A",IF(AA57>=Critérios!$B$8,"B","C"))) -> B | AC57: =IF(AA57="","",RANK(AA57,$AA$2:$AA$85)) -> 56 | AD57: =IF(AA57="","Sairia — sem métrica",IF(PERCENTRANK($AA$2:$AA$85,AA57)<Critérios!$B$6,"Sairia — terço inferior","Fica")) -> Fica | AE57: claro | AH57: candidato | AJ57: S002 | AK57: tt0417299 | AL57: =COUNT(G57)+IF(OR(I57<>"",K57<>""),1,0)+IF(M57<>"",1,0)+COUNTA(V57:Y57) -> 3 | AM57: =IF(AL57>=3,"Sim","Não") -> Sim | AN57: =IF(AND(AC57<>"",AC57<=Critérios!$B$9),"Sim","Não") -> Não
A58: S0057 | B58: The Flash | C58: The Flash | D58: 2014 | E58: The CW | F58: Curadoria | G58: 389361 | H58: 7.4 | P58: =IF(G58="","",PERCENTRANK($G$2:$G$85,G58)) -> 0.53 | Q58: =IF(J58="","",1-(J58-1)/20) | R58: =IF(M58="","",1-(M58-1)/(2*N58)) | S58: =IF(K58="","",0.5+0.5*PERCENTRANK($K$2:$K$85,K58)) | T58: =IF(COUNT(Q58:S58)=0,"",MAX(Q58:S58)) | U58: =COUNT(P58,T58) -> 1 | V58: YPulse 2016-09 (teens (13-17 presumido; amostra 13-33)) | Z58: =COUNTA(V58:Y58) -> 1 | AA58: =IF(U58=0,"",MIN(1,AVERAGE(P58,T58)+Critérios!$B$5*Z58)) -> 0.56 | AB58: =IF(AA58="","",IF(AA58>=Critérios!$B$7,"A",IF(AA58>=Critérios!$B$8,"B","C"))) -> B | AC58: =IF(AA58="","",RANK(AA58,$AA$2:$AA$85)) -> 57 | AD58: =IF(AA58="","Sairia — sem métrica",IF(PERCENTRANK($AA$2:$AA$85,AA58)<Critérios!$B$6,"Sairia — terço inferior","Fica")) -> Sairia — terço inferior | AE58: claro | AG58: conferir ano e título no Brasil | AH58: candidato | AK58: tt3107288 | AL58: =COUNT(G58)+IF(OR(I58<>"",K58<>""),1,0)+IF(M58<>"",1,0)+COUNTA(V58:Y58) -> 2 | AM58: =IF(AL58>=3,"Sim","Não") -> Não | AN58: =IF(AND(AC58<>"",AC58<=Critérios!$B$9),"Sim","Não") -> Não
A59: S0058 | B59: Amigos | C59: Friends | D59: 2002 | F59: Adicionado por: Nielsen | G59: 251 | H59: 7.7 | M59: 1 | N59: 40 | O59: 2001-02 #1; 2002-03 #2; 2003-04 #4; 2022 #11; 2023 #8 | P59: =IF(G59="","",PERCENTRANK($G$2:$G$85,G59)) -> 0 | Q59: =IF(J59="","",1-(J59-1)/20) | R59: =IF(M59="","",1-(M59-1)/(2*N59)) -> 1 | S59: =IF(K59="","",0.5+0.5*PERCENTRANK($K$2:$K$85,K59)) | T59: =IF(COUNT(Q59:S59)=0,"",MAX(Q59:S59)) -> 1 | U59: =COUNT(P59,T59) -> 2 | V59: UCLA Teens & Screens 2025 (top 25) 2025-10 (10-24) | Y59: #102 hoje | Z59: =COUNTA(V59:Y59) -> 2 | AA59: =IF(U59=0,"",MIN(1,AVERAGE(P59,T59)+Critérios!$B$5*Z59)) -> 0.56 | AB59: =IF(AA59="","",IF(AA59>=Critérios!$B$7,"A",IF(AA59>=Critérios!$B$8,"B","C"))) -> B | AC59: =IF(AA59="","",RANK(AA59,$AA$2:$AA$85)) -> 57 | AD59: =IF(AA59="","Sairia — sem métrica",IF(PERCENTRANK($AA$2:$AA$85,AA59)<Critérios!$B$6,"Sairia — terço inferior","Fica")) -> Sairia — terço inferior | AE59: a avaliar | AH59: candidato | AK59: tt0315608 | AL59: =COUNT(G59)+IF(OR(I59<>"",K59<>""),1,0)+IF(M59<>"",1,0)+COUNTA(V59:Y59) -> 4 | AM59: =IF(AL59>=3,"Sim","Não") -> Sim | AN59: =IF(AND(AC59<>"",AC59<=Critérios!$B$9),"Sim","Não") -> Não
A60: S0059 | B60: American Horror Story | C60: American Horror Story | D60: 2011 | E60: FX | F60: Curadoria | G60: 367169 | H60: 7.9 | P60: =IF(G60="","",PERCENTRANK($G$2:$G$85,G60)) -> 0.494 | Q60: =IF(J60="","",1-(J60-1)/20) | R60: =IF(M60="","",1-(M60-1)/(2*N60)) | S60: =IF(K60="","",0.5+0.5*PERCENTRANK($K$2:$K$85,K60)) | T60: =IF(COUNT(Q60:S60)=0,"",MAX(Q60:S60)) | U60: =COUNT(P60,T60) -> 1 | W60: 2023 (ano) | Y60: #13 hoje | Z60: =COUNTA(V60:Y60) -> 2 | AA60: =IF(U60=0,"",MIN(1,AVERAGE(P60,T60)+Critérios!$B$5*Z60)) -> 0.554 | AB60: =IF(AA60="","",IF(AA60>=Critérios!$B$7,"A",IF(AA60>=Critérios!$B$8,"B","C"))) -> B | AC60: =IF(AA60="","",RANK(AA60,$AA$2:$AA$85)) -> 59 | AD60: =IF(AA60="","Sairia — sem métrica",IF(PERCENTRANK($AA$2:$AA$85,AA60)<Critérios!$B$6,"Sairia — terço inferior","Fica")) -> Sairia — terço inferior | AE60: coral/antologia | AF60: Classificação alta — pistas suaves | AG60: conferir ano e título no Brasil | AH60: candidato | AK60: tt1844624 | AL60: =COUNT(G60)+IF(OR(I60<>"",K60<>""),1,0)+IF(M60<>"",1,0)+COUNTA(V60:Y60) -> 3 | AM60: =IF(AL60>=3,"Sim","Não") -> Sim | AN60: =IF(AND(AC60<>"",AC60<=Critérios!$B$9),"Sim","Não") -> Não
A61: S0060 | B61: Virgin River | C61: Virgin River | D61: 2019 | F61: Adicionado por: Nielsen | G61: 60786 | H61: 7.4 | M61: 4 | N61: 30 | O61: 2021 #4; 2022 #6; 2023 #4 | P61: =IF(G61="","",PERCENTRANK($G$2:$G$85,G61)) -> 0.0964 | Q61: =IF(J61="","",1-(J61-1)/20) | R61: =IF(M61="","",1-(M61-1)/(2*N61)) -> 0.95 | S61: =IF(K61="","",0.5+0.5*PERCENTRANK($K$2:$K$85,K61)) | T61: =IF(COUNT(Q61:S61)=0,"",MAX(Q61:S61)) -> 0.95 | U61: =COUNT(P61,T61) -> 2 | X61: semana encerrada 24 jul 2022 #1 (United States); semana encerrada 14 ago 2022 #7 (United States) | Z61: =COUNTA(V61:Y61) -> 1 | AA61: =IF(U61=0,"",MIN(1,AVERAGE(P61,T61)+Critérios!$B$5*Z61)) -> 0.5532 | AB61: =IF(AA61="","",IF(AA61>=Critérios!$B$7,"A",IF(AA61>=Critérios!$B$8,"B","C"))) -> B | AC61: =IF(AA61="","",RANK(AA61,$AA$2:$AA$85)) -> 60 | AD61: =IF(AA61="","Sairia — sem métrica",IF(PERCENTRANK($AA$2:$AA$85,AA61)<Critérios!$B$6,"Sairia — terço inferior","Fica")) -> Sairia — terço inferior | AE61: a avaliar | AH61: candidato | AK61: tt9077530 | AL61: =COUNT(G61)+IF(OR(I61<>"",K61<>""),1,0)+IF(M61<>"",1,0)+COUNTA(V61:Y61) -> 3 | AM61: =IF(AL61>=3,"Sim","Não") -> Sim | AN61: =IF(AND(AC61<>"",AC61<=Critérios!$B$9),"Sim","Não") -> Não
A62: S0061 | B62: O Último Reino | C62: The Last Kingdom | D62: 2015 | F62: Adicionado por: Nielsen | G62: 193644 | H62: 8.5 | M62: 14 | N62: 30 | O62: 2022 #14 | P62: =IF(G62="","",PERCENTRANK($G$2:$G$85,G62)) -> 0.253 | Q62: =IF(J62="","",1-(J62-1)/20) | R62: =IF(M62="","",1-(M62-1)/(2*N62)) -> 0.78333333 | S62: =IF(K62="","",0.5+0.5*PERCENTRANK($K$2:$K$85,K62)) | T62: =IF(COUNT(Q62:S62)=0,"",MAX(Q62:S62)) -> 0.78333333 | U62: =COUNT(P62,T62) -> 2 | X62: semana encerrada 20 mar 2022 #2 (United States) | Z62: =COUNTA(V62:Y62) -> 1 | AA62: =IF(U62=0,"",MIN(1,AVERAGE(P62,T62)+Critérios!$B$5*Z62)) -> 0.54816667 | AB62: =IF(AA62="","",IF(AA62>=Critérios!$B$7,"A",IF(AA62>=Critérios!$B$8,"B","C"))) -> B | AC62: =IF(AA62="","",RANK(AA62,$AA$2:$AA$85)) -> 61 | AD62: =IF(AA62="","Sairia — sem métrica",IF(PERCENTRANK($AA$2:$AA$85,AA62)<Critérios!$B$6,"Sairia — terço inferior","Fica")) -> Sairia — terço inferior | AE62: a avaliar | AH62: candidato | AK62: tt4179452 | AL62: =COUNT(G62)+IF(OR(I62<>"",K62<>""),1,0)+IF(M62<>"",1,0)+COUNTA(V62:Y62) -> 3 | AM62: =IF(AL62>=3,"Sim","Não") -> Sim | AN62: =IF(AND(AC62<>"",AC62<=Critérios!$B$9),"Sim","Não") -> Não
A63: S0062 | B63: Bluey | C63: Bluey | D63: 2018 | F63: Adicionado por: Nielsen | G63: 49680 | H63: 9.2 | M63: 1 | N63: 30 | O63: 2022 #8; 2022 #5; 2023 #2; 2024 #1; 2025 #1 | P63: =IF(G63="","",PERCENTRANK($G$2:$G$85,G63)) -> 0.0241 | Q63: =IF(J63="","",1-(J63-1)/20) | R63: =IF(M63="","",1-(M63-1)/(2*N63)) -> 1 | S63: =IF(K63="","",0.5+0.5*PERCENTRANK($K$2:$K$85,K63)) | T63: =IF(COUNT(Q63:S63)=0,"",MAX(Q63:S63)) -> 1 | U63: =COUNT(P63,T63) -> 2 | V63: YPulse 2025-02 (Gen Z (faixa não explicitada)) | Z63: =COUNTA(V63:Y63) -> 1 | AA63: =IF(U63=0,"",MIN(1,AVERAGE(P63,T63)+Critérios!$B$5*Z63)) -> 0.54205 | AB63: =IF(AA63="","",IF(AA63>=Critérios!$B$7,"A",IF(AA63>=Critérios!$B$8,"B","C"))) -> B | AC63: =IF(AA63="","",RANK(AA63,$AA$2:$AA$85)) -> 62 | AD63: =IF(AA63="","Sairia — sem métrica",IF(PERCENTRANK($AA$2:$AA$85,AA63)<Critérios!$B$6,"Sairia — terço inferior","Fica")) -> Sairia — terço inferior | AE63: a avaliar | AH63: candidato | AK63: tt7678620 | AL63: =COUNT(G63)+IF(OR(I63<>"",K63<>""),1,0)+IF(M63<>"",1,0)+COUNTA(V63:Y63) -> 3 | AM63: =IF(AL63>=3,"Sim","Não") -> Sim | AN63: =IF(AND(AC63<>"",AC63<=Critérios!$B$9),"Sim","Não") -> Não
A64: S0063 | B64: Inventando Anna | C64: Inventing Anna | D64: 2022 | F64: Adicionado por: Nielsen | G64: 91807 | H64: 6.9 | M64: 9 | N64: 30 | O64: 2022 #9 | P64: =IF(G64="","",PERCENTRANK($G$2:$G$85,G64)) -> 0.145 | Q64: =IF(J64="","",1-(J64-1)/20) | R64: =IF(M64="","",1-(M64-1)/(2*N64)) -> 0.86666667 | S64: =IF(K64="","",0.5+0.5*PERCENTRANK($K$2:$K$85,K64)) | T64: =IF(COUNT(Q64:S64)=0,"",MAX(Q64:S64)) -> 0.86666667 | U64: =COUNT(P64,T64) -> 2 | X64: semana encerrada 20 fev 2022 #3 (United States); semana encerrada 6 mar 2022 #6 (United States) | Z64: =COUNTA(V64:Y64) -> 1 | AA64: =IF(U64=0,"",MIN(1,AVERAGE(P64,T64)+Critérios!$B$5*Z64)) -> 0.53583333 | AB64: =IF(AA64="","",IF(AA64>=Critérios!$B$7,"A",IF(AA64>=Critérios!$B$8,"B","C"))) -> B | AC64: =IF(AA64="","",RANK(AA64,$AA$2:$AA$85)) -> 63 | AD64: =IF(AA64="","Sairia — sem métrica",IF(PERCENTRANK($AA$2:$AA$85,AA64)<Critérios!$B$6,"Sairia — terço inferior","Fica")) -> Sairia — terço inferior | AE64: a avaliar | AH64: candidato | AK64: tt8740976 | AL64: =COUNT(G64)+IF(OR(I64<>"",K64<>""),1,0)+IF(M64<>"",1,0)+COUNTA(V64:Y64) -> 3 | AM64: =IF(AL64>=3,"Sim","Não") -> Sim | AN64: =IF(AND(AC64<>"",AC64<=Critérios!$B$9),"Sim","Não") -> Não
A65: S0064 | B65: Maid | C65: Maid | D65: 2021 | F65: Adicionado por: Nielsen | G65: 123279 | H65: 8.3 | M65: 13 | N65: 30 | O65: 2021 #13 | P65: =IF(G65="","",PERCENTRANK($G$2:$G$85,G65)) -> 0.205 | Q65: =IF(J65="","",1-(J65-1)/20) | R65: =IF(M65="","",1-(M65-1)/(2*N65)) -> 0.8 | S65: =IF(K65="","",0.5+0.5*PERCENTRANK($K$2:$K$85,K65)) | T65: =IF(COUNT(Q65:S65)=0,"",MAX(Q65:S65)) -> 0.8 | U65: =COUNT(P65,T65) -> 2 | X65: semana 25–31 out 2021 #6 (Italy); semana 1–7 nov 2021 #5 (Spain) | Z65: =COUNTA(V65:Y65) -> 1 | AA65: =IF(U65=0,"",MIN(1,AVERAGE(P65,T65)+Critérios!$B$5*Z65)) -> 0.5325 | AB65: =IF(AA65="","",IF(AA65>=Critérios!$B$7,"A",IF(AA65>=Critérios!$B$8,"B","C"))) -> B | AC65: =IF(AA65="","",RANK(AA65,$AA$2:$AA$85)) -> 64 | AD65: =IF(AA65="","Sairia — sem métrica",IF(PERCENTRANK($AA$2:$AA$85,AA65)<Critérios!$B$6,"Sairia — terço inferior","Fica")) -> Sairia — terço inferior | AE65: a avaliar | AH65: candidato | AK65: tt11337908 | AL65: =COUNT(G65)+IF(OR(I65<>"",K65<>""),1,0)+IF(M65<>"",1,0)+COUNTA(V65:Y65) -> 3 | AM65: =IF(AL65>=3,"Sim","Não") -> Sim | AN65: =IF(AND(AC65<>"",AC65<=Critérios!$B$9),"Sim","Não") -> Não
A66: S0065 | B66: O Urso | C66: The Bear | D66: 2022 | E66: FX / Hulu | F66: Curadoria | G66: 328101 | H66: 8.5 | P66: =IF(G66="","",PERCENTRANK($G$2:$G$85,G66)) -> 0.47 | Q66: =IF(J66="","",1-(J66-1)/20) | R66: =IF(M66="","",1-(M66-1)/(2*N66)) | S66: =IF(K66="","",0.5+0.5*PERCENTRANK($K$2:$K$85,K66)) | T66: =IF(COUNT(Q66:S66)=0,"",MAX(Q66:S66)) | U66: =COUNT(P66,T66) -> 1 | X66: semana encerrada 17 jul 2022 #10 (United States); semana encerrada 24 jul 2022 #10 (United States); 1 jan–30 nov 2023 #8 (United States) | Y66: #39 hoje | Z66: =COUNTA(V66:Y66) -> 2 | AA66: =IF(U66=0,"",MIN(1,AVERAGE(P66,T66)+Critérios!$B$5*Z66)) -> 0.53 | AB66: =IF(AA66="","",IF(AA66>=Critérios!$B$7,"A",IF(AA66>=Critérios!$B$8,"B","C"))) -> B | AC66: =IF(AA66="","",RANK(AA66,$AA$2:$AA$85)) -> 65 | AD66: =IF(AA66="","Sairia — sem métrica",IF(PERCENTRANK($AA$2:$AA$85,AA66)<Critérios!$B$6,"Sairia — terço inferior","Fica")) -> Sairia — terço inferior | AE66: claro | AG66: conferir ano e título no Brasil | AH66: candidato | AK66: tt14452776 | AL66: =COUNT(G66)+IF(OR(I66<>"",K66<>""),1,0)+IF(M66<>"",1,0)+COUNTA(V66:Y66) -> 3 | AM66: =IF(AL66>=3,"Sim","Não") -> Sim | AN66: =IF(AND(AC66<>"",AC66<=Critérios!$B$9),"Sim","Não") -> Não
A67: S0066 | B67: Orange Is the New Black | C67: Orange Is the New Black | D67: 2013 | E67: Netflix | F67: Curadoria | G67: 339063 | H67: 8 | P67: =IF(G67="","",PERCENTRANK($G$2:$G$85,G67)) -> 0.482 | Q67: =IF(J67="","",1-(J67-1)/20) | R67: =IF(M67="","",1-(M67-1)/(2*N67)) | S67: =IF(K67="","",0.5+0.5*PERCENTRANK($K$2:$K$85,K67)) | T67: =IF(COUNT(Q67:S67)=0,"",MAX(Q67:S67)) | U67: =COUNT(P67,T67) -> 1 | V67: YPulse 2016-09 (teens (13-17 presumido; amostra 13-33)) | Z67: =COUNTA(V67:Y67) -> 1 | AA67: =IF(U67=0,"",MIN(1,AVERAGE(P67,T67)+Critérios!$B$5*Z67)) -> 0.512 | AB67: =IF(AA67="","",IF(AA67>=Critérios!$B$7,"A",IF(AA67>=Critérios!$B$8,"B","C"))) -> B | AC67: =IF(AA67="","",RANK(AA67,$AA$2:$AA$85)) -> 66 | AD67: =IF(AA67="","Sairia — sem métrica",IF(PERCENTRANK($AA$2:$AA$85,AA67)<Critérios!$B$6,"Sairia — terço inferior","Fica")) -> Sairia — terço inferior | AE67: claro | AF67: Classificação alta — pistas suaves | AG67: conferir ano e título no Brasil | AH67: candidato | AK67: tt2372162 | AL67: =COUNT(G67)+IF(OR(I67<>"",K67<>""),1,0)+IF(M67<>"",1,0)+COUNTA(V67:Y67) -> 2 | AM67: =IF(AL67>=3,"Sim","Não") -> Não | AN67: =IF(AND(AC67<>"",AC67<=Critérios!$B$9),"Sim","Não") -> Não
A68: S0067 | B68: Evil: Contatos Sobrenaturais | C68: Evil | D68: 2019 | F68: Adicionado por: Nielsen | G68: 53982 | H68: 7.7 | M68: 8 | N68: 30 | O68: 2024 #8 | P68: =IF(G68="","",PERCENTRANK($G$2:$G$85,G68)) -> 0.0482 | Q68: =IF(J68="","",1-(J68-1)/20) | R68: =IF(M68="","",1-(M68-1)/(2*N68)) -> 0.88333333 | S68: =IF(K68="","",0.5+0.5*PERCENTRANK($K$2:$K$85,K68)) | T68: =IF(COUNT(Q68:S68)=0,"",MAX(Q68:S68)) -> 0.88333333 | U68: =COUNT(P68,T68) -> 2 | Y68: #82 hoje | Z68: =COUNTA(V68:Y68) -> 1 | AA68: =IF(U68=0,"",MIN(1,AVERAGE(P68,T68)+Critérios!$B$5*Z68)) -> 0.49576667 | AB68: =IF(AA68="","",IF(AA68>=Critérios!$B$7,"A",IF(AA68>=Critérios!$B$8,"B","C"))) -> B | AC68: =IF(AA68="","",RANK(AA68,$AA$2:$AA$85)) -> 67 | AD68: =IF(AA68="","Sairia — sem métrica",IF(PERCENTRANK($AA$2:$AA$85,AA68)<Critérios!$B$6,"Sairia — terço inferior","Fica")) -> Sairia — terço inferior | AE68: a avaliar | AH68: candidato | AK68: tt9055008 | AL68: =COUNT(G68)+IF(OR(I68<>"",K68<>""),1,0)+IF(M68<>"",1,0)+COUNTA(V68:Y68) -> 3 | AM68: =IF(AL68>=3,"Sim","Não") -> Sim | AN68: =IF(AND(AC68<>"",AC68<=Critérios!$B$9),"Sim","Não") -> Não
A69: S0068 | C69: I Will Find You | D69: 2026 | E69: Netflix | F69: Audiência oficial (coleta) | G69: 67985 | H69: 7.1 | I69: 120800000 | J69: 5 | P69: =IF(G69="","",PERCENTRANK($G$2:$G$85,G69)) -> 0.108 | Q69: =IF(J69="","",1-(J69-1)/20) -> 0.8 | R69: =IF(M69="","",1-(M69-1)/(2*N69)) | S69: =IF(K69="","",0.5+0.5*PERCENTRANK($K$2:$K$85,K69)) | T69: =IF(COUNT(Q69:S69)=0,"",MAX(Q69:S69)) -> 0.8 | U69: =COUNT(P69,T69) -> 2 | Y69: #62 hoje | Z69: =COUNTA(V69:Y69) -> 1 | AA69: =IF(U69=0,"",MIN(1,AVERAGE(P69,T69)+Critérios!$B$5*Z69)) -> 0.484 | AB69: =IF(AA69="","",IF(AA69>=Critérios!$B$7,"A",IF(AA69>=Critérios!$B$8,"B","C"))) -> B | AC69: =IF(AA69="","",RANK(AA69,$AA$2:$AA$85)) -> 68 | AD69: =IF(AA69="","Sairia — sem métrica",IF(PERCENTRANK($AA$2:$AA$85,AA69)<Critérios!$B$6,"Sairia — terço inferior","Fica")) -> Sairia — terço inferior | AE69: a avaliar | AG69: conferir ano e título no Brasil | AH69: candidato | AJ69: S030 | AK69: tt34771210 | AL69: =COUNT(G69)+IF(OR(I69<>"",K69<>""),1,0)+IF(M69<>"",1,0)+COUNTA(V69:Y69) -> 3 | AM69: =IF(AL69>=3,"Sim","Não") -> Sim | AN69: =IF(AND(AC69<>"",AC69<=Critérios!$B$9),"Sim","Não") -> Não
A70: S0069 | B70: Gossip Girl: A Garota do Blog | C70: Gossip Girl | D70: 2007 | E70: The CW | F70: Audiência oficial (coleta) | G70: 218059 | H70: 7.5 | K70: 2800000 | P70: =IF(G70="","",PERCENTRANK($G$2:$G$85,G70)) -> 0.325 | Q70: =IF(J70="","",1-(J70-1)/20) | R70: =IF(M70="","",1-(M70-1)/(2*N70)) | S70: =IF(K70="","",0.5+0.5*PERCENTRANK($K$2:$K$85,K70)) -> 0.5625 | T70: =IF(COUNT(Q70:S70)=0,"",MAX(Q70:S70)) -> 0.5625 | U70: =COUNT(P70,T70) -> 2 | X70: semana 29 nov–5 dez 2021 #9 (Spain) | Z70: =COUNTA(V70:Y70) -> 1 | AA70: =IF(U70=0,"",MIN(1,AVERAGE(P70,T70)+Critérios!$B$5*Z70)) -> 0.47375 | AB70: =IF(AA70="","",IF(AA70>=Critérios!$B$7,"A",IF(AA70>=Critérios!$B$8,"B","C"))) -> B | AC70: =IF(AA70="","",RANK(AA70,$AA$2:$AA$85)) -> 69 | AD70: =IF(AA70="","Sairia — sem métrica",IF(PERCENTRANK($AA$2:$AA$85,AA70)<Critérios!$B$6,"Sairia — terço inferior","Fica")) -> Sairia — terço inferior | AE70: dupla | AH70: candidato | AJ70: S014 | AK70: tt0397442 | AL70: =COUNT(G70)+IF(OR(I70<>"",K70<>""),1,0)+IF(M70<>"",1,0)+COUNTA(V70:Y70) -> 3 | AM70: =IF(AL70>=3,"Sim","Não") -> Sim | AN70: =IF(AND(AC70<>"",AC70<=Critérios!$B$9),"Sim","Não") -> Não
A71: S0070 | B71: Gavião Arqueiro | C71: Hawkeye | D71: 2021 | F71: Adicionado por: Parrot Analytics (Brasil) | G71: 250051 | H71: 7.4 | P71: =IF(G71="","",PERCENTRANK($G$2:$G$85,G71)) -> 0.386 | Q71: =IF(J71="","",1-(J71-1)/20) | R71: =IF(M71="","",1-(M71-1)/(2*N71)) | S71: =IF(K71="","",0.5+0.5*PERCENTRANK($K$2:$K$85,K71)) | T71: =IF(COUNT(Q71:S71)=0,"",MAX(Q71:S71)) | U71: =COUNT(P71,T71) -> 1 | W71: fev 2022 | X71: semana 22–28 nov 2021 #2 (Italy); semana 29 nov–5 dez 2021 #2 (Spain); semana 22–28 nov 2021 #1 (United States) | Z71: =COUNTA(V71:Y71) -> 2 | AA71: =IF(U71=0,"",MIN(1,AVERAGE(P71,T71)+Critérios!$B$5*Z71)) -> 0.446 | AB71: =IF(AA71="","",IF(AA71>=Critérios!$B$7,"A",IF(AA71>=Critérios!$B$8,"B","C"))) -> B | AC71: =IF(AA71="","",RANK(AA71,$AA$2:$AA$85)) -> 70 | AD71: =IF(AA71="","Sairia — sem métrica",IF(PERCENTRANK($AA$2:$AA$85,AA71)<Critérios!$B$6,"Sairia — terço inferior","Fica")) -> Sairia — terço inferior | AE71: a avaliar | AH71: candidato | AK71: tt10160804 | AL71: =COUNT(G71)+IF(OR(I71<>"",K71<>""),1,0)+IF(M71<>"",1,0)+COUNTA(V71:Y71) -> 3 | AM71: =IF(AL71>=3,"Sim","Não") -> Sim | AN71: =IF(AND(AC71<>"",AC71<=Critérios!$B$9),"Sim","Não") -> Não
A72: S0071 | B72: Silo | C72: Silo | D72: 2023 | F72: Adicionado por: Whip Media | G72: 249014 | H72: 8.1 | P72: =IF(G72="","",PERCENTRANK($G$2:$G$85,G72)) -> 0.373 | Q72: =IF(J72="","",1-(J72-1)/20) | R72: =IF(M72="","",1-(M72-1)/(2*N72)) | S72: =IF(K72="","",0.5+0.5*PERCENTRANK($K$2:$K$85,K72)) | T72: =IF(COUNT(Q72:S72)=0,"",MAX(Q72:S72)) | U72: =COUNT(P72,T72) -> 1 | X72: 1 jan–30 nov 2023 #15 (United States) | Y72: #10 hoje | Z72: =COUNTA(V72:Y72) -> 2 | AA72: =IF(U72=0,"",MIN(1,AVERAGE(P72,T72)+Critérios!$B$5*Z72)) -> 0.433 | AB72: =IF(AA72="","",IF(AA72>=Critérios!$B$7,"A",IF(AA72>=Critérios!$B$8,"B","C"))) -> B | AC72: =IF(AA72="","",RANK(AA72,$AA$2:$AA$85)) -> 71 | AD72: =IF(AA72="","Sairia — sem métrica",IF(PERCENTRANK($AA$2:$AA$85,AA72)<Critérios!$B$6,"Sairia — terço inferior","Fica")) -> Sairia — terço inferior | AE72: a avaliar | AH72: candidato | AK72: tt14688458 | AL72: =COUNT(G72)+IF(OR(I72<>"",K72<>""),1,0)+IF(M72<>"",1,0)+COUNTA(V72:Y72) -> 3 | AM72: =IF(AL72>=3,"Sim","Não") -> Sim | AN72: =IF(AND(AC72<>"",AC72<=Critérios!$B$9),"Sim","Não") -> Não
A73: S0072 | B73: SEAL Team: Soldados de Elite | C73: SEAL Team | D73: 2017 | F73: Adicionado por: Nielsen | G73: 42270 | H73: 7.9 | M73: 23 | N73: 40 | O73: 2017-18 #23 | P73: =IF(G73="","",PERCENTRANK($G$2:$G$85,G73)) -> 0.012 | Q73: =IF(J73="","",1-(J73-1)/20) | R73: =IF(M73="","",1-(M73-1)/(2*N73)) -> 0.725 | S73: =IF(K73="","",0.5+0.5*PERCENTRANK($K$2:$K$85,K73)) | T73: =IF(COUNT(Q73:S73)=0,"",MAX(Q73:S73)) -> 0.725 | U73: =COUNT(P73,T73) -> 2 | Y73: #53 hoje | Z73: =COUNTA(V73:Y73) -> 1 | AA73: =IF(U73=0,"",MIN(1,AVERAGE(P73,T73)+Critérios!$B$5*Z73)) -> 0.3985 | AB73: =IF(AA73="","",IF(AA73>=Critérios!$B$7,"A",IF(AA73>=Critérios!$B$8,"B","C"))) -> C | AC73: =IF(AA73="","",RANK(AA73,$AA$2:$AA$85)) -> 72 | AD73: =IF(AA73="","Sairia — sem métrica",IF(PERCENTRANK($AA$2:$AA$85,AA73)<Critérios!$B$6,"Sairia — terço inferior","Fica")) -> Sairia — terço inferior | AE73: a avaliar | AH73: candidato | AK73: tt6473344 | AL73: =COUNT(G73)+IF(OR(I73<>"",K73<>""),1,0)+IF(M73<>"",1,0)+COUNTA(V73:Y73) -> 3 | AM73: =IF(AL73>=3,"Sim","Não") -> Sim | AN73: =IF(AND(AC73<>"",AC73<=Critérios!$B$9),"Sim","Não") -> Não
A74: S0073 | B74: O Livro de Boba Fett | C74: The Book of Boba Fett | D74: 2021 | F74: Adicionado por: Parrot Analytics (Brasil) | G74: 213895 | H74: 7.1 | P74: =IF(G74="","",PERCENTRANK($G$2:$G$85,G74)) -> 0.301 | Q74: =IF(J74="","",1-(J74-1)/20) | R74: =IF(M74="","",1-(M74-1)/(2*N74)) | S74: =IF(K74="","",0.5+0.5*PERCENTRANK($K$2:$K$85,K74)) | T74: =IF(COUNT(Q74:S74)=0,"",MAX(Q74:S74)) | U74: =COUNT(P74,T74) -> 1 | W74: fev 2022 #1 | X74: semana 17–23 jan 2022 #1 (Germany); semana 3–9 jan 2022 #3 (United States); semana 17–23 jan 2022 #2 (United States) | Z74: =COUNTA(V74:Y74) -> 2 | AA74: =IF(U74=0,"",MIN(1,AVERAGE(P74,T74)+Critérios!$B$5*Z74)) -> 0.361 | AB74: =IF(AA74="","",IF(AA74>=Critérios!$B$7,"A",IF(AA74>=Critérios!$B$8,"B","C"))) -> C | AC74: =IF(AA74="","",RANK(AA74,$AA$2:$AA$85)) -> 73 | AD74: =IF(AA74="","Sairia — sem métrica",IF(PERCENTRANK($AA$2:$AA$85,AA74)<Critérios!$B$6,"Sairia — terço inferior","Fica")) -> Sairia — terço inferior | AE74: a avaliar | AH74: candidato | AK74: tt13668894 | AL74: =COUNT(G74)+IF(OR(I74<>"",K74<>""),1,0)+IF(M74<>"",1,0)+COUNTA(V74:Y74) -> 3 | AM74: =IF(AL74>=3,"Sim","Não") -> Sim | AN74: =IF(AND(AC74<>"",AC74<=Critérios!$B$9),"Sim","Não") -> Não
A75: S0074 | B75: Magnatas do Crime | C75: The Gentlemen | D75: 2024 | F75: Adicionado por: Whip Media | G75: 208635 | H75: 8.1 | P75: =IF(G75="","",PERCENTRANK($G$2:$G$85,G75)) -> 0.289 | Q75: =IF(J75="","",1-(J75-1)/20) | R75: =IF(M75="","",1-(M75-1)/(2*N75)) | S75: =IF(K75="","",0.5+0.5*PERCENTRANK($K$2:$K$85,K75)) | T75: =IF(COUNT(Q75:S75)=0,"",MAX(Q75:S75)) | U75: =COUNT(P75,T75) -> 1 | X75: semana encerrada 17 mar 2024 #6 (United States) | Y75: #16 hoje | Z75: =COUNTA(V75:Y75) -> 2 | AA75: =IF(U75=0,"",MIN(1,AVERAGE(P75,T75)+Critérios!$B$5*Z75)) -> 0.349 | AB75: =IF(AA75="","",IF(AA75>=Critérios!$B$7,"A",IF(AA75>=Critérios!$B$8,"B","C"))) -> C | AC75: =IF(AA75="","",RANK(AA75,$AA$2:$AA$85)) -> 74 | AD75: =IF(AA75="","Sairia — sem métrica",IF(PERCENTRANK($AA$2:$AA$85,AA75)<Critérios!$B$6,"Sairia — terço inferior","Fica")) -> Sairia — terço inferior | AE75: a avaliar | AH75: candidato | AK75: tt13210838 | AL75: =COUNT(G75)+IF(OR(I75<>"",K75<>""),1,0)+IF(M75<>"",1,0)+COUNTA(V75:Y75) -> 3 | AM75: =IF(AL75>=3,"Sim","Não") -> Sim | AN75: =IF(AND(AC75<>"",AC75<=Critérios!$B$9),"Sim","Não") -> Não
A76: S0075 | B76: Pacificador | C76: Peacemaker | D76: 2022 | F76: Adicionado por: Parrot Analytics (Brasil) | G76: 200903 | H76: 8.2 | P76: =IF(G76="","",PERCENTRANK($G$2:$G$85,G76)) -> 0.277 | Q76: =IF(J76="","",1-(J76-1)/20) | R76: =IF(M76="","",1-(M76-1)/(2*N76)) | S76: =IF(K76="","",0.5+0.5*PERCENTRANK($K$2:$K$85,K76)) | T76: =IF(COUNT(Q76:S76)=0,"",MAX(Q76:S76)) | U76: =COUNT(P76,T76) -> 1 | W76: fev 2022 #3 | X76: semana 17–23 jan 2022 #3 (United States); semana encerrada 20 fev 2022 #2 (United States) | Z76: =COUNTA(V76:Y76) -> 2 | AA76: =IF(U76=0,"",MIN(1,AVERAGE(P76,T76)+Critérios!$B$5*Z76)) -> 0.337 | AB76: =IF(AA76="","",IF(AA76>=Critérios!$B$7,"A",IF(AA76>=Critérios!$B$8,"B","C"))) -> C | AC76: =IF(AA76="","",RANK(AA76,$AA$2:$AA$85)) -> 75 | AD76: =IF(AA76="","Sairia — sem métrica",IF(PERCENTRANK($AA$2:$AA$85,AA76)<Critérios!$B$6,"Sairia — terço inferior","Fica")) -> Sairia — terço inferior | AE76: a avaliar | AH76: candidato | AK76: tt13146488 | AL76: =COUNT(G76)+IF(OR(I76<>"",K76<>""),1,0)+IF(M76<>"",1,0)+COUNTA(V76:Y76) -> 3 | AM76: =IF(AL76>=3,"Sim","Não") -> Sim | AN76: =IF(AND(AC76<>"",AC76<=Critérios!$B$9),"Sim","Não") -> Não
